Workbook

Sheet User Guide
A1: 📘 USER GUIDE — Singapore Property Leverage Optimizer
B3: WHAT THIS WORKBOOK DOES
B4: This workbook helps you decide whether to buy property in Singapore — and which type — by comparing 6 property scenarios against a pure investment portfolio ("No Property" benchmark). It models a 20-year horizon and accounts for:
B5: • Mortgage leverage (75% LTV) with SORA-based interest rates
B6: • Leasehold decay using SLA Bala’s Table (critical for HDB & 99-year condos)
B7: • CPF OA usage and accrued interest you must repay on sale
B8: • Transaction costs (BSD, ABSD, legal fees, agent fees)
B9: • Imputed rent savings (owner-occupied) or rental income (investment mode)
B10: • Opportunity cost: what your cash would have grown to in a 60/40 portfolio instead
B11: • Interest rate stress testing (Base / Stress / Severe SORA scenarios)
B13: The 6 property types compared:
B14: 1. HDB 1984 — Older resale HDB (57-year lease remaining), lowest entry cost but highest lease decay risk
B15: 2. HDB 2005 — Mid-age resale HDB (78-year lease), moderate decay
... B23: Change values in the Assumptions sheet and the entire model recalculates automatically across all 14 sheets.
A25: STEP 1 | B25: Enter Your Investor Profile (Assumptions sheet, rows 4–10) | E25: Your Value ✏️
B26: Cell | C26: What to Enter | D26: Guidance | E26: ← Type here (auto-syncs to model)
B27: Assumptions!C4 | C27: Your current age (e.g., 32) | D27: This determines your exit age. Exit Age = Current Age + Analysis Horizon. | E27: 32
B28: Assumptions!C5 | C28: Analysis horizon in years (e.g., 30) | D28: How many years to project. The property sheets show 20-year detail; this sets the overall planning window. | E28: 30
B29: Assumptions!C7 | C29: Your total net worth in SGD (e.g., 800,000) | D29: Include all liquid savings + CPF OA. This is the total capital pool the model allocates between property and investments. | E29: 800000
B30: Assumptions!C8 | C30: Your CPF OA balance (e.g., 150,000) | D30: Amount of CPF OA you will use for the downpayment. Must be ≤ Total Net Worth. CPF accrued interest (2.5%) must be repaid when you sell. | E30: 150000
B31: Assumptions!C9 | C31: CPF OA interest rate (default 2.5%) | D31: Currently 2.5% p.a. from CPF Board. Only change if policy changes. | E31: 0.025
B32: Assumptions!C10 | C32: Residency status (DROPDOWN) | D32: Choose: "SC 1st Property" (0% ABSD), "SC 2nd Property" (20% ABSD), or "PR" (5% ABSD). This changes ABSD across all properties. | E32: SC 1st Property
C33: → C6 (Exit Age) is auto-calculated. Do NOT type in it.
A35: STEP 2 | B35: Set Your Interest Rate Scenario (Assumptions sheet, rows 13–19) | E35: Your Value ✏️
B36: Cell | C36: What to Enter | D36: Guidance | E36: ← Type here (auto-syncs to model)
B37: Assumptions!C13 | C37: 6M Compounded SORA (e.g., 1.221%) | D37: Look up the latest rate from MAS. Pre-filled with Feb 2026 rate. This feeds the Base mortgage rate. | E37: 0.01221
B38: Assumptions!C14 | C38: Bank spread (e.g., 0.45%) | D38: Your bank's quoted spread above SORA. Typical SG banks: 0.40%–0.55%. Base rate = SORA + Spread (auto-calculated in C15). | E38: 0.0045
B39: Assumptions!C16 | C39: Stress mortgage rate (e.g., 3.5%) | D39: A moderately adverse rate scenario. Used when you switch to "Stress" in C18. | E39: 0.035
B40: Assumptions!C17 | C40: Severe mortgage rate (e.g., 5.0%) | D40: Worst-case rate scenario. Useful for stress-testing affordability. | E40: 0.05
B41: Assumptions!C18 | C41: Active Rate Scenario (DROPDOWN) | D41: Choose: "Base" / "Stress" / "Severe". This switches the mortgage rate used in all calculations. The effective rate appears in C19. | E41: Base
C42: → C15 (All-in Base Rate) and C19 (Effective Rate) are formulas. Do NOT type in them.
C43: → Note: HDB loans use a fixed 2.6% (CPF rate). Only private property rates change with this dropdown.
A45: STEP 3 | B45: Adjust Leverage & Financing (Assumptions sheet, rows 22–27) | E45: Your Value ✏️
B46: Cell | C46: What to Enter | D46: Guidance | E46: ← Type here (auto-syncs to model)
B47: Assumptions!C22 | C47: LTV Ratio (default 75%) | D47: Maximum LTV in SG is 75% for first property. Downpayment % (C23) auto-calculates as 1 – LTV. | E47: 0.75
B48: Assumptions!C24 | C48: CPF usage for downpayment (default 20%) | D48: % of property price paid from CPF OA. Cash downpayment (C25) = Total downpayment – CPF usage. | E48: 0.2
B49: Assumptions!C26 | C49: Mortgage tenure in years (e.g., 30) | D49: Range: 15–35 years. Longer tenure = lower monthly payment but more interest. Max age at loan maturity is 65 (bank) or 75 (HDB). | E49: 30
C50: → C23 (Downpayment %), C25 (Cash DP %), and C27 (Leverage Multiple) are all formulas.
A53: STEP 4 | B53: Customize Property Details (Assumptions sheet, rows 31–43) | E53: Your Value ✏️
B54: Cell | C54: What to Enter | D54: Guidance | E54: ← Type here (auto-syncs to model)
B55: Assumptions!C31:H31 | C55: Purchase price for each property type | D55: Enter realistic asking prices from PropertyGuru/99.co for properties you're considering. Each column = one property type. | E55: → Edit on Assumptions sheet (6 properties)
B56: Assumptions!C32:H32 | C56: Price per square foot ($PSF) | D56: For your reference only — not used in calculations. Helps you sanity-check the purchase price. | E56: → Edit on Assumptions sheet (6 properties)
B57: Assumptions!C33:H33 | C57: Remaining lease in years | D57: Critical for HDB & 99LH. Enter "Freehold" for FH properties. Drives the Bala Table lease-decay calculation. | E57: → Edit on Assumptions sheet (6 properties)
B58: Assumptions!B34 + Scenario Tables | C58: Land appreciation scenario | D58: B34 selects the scenario: Pessimistic / Base / Optimistic / Custom. Each property can have its own rate. Edit rates in the Scenario Tables sheet. | E58: → Edit on Scenario Tables sheet
B59: Assumptions!C35:H35 | C59: Monthly imputed rent (or market rent) | D59: What you'd pay in rent for this property. In owner-occupied mode, this is your "rent savings". In investment mode, this is rental income. | E59: → Edit on Assumptions sheet (6 properties)
B60: Assumptions!C36:H36 | C60: Annual rent growth rate (default 2%) | D60: How fast rents grow each year. Also drives maintenance cost growth. | E60: → Edit on Assumptions sheet (6 properties)
B61: Assumptions!C37:H37 | C61: Annual maintenance / condo fees (Year 1) | D61: HDB: Town Council S&CC (~$90–110/mo). Condo: MCST fees ($500–700/mo). Landed: garden + repairs (~$1,500/mo). | E61: → Edit on Assumptions sheet (6 properties)
B62: Assumptions!C39 | C62: Usage mode: Owner-Occupied or Investment | D62: Owner-Occupied: rent is imputed savings, OO property tax bands. Investment: rental income less vacancy, mgmt fees, and income tax. | E62: Owner-Occupied
B63: Assumptions!C40–C42 | C63: Investment-only: Vacancy, Mgmt fee, Tax rate | D63: Only relevant if C39 = Investment. Vacancy 8.33% = 1 month/yr. Mgmt fee 10%. Tax rate = your marginal income tax rate. | E63: → Edit on Assumptions sheet (C40–C42)
B64: Assumptions!C43 | C64: General inflation rate (default 2.5%) | D64: Used to convert nominal returns into real (inflation-adjusted) returns. MAS long-term avg ~2%. | E64: 0.025
A67: STEP 5 | B67: Set Your Benchmark Portfolio (Assumptions sheet, rows 54–55) | E67: Your Value ✏️
B68: Cell | C68: What to Enter | D68: Guidance | E68: ← Type here (auto-syncs to model)
B69: Assumptions!C54 | C69: 60/40 Portfolio CAGR (default 5.5%) | D69: This is the "No Property" alternative return. If you wouldn't buy property, what CAGR would your investments earn? 5.5% is moderate for a 60/40 mix. | E69: 0.055
B70: Assumptions!C55 | C70: Portfolio standard deviation (default 9%) | D70: Used for volatility modeling in the Sensitivity Analysis. ~9% is typical for a 60/40 portfolio. | E70: 0.09
C71: → This is the single most impactful assumption. A higher CAGR makes "No Property" harder to beat.
A75: STEP 6 | B75: Fine-Tune Scenarios (Scenario Tables sheet)
B76: The Scenario Tables sheet is where you define what each scenario name means. It has 4 tables:
B77: 1. Land Appreciation Rates — Per-property growth rates for Pessimistic / Base / Optimistic / Custom scenarios
B78: 2. Mortgage Rate Scenarios — Defines Base / Stress / Severe rates
B79: 3. ABSD Rates — Rates by residency status (auto-linked to Assumptions!C10)
B80: 4. Mortgage Rates by Property — Shows which rate each property gets (HDB = 2.6% fixed, private = market rate)
B82: The ✔ column shows which scenario is currently active. You switch scenarios using the dropdowns on the Assumptions sheet (B34, C18, C10).
B83: To create your own scenario: select "Custom" in B34, then edit the Custom row values in the Scenario Tables sheet (row 8, columns C–H).
B86: HOW TO READ THE RESULTS
B87: Once you've entered your inputs, the model auto-calculates everything. Here’s what each sheet shows you:
B89: Sheet | C89: What It Shows | D89: Key Outputs to Look At
B90: 📊 Dashboard | C90: Executive summary comparing all 6 properties side-by-side at Year 20 | D90: 🏆 Ranking Table (row ~41): properties ranked by total NW. Risk flags: 🔴 = underperforms, 🟡 = high decay, ⚠️ = high capital lockup, 🟢 = beats benchmark
B91: 📊 Sensitivity Analysis | C91: Two-way data tables for a selected property (dropdown at C4) | D91: Table 1: Property equity at various appreciation × mortgage rates. Table 2: Total NW. Table 3: Property advantage vs. portfolio at different alt. CAGRs.
B92: HDB 1984 / HDB 2005 / HDB 2015 | C92: Detailed 20-year year-by-year analysis for each HDB type | D92: Capital structure, annual mortgage split (interest vs principal), Bala factor decay, property equity, cumulative net benefit, ROE, real (inflation-adj) returns.
B93: Condo 99LH / FH Condo / FH Landed | C93: Same 20-year analysis for private properties | D93: Same structure as HDB sheets. FH properties show Bala factor = 1.0 (no decay). Compare terminal equity and ROE across types.
B94: 💰 Opportunity Cost | C94: Tracks your liquid portfolio (cash not in property) growing at the benchmark CAGR, minus annual mortgage payments | D94: Terminal NW comparison table (row ~35): Property equity + Liquid portfolio = Total NW for each option. NW CAGR shows annualized growth. ROE and leverage metrics.
B95: 📉 Cash Flow Waterfall | C95: Year-by-year breakdown of mortgage payment, interest vs principal, rental cash flow, and equity for a selected property | D95: Select property via dropdown (C3). Shows annual mortgage split, net rental cash flow, market value, and net equity. Totals row at bottom.
B96: 📊 Bala Table | C96: SLA’s official Bala’s Table showing leasehold value as % of freehold | D96: Reference data. Shows that a 60-year lease = ~66% of freehold value, a 40-year lease = ~47%. Lending restrictions noted.
B97: 🗓️ Scenario Tables | C97: Configuration tables that define what each scenario means | D97: Edit these to change the rates behind Pessimistic/Base/Optimistic/Custom. The ✔ column shows what’s active.
B98: 📝 Plan | C98: Internal build plan document (for reference/development) | D98: You can ignore this sheet — it’s a development roadmap, not part of the analysis.
B102: QUICK REFERENCE — ALL EDITABLE INPUTS AT A GLANCE
B103: Cell | C103: Description | D103: Default Value
B104: INVESTOR PROFILE
B105: Assumptions!C4 | C105: Current Age | D105: 32
B106: Assumptions!C5 | C106: Analysis Horizon (years) | D106: 30
B107: Assumptions!C7 | C107: Total Net Worth ($) | D107: 800000
B108: Assumptions!C8 | C108: CPF OA Balance ($) | D108: 150000
B109: Assumptions!C9 | C109: CPF OA Interest Rate | D109: 0.025
B110: Assumptions!C10 | C110: Residency Status (DROPDOWN) | D110: SC 1st Property
B111: MARKET RATES & SCENARIO
B112: Assumptions!C13 | C112: 6M Compounded SORA | D112: 0.01221
B113: Assumptions!C14 | C113: Bank Spread | D113: 0.0045
B114: Assumptions!C16 | C114: Stress Mortgage Rate | D114: 0.035
B115: Assumptions!C17 | C115: Severe Mortgage Rate | D115: 0.05
B116: Assumptions!C18 | C116: Active Rate Scenario (DROPDOWN) | D116: Base
B117: LEVERAGE
B118: Assumptions!C22 | C118: LTV Ratio | D118: 0.75
B119: Assumptions!C24 | C119: CPF Usage for Downpayment (%) | D119: 0.2
B120: Assumptions!C26 | C120: Mortgage Tenure (years) | D120: 30
B121: PROPERTY DETAILS (per property, columns C–H)
B122: Assumptions!C31:H31 | C122: Purchase Price | D122: $780K – $7M (varies by type)
B123: Assumptions!C33:H33 | C123: Remaining Lease (years) | D123: 57–99 yrs / Freehold
B124: Assumptions!C35:H35 | C124: Monthly Imputed Rent | D124: $4,500–$15,000
B125: Assumptions!C37:H37 | C125: Annual Maintenance / Condo Fees | D125: $1,080–$18,000
B126: BENCHMARK
...

Sheet Assumptions
A1: SINGAPORE PROPERTY LEVERAGE OPTIMIZER — ASSUMPTIONS
A3: INVESTOR PROFILE
A4: Current Age | C4: ='User Guide'!E27 -> 32 | D4: years
A5: Analysis Horizon | C5: ='User Guide'!E28 -> 30 | D5: years
A6: Exit Age | C6: =C4+C5 -> 62 | D6: years
A7: Total Net Worth | C7: ='User Guide'!E29 -> 800000
A8: CPF OA Balance | C8: ='User Guide'!E30 -> 150000 | D8: ← Edit via User Guide sheet
A9: CPF OA Interest Rate | C9: ='User Guide'!E31 -> 0.025
A10: Residency Status | C10: ='User Guide'!E32 -> SC 1st Property | D10: ← Dropdown
A12: MARKET RATES (LIVE DATA — Feb 2026)
A13: 6M Compounded SORA | C13: ='User Guide'!E37 -> 0.01221
A14: Bank Spread | C14: ='User Guide'!E38 -> 0.0045
A15: All-in Mortgage Rate (Base) | C15: =C13+C14 -> 0.01671 | D15: SORA + Spread
A16: Stress Mortgage Rate | C16: ='User Guide'!E39 -> 0.035
A17: Severe Mortgage Rate | C17: ='User Guide'!E40 -> 0.05
A18: Active Rate Scenario | C18: ='User Guide'!E41 -> Base | D18: ← Dropdown: Base / Stress / Severe
A19: Effective Mortgage Rate | C19: =INDEX('Scenario Tables'!C$24:C$26,MATCH(C18,'Scenario Tables'!$A$24:$A$26,0)) -> 0.026 | D19: ← Used in all calcs
A21: LEVERAGE & FINANCING
A22: LTV Ratio | C22: ='User Guide'!E47 -> 0.75
A23: Downpayment % | C23: =1-C22 -> 0.25
A24: CPF Usage for Downpayment % | C24: ='User Guide'!E48 -> 0.2 | D24: of property price
A25: Cash Downpayment % | C25: =C23-C24 -> 0.05 | D25: of property price
A26: Mortgage Tenure (years) | C26: ='User Guide'!E49 -> 30 | D26: ← Flexible: 15-35
A27: Leverage Multiple | C27: =1/C23 -> 4
A29: PROPERTY ASSUMPTIONS | F29: PROPERTY ASSUMPTIONS | G29: PROPERTY ASSUMPTIONS | H29: PROPERTY ASSUMPTIONS
C30: HDB 1984 | D30: Condo 99LH | E30: FH Condo | F30: HDB 2005 | G30: HDB 2015 | H30: FH Landed (Prime)
A31: Purchase Price | C31: 1400000 | D31: 2500000 | E31: 3900000 | F31: 780000 | G31: 1400000 | H31: 7000000
A32: PSF ($) | C32: 885 | D32: 1800 | E32: 2600 | F32: 650 | G32: 1200 | H32: 1556
A33: Remaining Lease (years) | C33: 57 | D33: 93 | E33: Freehold | F33: 78 | G33: 88 | H33: 999
A34: Land Appreciation Scenario | B34: Custom | C34: =INDEX('Scenario Tables'!C$5:C$8,MATCH(B34,'Scenario Tables'!$A$5:$A$8,0)) -> 0.02 | D34: =INDEX('Scenario Tables'!D$5:D$8,MATCH(B34,'Scenario Tables'!$A$5:$A$8,0)) -> 0.03 | E34: =INDEX('Scenario Tables'!E$5:E$8,MATCH(B34,'Scenario Tables'!$A$5:$A$8,0)) -> 0.04 | F34: =INDEX('Scenario Tables'!F$5:F$8,MATCH(B34,'Scenario Tables'!$A$5:$A$8,0)) -> 0.03 | G34: =INDEX('Scenario Tables'!G$5:G$8,MATCH(B34,'Scenario Tables'!$A$5:$A$8,0)) -> 0.03 | H34: =INDEX('Scenario Tables'!H$5:H$8,MATCH(B34,'Scenario Tables'!$A$5:$A$8,0)) -> 0.05
A35: Monthly Imputed Rent | C35: 4500 | D35: 5200 | E35: 8200 | F35: 4500 | G35: 4500 | H35: 15000
A36: Annual Rent Growth | C36: 0.02 | D36: 0.02 | E36: 0.02 | F36: 0.02 | G36: 0.02 | H36: 0.02
A37: Annual Maintenance/Condo Fee (Yr1) | C37: 1080 | D37: 6000 | E37: 8400 | F37: 1200 | G37: 1320 | H37: 18000
A38: Property Tax Method | C38: IRAS Progressive on AV | D38: IRAS Progressive on AV | E38: IRAS Progressive on AV | F38: IRAS Progressive on AV | G38: IRAS Progressive on AV | H38: IRAS Progressive on AV
A39: Usage Mode | C39: ='User Guide'!E62 -> Owner-Occupied
A40: Vacancy Rate (% annual) | C40: 0.0833 | D40: ← Investment only
A41: Property Mgmt Fee (% of rent) | C41: 0.1 | D41: ← Investment only
A42: Rental Income Tax Rate | C42: 0.15 | D42: ← Investment only
A43: General Inflation Rate | C43: ='User Guide'!E64 -> 0.025 | D43: ← Real return calc
A45: TRANSACTION COSTS
A46: BSD (Buyer Stamp Duty) | C46: =IF(C31<=180000,C31*0.01,IF(C31<=360000,180000*0.01+(C31-180000)*0.02,IF(C31<=640000,180000*0.01+180000*0.02+(C31-360000)*0.03,IF(C31<=1000000,180000*0.01+180000*0.02+280000*0.03+(C31-640000)*0.04,IF(C31<=1500000,180000*0.01+180000*0.02+280000*0.03+360000*0.04+(C31-1000000)*0.05,180000*0.01+180000*0.02+280000*0.03+360000*0.04+500000*0.05+(C31-1500000)*0.06))))) -> 48200 | D46: =IF(D31<=180000,D31*0.01,IF(D31<=360000,180000*0.01+(D31-180000)*0.02,IF(D31<=640000,180000*0.01+180000*0.02+(D31-360000)*0.03,IF(D31<=1000000,180000*0.01+180000*0.02+280000*0.03+(D31-640000)*0.04,IF(D31<=1500000,180000*0.01+180000*0.02+280000*0.03+360000*0.04+(D31-1000000)*0.05,180000*0.01+180000*0.02+280000*0.03+360000*0.04+500000*0.05+(D31-1500000)*0.06))))) -> 113200 | E46: =IF(E31<=180000,E31*0.01,IF(E31<=360000,180000*0.01+(E31-180000)*0.02,IF(E31<=640000,180000*0.01+180000*0.02+(E31-360000)*0.03,IF(E31<=1000000,180000*0.01+180000*0.02+280000*0.03+(E31-640000)*0.04,IF(E31<=1500000,180000*0.01+180000*0.02+280000*0.03+360000*0.04+(E31-1000000)*0.05,180000*0.01+180000*0.02+280000*0.03+360000*0.04+500000*0.05+(E31-1500000)*0.06))))) -> 197200 | F46: =IF(F31<=180000,F31*0.01,IF(F31<=360000,180000*0.01+(F31-180000)*0.02,IF(F31<=640000,180000*0.01+180000*0.02+(F31-360000)*0.03,IF(F31<=1000000,180000*0.01+180000*0.02+280000*0.03+(F31-640000)*0.04,IF(F31<=1500000,180000*0.01+180000*0.02+280000*0.03+360000*0.04+(F31-1000000)*0.05,180000*0.01+180000*0.02+280000*0.03+360000*0.04+500000*0.05+(F31-1500000)*0.06))))) -> 19400 | G46: =IF(G31<=180000,G31*0.01,IF(G31<=360000,180000*0.01+(G31-180000)*0.02,IF(G31<=640000,180000*0.01+180000*0.02+(G31-360000)*0.03,IF(G31<=1000000,180000*0.01+180000*0.02+280000*0.03+(G31-640000)*0.04,IF(G31<=1500000,180000*0.01+180000*0.02+280000*0.03+360000*0.04+(G31-1000000)*0.05,180000*0.01+180000*0.02+280000*0.03+360000*0.04+500000*0.05+(G31-1500000)*0.06))))) -> 48200 | H46: =IF(H31<=180000,H31*0.01,IF(H31<=360000,180000*0.01+(H31-180000)*0.02,IF(H31<=640000,180000*0.01+180000*0.02+(H31-360000)*0.03,IF(H31<=1000000,180000*0.01+180000*0.02+280000*0.03+(H31-640000)*0.04,IF(H31<=1500000,180000*0.01+180000*0.02+280000*0.03+360000*0.04+(H31-1000000)*0.05,180000*0.01+180000*0.02+280000*0.03+360000*0.04+500000*0.05+(H31-1500000)*0.06))))) -> 383200
A47: ABSD Rate | C47: =INDEX('Scenario Tables'!C$18:C$20,MATCH(C10,'Scenario Tables'!$A$18:$A$20,0)) -> 0 | D47: =C47 -> 0 | E47: =C47 -> 0 | F47: =C47 -> 0 | G47: =C47 -> 0 | H47: =C47 -> 0
A48: ABSD Amount | C48: =C47*C31 -> 0 | D48: =D47*D31 -> 0 | E48: =E47*E31 -> 0 | F48: =F47*F31 -> 0 | G48: =G47*G31 -> 0 | H48: =H47*H31 -> 0
A49: Legal + Misc (est. 1%) | C49: =C31*0.01 -> 14000 | D49: =D31*0.01 -> 25000 | E49: =E31*0.01 -> 39000 | F49: =F31*0.01 -> 7800 | G49: =G31*0.01 -> 14000 | H49: =H31*0.01 -> 70000
A50: Agent Fee on Exit (1%) | C50: 0.01 | D50: 0.01 | E50: 0.01 | F50: 0.01 | G50: 0.01 | H50: 0.01
A51: Total Upfront Costs (excl. downpayment) | C51: =C46+C48+C49 -> 62200 | D51: =D46+D48+D49 -> 138200 | E51: =E46+E48+E49 -> 236200 | F51: =F46+F48+F49 -> 27200 | G51: =G46+G48+G49 -> 62200 | H51: =H46+H48+H49 -> 453200
A53: BENCHMARK PORTFOLIO
A54: 60/40 Portfolio CAGR | C54: ='User Guide'!E69 -> 0.055
A55: Portfolio Std Dev (for vol model) | C55: ='User Guide'!E70 -> 0.09 | D55: ← ~9% for 60/40

Sheet Dashboard
A1: LEVERAGED PROPERTY ANALYSIS — EXECUTIVE DASHBOARD
A3: ACTIVE SCENARIO
A4: Residency Status | C4: =Assumptions!C10 -> SC 1st Property | G4: Rate Scenario | I4: =Assumptions!C18 -> Base
A5: Effective Mortgage Rate | C5: =Assumptions!C19 -> 0.026 | G5: Mortgage Tenure | I5: =Assumptions!C26 -> 30
A6: Investor Net Worth | C6: =Assumptions!C7 -> 800000 | G6: Analysis Horizon | I6: =Assumptions!C5 -> 30
A7: Benchmark Portfolio CAGR | C7: =Assumptions!C54 -> 0.055
A9: PROPERTY COMPARISON (20-YEAR TERMINAL VALUES)
C10: HDB 1984 | D10: HDB 2005 | E10: HDB 2015 | F10: Condo 99LH | G10: FH Condo | H10: No Property | I10: FH Landed
A11: PURCHASE & CAPITAL
A12: Purchase Price | C12: ='HDB 1984'!C4 -> 1400000 | D12: ='HDB 2005'!C4 -> 780000 | E12: ='HDB 2015'!C4 -> 1400000 | F12: ='Condo 99LH'!C4 -> 2500000 | G12: ='FH Condo'!C4 -> 3900000 | H12: - | I12: ='FH Landed (Prime)'!C4 -> 7000000
A13: Total Cash Outlay (Day 1) | C13: ='HDB 1984'!C9 -> 262200 | D13: ='HDB 2005'!C9 -> 72200 | E13: ='HDB 2015'!C9 -> 262200 | F13: ='Condo 99LH'!C9 -> 613200 | G13: ='FH Condo'!C9 -> 1061200 | H13: - | I13: ='FH Landed (Prime)'!C9 -> 2053200
A14: Total Equity at Risk (Cash + CPF) | C14: ='HDB 1984'!C10 -> 412200 | D14: ='HDB 2005'!C10 -> 222200 | E14: ='HDB 2015'!C10 -> 412200 | F14: ='Condo 99LH'!C10 -> 763200 | G14: ='FH Condo'!C10 -> 1211200 | H14: - | I14: ='FH Landed (Prime)'!C10 -> 2203200
A15: TERMINAL VALUES (YEAR 20)
A16: Property Market Value | C16: ='HDB 1984'!F35 -> 1508236.6 | D16: ='HDB 2005'!F35 -> 1167366.8 | E16: ='HDB 2015'!F35 -> 2167333.5 | F16: ='Condo 99LH'!F35 -> 3902861.1 | G16: ='FH Condo'!F35 -> 8545380.3 | H16: - | I16: ='FH Landed (Prime)'!F35 -> 18573084
A17: Property Equity (Net of CPF) | C17: ='HDB 1984'!Q35 -> 872887.87 | D17: ='HDB 2005'!Q35 -> 728542.06 | E17: ='HDB 2015'!Q35 -> 1531984.7 | F17: ='Condo 99LH'!Q35 -> 2979508.9 | G17: ='FH Condo'!Q35 -> 7212238.5 | H17: - | I17: ='FH Landed (Prime)'!Q35 -> 16332551
A18: Liquid Portfolio | C18: ='Opportunity Cost'!C34 -> -189685.74 | D18: ='Opportunity Cost'!G34 -> 1143610 | E18: ='Opportunity Cost'!H34 -> -189685.74 | F18: ='Opportunity Cost'!D34 -> -2227400.2 | G18: ='Opportunity Cost'!E34 -> -5087120.5 | H18: ='Opportunity Cost'!F34 -> 2334206 | I18: ='Opportunity Cost'!I34 -> -11419358
A19: TOTAL NET WORTH | C19: =C18+C17 -> 683202.13 | D19: =D18+D17 -> 1872152.1 | E19: =E18+E17 -> 1342299 | F19: =F18+F17 -> 752108.73 | G19: =G18+G17 -> 2125118.1 | H19: =H18 -> 2334206 | I19: =I18+I17 -> 4913192.7
A20: PERFORMANCE METRICS
A21: NW CAGR (20yr) | C21: ='Opportunity Cost'!C42 -> -0.0078599961 | D21: ='Opportunity Cost'!G42 -> 0.043428168 | E21: ='Opportunity Cost'!H42 -> 0.026214068 | F21: ='Opportunity Cost'!D42 -> -0.0030817831 | G21: ='Opportunity Cost'!E42 -> 0.050061302 | H21: ='Opportunity Cost'!F42 -> 0.055 | I21: ='Opportunity Cost'!I42 -> 0.094998919
A22: NW vs. No Property | C22: =C19-H19 -> -1651003.9 | D22: =D19-H19 -> -462053.93 | E22: =E19-H19 -> -991906.99 | F22: =F19-H19 -> -1582097.3 | G22: =G19-H19 -> -209087.94 | H22: - | I22: =I19-H19 -> 2578986.7
A23: Annualized ROE on Equity | C23: ='HDB 1984'!I40 -> 0.048579418 | D23: ='HDB 2005'!I40 -> 0.073631354 | E23: ='HDB 2015'!I40 -> 0.074152745 | F23: ='Condo 99LH'!I40 -> 0.073812702 | G23: ='FH Condo'!I40 -> 0.094742578 | H23: - | I23: ='FH Landed (Prime)'!I40 -> 0.1059952
A24: Breakeven Year | C24: ='HDB 1984'!I41 -> 2 | D24: ='HDB 2005'!I41 -> 1 | E24: ='HDB 2015'!I41 -> 2 | F24: ='Condo 99LH'!I41 -> 2 | G24: ='FH Condo'!I41 -> 2 | H24: - | I24: ='FH Landed (Prime)'!I41 -> 1
A26: LEASE DECAY IMPACT ANALYSIS
C27: HDB 1984 | D27: HDB 2005 | E27: HDB 2015 | F27: Condo 99LH | G27: FH Condo | I27: FH Landed
A28: Starting Lease | C28: ='HDB 1984'!C15 -> 57 | D28: ='HDB 2005'!C15 -> 78 | E28: ='HDB 2015'!C15 -> 88 | F28: ='Condo 99LH'!C15 -> 93 | G28: Freehold | I28: Freehold
A29: Terminal Lease (Year 20) | C29: ='HDB 1984'!C35 -> 37 | D29: ='HDB 2005'!C35 -> 58 | E29: ='HDB 2015'!C35 -> 68 | F29: ='Condo 99LH'!C35 -> 73 | G29: Freehold | I29: Freehold
A30: Bala Factor: Start → End | C30: ='HDB 1984'!D15 -> 0.64 | D30: ='HDB 2005'!D15 -> 0.782 | E30: ='HDB 2015'!D15 -> 0.84 | F30: ='Condo 99LH'!D15 -> 0.87 | G30: 1 | I30: 1
A31: → | C31: ='HDB 1984'!D35 -> 0.464 | D31: ='HDB 2005'!D35 -> 0.648 | E31: ='HDB 2015'!D35 -> 0.72 | F31: ='Condo 99LH'!D35 -> 0.752 | G31: 1 | I31: 1
A32: Total Bala Decay (%) | C32: ='HDB 1984'!D15-'HDB 1984'!D35 -> 0.176 | D32: ='HDB 2005'!D15-'HDB 2005'!D35 -> 0.134 | E32: ='HDB 2015'!D15-'HDB 2015'!D35 -> 0.12 | F32: ='Condo 99LH'!D15-'Condo 99LH'!D35 -> 0.118 | G32: 0 | I32: 0
A33: Value Destroyed by Decay ($) | C33: ='HDB 1984'!E35*('HDB 1984'!D15-'HDB 1984'!D35) -> 572089.75 | D33: ='HDB 2005'!E35*('HDB 2005'!D15-'HDB 2005'!D35) -> 241399.93 | E33: ='HDB 2015'!E35*('HDB 2015'!D15-'HDB 2015'!D35) -> 361222.25 | F33: ='Condo 99LH'!E35*('Condo 99LH'!D15-'Condo 99LH'!D35) -> 612417.03 | G33: 0 | I33: 0
A35: 🏆 PROPERTY RANKING TABLE
A36: Rank | B36: Property | C36: Total Net Worth | D36: NW vs. No Property | E36: ROE on Equity | F36: Equity at Risk | G36: Lease Decay ($) | H36: Breakeven Yr | I36: Risk Flags | K36: Property | L36: NW | M36: ROE | N36: Equity at Risk | O36: Decay $ | P36: Breakeven | Q36: NW Rank | R36: ROE Rank | S36: Risk Flags
A37: 1 | B37: =INDEX($K$37:$K$42,MATCH(1,$Q$37:$Q$42,0)) -> FH Landed | C37: =INDEX($L$37:$L$42,MATCH(1,$Q$37:$Q$42,0)) -> 4913192.7 | D37: =INDEX($L$37:$L$42,MATCH(1,$Q$37:$Q$42,0))-$H$19 -> 2578986.7 | E37: =INDEX($M$37:$M$42,MATCH(1,$Q$37:$Q$42,0)) -> 0.1059952 | F37: =INDEX($N$37:$N$42,MATCH(1,$Q$37:$Q$42,0)) -> 2203200 | G37: =INDEX($O$37:$O$42,MATCH(1,$Q$37:$Q$42,0)) -> 0 | H37: =INDEX($P$37:$P$42,MATCH(1,$Q$37:$Q$42,0)) -> 1 | I37: =INDEX($S$37:$S$42,MATCH(1,$Q$37:$Q$42,0)) -> ⚠️ 🟢 | K37: HDB 1984 | L37: =C19 -> 683202.13 | M37: =C23 -> 0.048579418 | N37: =C14 -> 412200 | O37: =C33 -> 572089.75 | P37: =C24 -> 2 | Q37: =RANK(L37,$L$37:$L$42,0) -> 6 | R37: =RANK(M37,$M$37:$M$42,0) -> 6 | S37: =IF(L37<$H$19,"🔴 ","")&IF(O37>400000,"🟡 ","")&IF(N37>1000000,"⚠️ ","")&IF(L37>$H$19,"🟢","") -> 🔴 🟡
A38: 2 | B38: =INDEX($K$37:$K$42,MATCH(2,$Q$37:$Q$42,0)) -> FH Condo | C38: =INDEX($L$37:$L$42,MATCH(2,$Q$37:$Q$42,0)) -> 2125118.1 | D38: =INDEX($L$37:$L$42,MATCH(2,$Q$37:$Q$42,0))-$H$19 -> -209087.94 | E38: =INDEX($M$37:$M$42,MATCH(2,$Q$37:$Q$42,0)) -> 0.094742578 | F38: =INDEX($N$37:$N$42,MATCH(2,$Q$37:$Q$42,0)) -> 1211200 | G38: =INDEX($O$37:$O$42,MATCH(2,$Q$37:$Q$42,0)) -> 0 | H38: =INDEX($P$37:$P$42,MATCH(2,$Q$37:$Q$42,0)) -> 2 | I38: =INDEX($S$37:$S$42,MATCH(2,$Q$37:$Q$42,0)) -> 🔴 ⚠️ | K38: HDB 2005 | L38: =D19 -> 1872152.1 | M38: =D23 -> 0.073631354 | N38: =D14 -> 222200 | O38: =D33 -> 241399.93 | P38: =D24 -> 1 | Q38: =RANK(L38,$L$37:$L$42,0) -> 3 | R38: =RANK(M38,$M$37:$M$42,0) -> 5 | S38: =IF(L38<$H$19,"🔴 ","")&IF(O38>400000,"🟡 ","")&IF(N38>1000000,"⚠️ ","")&IF(L38>$H$19,"🟢","") -> 🔴
A39: 3 | B39: =INDEX($K$37:$K$42,MATCH(3,$Q$37:$Q$42,0)) -> HDB 2005 | C39: =INDEX($L$37:$L$42,MATCH(3,$Q$37:$Q$42,0)) -> 1872152.1 | D39: =INDEX($L$37:$L$42,MATCH(3,$Q$37:$Q$42,0))-$H$19 -> -462053.93 | E39: =INDEX($M$37:$M$42,MATCH(3,$Q$37:$Q$42,0)) -> 0.073631354 | F39: =INDEX($N$37:$N$42,MATCH(3,$Q$37:$Q$42,0)) -> 222200 | G39: =INDEX($O$37:$O$42,MATCH(3,$Q$37:$Q$42,0)) -> 241399.93 | H39: =INDEX($P$37:$P$42,MATCH(3,$Q$37:$Q$42,0)) -> 1 | I39: =INDEX($S$37:$S$42,MATCH(3,$Q$37:$Q$42,0)) -> 🔴 | K39: HDB 2015 | L39: =E19 -> 1342299 | M39: =E23 -> 0.074152745 | N39: =E14 -> 412200 | O39: =E33 -> 361222.25 | P39: =E24 -> 2 | Q39: =RANK(L39,$L$37:$L$42,0) -> 4 | R39: =RANK(M39,$M$37:$M$42,0) -> 3 | S39: =IF(L39<$H$19,"🔴 ","")&IF(O39>400000,"🟡 ","")&IF(N39>1000000,"⚠️ ","")&IF(L39>$H$19,"🟢","") -> 🔴
A40: 4 | B40: =INDEX($K$37:$K$42,MATCH(4,$Q$37:$Q$42,0)) -> HDB 2015 | C40: =INDEX($L$37:$L$42,MATCH(4,$Q$37:$Q$42,0)) -> 1342299 | D40: =INDEX($L$37:$L$42,MATCH(4,$Q$37:$Q$42,0))-$H$19 -> -991906.99 | E40: =INDEX($M$37:$M$42,MATCH(4,$Q$37:$Q$42,0)) -> 0.074152745 | F40: =INDEX($N$37:$N$42,MATCH(4,$Q$37:$Q$42,0)) -> 412200 | G40: =INDEX($O$37:$O$42,MATCH(4,$Q$37:$Q$42,0)) -> 361222.25 | H40: =INDEX($P$37:$P$42,MATCH(4,$Q$37:$Q$42,0)) -> 2 | I40: =INDEX($S$37:$S$42,MATCH(4,$Q$37:$Q$42,0)) -> 🔴 | K40: Condo 99LH | L40: =F19 -> 752108.73 | M40: =F23 -> 0.073812702 | N40: =F14 -> 763200 | O40: =F33 -> 612417.03 | P40: =F24 -> 2 | Q40: =RANK(L40,$L$37:$L$42,0) -> 5 | R40: =RANK(M40,$M$37:$M$42,0) -> 4 | S40: =IF(L40<$H$19,"🔴 ","")&IF(O40>400000,"🟡 ","")&IF(N40>1000000,"⚠️ ","")&IF(L40>$H$19,"🟢","") -> 🔴 🟡
A41: 5 | B41: =INDEX($K$37:$K$42,MATCH(5,$Q$37:$Q$42,0)) -> Condo 99LH | C41: =INDEX($L$37:$L$42,MATCH(5,$Q$37:$Q$42,0)) -> 752108.73 | D41: =INDEX($L$37:$L$42,MATCH(5,$Q$37:$Q$42,0))-$H$19 -> -1582097.3 | E41: =INDEX($M$37:$M$42,MATCH(5,$Q$37:$Q$42,0)) -> 0.073812702 | F41: =INDEX($N$37:$N$42,MATCH(5,$Q$37:$Q$42,0)) -> 763200 | G41: =INDEX($O$37:$O$42,MATCH(5,$Q$37:$Q$42,0)) -> 612417.03 | H41: =INDEX($P$37:$P$42,MATCH(5,$Q$37:$Q$42,0)) -> 2 | I41: =INDEX($S$37:$S$42,MATCH(5,$Q$37:$Q$42,0)) -> 🔴 🟡 | K41: FH Condo | L41: =G19 -> 2125118.1 | M41: =G23 -> 0.094742578 | N41: =G14 -> 1211200 | O41: =G33 -> 0 | P41: =G24 -> 2 | Q41: =RANK(L41,$L$37:$L$42,0) -> 2 | R41: =RANK(M41,$M$37:$M$42,0) -> 2 | S41: =IF(L41<$H$19,"🔴 ","")&IF(O41>400000,"🟡 ","")&IF(N41>1000000,"⚠️ ","")&IF(L41>$H$19,"🟢","") -> 🔴 ⚠️
A42: 6 | B42: =INDEX($K$37:$K$42,MATCH(6,$Q$37:$Q$42,0)) -> HDB 1984 | C42: =INDEX($L$37:$L$42,MATCH(6,$Q$37:$Q$42,0)) -> 683202.13 | D42: =INDEX($L$37:$L$42,MATCH(6,$Q$37:$Q$42,0))-$H$19 -> -1651003.9 | E42: =INDEX($M$37:$M$42,MATCH(6,$Q$37:$Q$42,0)) -> 0.048579418 | F42: =INDEX($N$37:$N$42,MATCH(6,$Q$37:$Q$42,0)) -> 412200 | G42: =INDEX($O$37:$O$42,MATCH(6,$Q$37:$Q$42,0)) -> 572089.75 | H42: =INDEX($P$37:$P$42,MATCH(6,$Q$37:$Q$42,0)) -> 2 | I42: =INDEX($S$37:$S$42,MATCH(6,$Q$37:$Q$42,0)) -> 🔴 🟡 | K42: FH Landed | L42: =I19 -> 4913192.7 | M42: =I23 -> 0.1059952 | N42: =I14 -> 2203200 | O42: =I33 -> 0 | P42: =I24 -> 1 | Q42: =RANK(L42,$L$37:$L$42,0) -> 1 | R42: =RANK(M42,$M$37:$M$42,0) -> 1 | S42: =IF(L42<$H$19,"🔴 ","")&IF(O42>400000,"🟡 ","")&IF(N42>1000000,"⚠️ ","")&IF(L42>$H$19,"🟢","") -> ⚠️ 🟢
A44: QUICK STATS | B44: Best: | C44: =B37 -> FH Landed | D44: Worst: | E44: =B42 -> HDB 1984 | F44: Spread: | G44: =C37-C42 -> 4229990.6
A45: FLAG LEGEND | B45: 🔴 Underperforms No Property | D45: 🟡 Lease decay > $400K | F45: ⚠️ Capital lock-up > $1M | H45: 🟢 Beats No Property
A47: 📊 VISUAL ANALYSIS
B49: HDB 1984 | C49: HDB 2005 | D49: HDB 2015 | E49: Condo 99LH | F49: FH Condo | G49: FH Landed
A50: Total Net Worth ($) | B50: =C19 -> 683202.13 | C50: =D19 -> 1872152.1 | D50: =E19 -> 1342299 | E50: =F19 -> 752108.73 | F50: =G19 -> 2125118.1 | G50: =I19 -> 4913192.7
A51: No Property Baseline ($) | B51: =$H$19 -> 2334206 | C51: =$H$19 -> 2334206 | D51: =$H$19 -> 2334206 | E51: =$H$19 -> 2334206 | F51: =$H$19 -> 2334206 | G51: =$H$19 -> 2334206
B53: HDB 1984 | C53: HDB 2005 | D53: HDB 2015 | E53: Condo 99LH | F53: FH Condo | G53: FH Landed
A54: Property Equity ($) | B54: =C17 -> 872887.87 | C54: =D17 -> 728542.06 | D54: =E17 -> 1531984.7 | E54: =F17 -> 2979508.9 | F54: =G17 -> 7212238.5 | G54: =I17 -> 16332551
A55: Liquid Portfolio ($) | B55: =C18 -> -189685.74 | C55: =D18 -> 1143610 | D55: =E18 -> -189685.74 | E55: =F18 -> -2227400.2 | F55: =G18 -> -5087120.5 | G55: =I18 -> -11419358
B57: HDB 1984 | C57: HDB 2005 | D57: HDB 2015 | E57: Condo 99LH | F57: FH Condo | G57: FH Landed
A58: Annualized ROE | B58: =C23 -> 0.048579418 | C58: =D23 -> 0.073631354 | D58: =E23 -> 0.074152745 | E58: =F23 -> 0.073812702 | F58: =G23 -> 0.094742578 | G58: =I23 -> 0.1059952
A115: 🚩 RISK ASSESSMENT & DECISION MATRIX
A116: Property | B116: Beats Benchmark? | C116: Lease Risk | D116: Capital Intensity | E116: ROE Rating | F116: Decay Impact | G116: Overall Risk Score | H116: Verdict
A117: HDB 1984 | B117: =IF(C19>$H$19,"✅ Yes","❌ No") -> ❌ No | C117: =IF(C28="Freehold","🟢 None",IF(C28<60,"🔴 High",IF(C28<80,"🟡 Medium","🟢 Low"))) -> 🔴 High | D117: =IF(C14>1500000,"🔴 Very High",IF(C14>1000000,"🟡 High",IF(C14>500000,"🟢 Medium","🟢 Low"))) -> 🟢 Low | E117: =IF(C23>0.09,"🟢 Strong",IF(C23>0.07,"🟢 Good",IF(C23>0.05,"🟡 Fair","🔴 Weak"))) -> 🔴 Weak | F117: =IF(C33>500000,"🔴 Severe",IF(C33>300000,"🟡 Moderate",IF(C33>0,"🟢 Minor","🟢 None"))) -> 🔴 Severe | G117: =COUNTIF(B117:F117,"🔴*")*2+COUNTIF(B117:F117,"🟡*")*1+COUNTIF(B117:F117,"❌*")*2 -> 8 | H117: =IF(G117<=1,"⭐ Excellent",IF(G117<=3,"✅ Favorable",IF(G117<=5,"⚠️ Moderate","🛑 Caution"))) -> 🛑 Caution
A118: HDB 2005 | B118: =IF(D19>$H$19,"✅ Yes","❌ No") -> ❌ No | C118: =IF(D28="Freehold","🟢 None",IF(D28<60,"🔴 High",IF(D28<80,"🟡 Medium","🟢 Low"))) -> 🟡 Medium | D118: =IF(D14>1500000,"🔴 Very High",IF(D14>1000000,"🟡 High",IF(D14>500000,"🟢 Medium","🟢 Low"))) -> 🟢 Low | E118: =IF(D23>0.09,"🟢 Strong",IF(D23>0.07,"🟢 Good",IF(D23>0.05,"🟡 Fair","🔴 Weak"))) -> 🟢 Good | F118: =IF(D33>500000,"🔴 Severe",IF(D33>300000,"🟡 Moderate",IF(D33>0,"🟢 Minor","🟢 None"))) -> 🟢 Minor | G118: =COUNTIF(B118:F118,"🔴*")*2+COUNTIF(B118:F118,"🟡*")*1+COUNTIF(B118:F118,"❌*")*2 -> 3 | H118: =IF(G118<=1,"⭐ Excellent",IF(G118<=3,"✅ Favorable",IF(G118<=5,"⚠️ Moderate","🛑 Caution"))) -> ✅ Favorable
A119: HDB 2015 | B119: =IF(E19>$H$19,"✅ Yes","❌ No") -> ❌ No | C119: =IF(E28="Freehold","🟢 None",IF(E28<60,"🔴 High",IF(E28<80,"🟡 Medium","🟢 Low"))) -> 🟢 Low | D119: =IF(E14>1500000,"🔴 Very High",IF(E14>1000000,"🟡 High",IF(E14>500000,"🟢 Medium","🟢 Low"))) -> 🟢 Low | E119: =IF(E23>0.09,"🟢 Strong",IF(E23>0.07,"🟢 Good",IF(E23>0.05,"🟡 Fair","🔴 Weak"))) -> 🟢 Good | F119: =IF(E33>500000,"🔴 Severe",IF(E33>300000,"🟡 Moderate",IF(E33>0,"🟢 Minor","🟢 None"))) -> 🟡 Moderate | G119: =COUNTIF(B119:F119,"🔴*")*2+COUNTIF(B119:F119,"🟡*")*1+COUNTIF(B119:F119,"❌*")*2 -> 3 | H119: =IF(G119<=1,"⭐ Excellent",IF(G119<=3,"✅ Favorable",IF(G119<=5,"⚠️ Moderate","🛑 Caution"))) -> ✅ Favorable
A120: Condo 99LH | B120: =IF(F19>$H$19,"✅ Yes","❌ No") -> ❌ No | C120: =IF(F28="Freehold","🟢 None",IF(F28<60,"🔴 High",IF(F28<80,"🟡 Medium","🟢 Low"))) -> 🟢 Low | D120: =IF(F14>1500000,"🔴 Very High",IF(F14>1000000,"🟡 High",IF(F14>500000,"🟢 Medium","🟢 Low"))) -> 🟢 Medium | E120: =IF(F23>0.09,"🟢 Strong",IF(F23>0.07,"🟢 Good",IF(F23>0.05,"🟡 Fair","🔴 Weak"))) -> 🟢 Good | F120: =IF(F33>500000,"🔴 Severe",IF(F33>300000,"🟡 Moderate",IF(F33>0,"🟢 Minor","🟢 None"))) -> 🔴 Severe | G120: =COUNTIF(B120:F120,"🔴*")*2+COUNTIF(B120:F120,"🟡*")*1+COUNTIF(B120:F120,"❌*")*2 -> 4 | H120: =IF(G120<=1,"⭐ Excellent",IF(G120<=3,"✅ Favorable",IF(G120<=5,"⚠️ Moderate","🛑 Caution"))) -> ⚠️ Moderate
A121: FH Condo | B121: =IF(G19>$H$19,"✅ Yes","❌ No") -> ❌ No | C121: =IF(G28="Freehold","🟢 None",IF(G28<60,"🔴 High",IF(G28<80,"🟡 Medium","🟢 Low"))) -> 🟢 None | D121: =IF(G14>1500000,"🔴 Very High",IF(G14>1000000,"🟡 High",IF(G14>500000,"🟢 Medium","🟢 Low"))) -> 🟡 High | E121: =IF(G23>0.09,"🟢 Strong",IF(G23>0.07,"🟢 Good",IF(G23>0.05,"🟡 Fair","🔴 Weak"))) -> 🟢 Strong | F121: =IF(G33>500000,"🔴 Severe",IF(G33>300000,"🟡 Moderate",IF(G33>0,"🟢 Minor","🟢 None"))) -> 🟢 None | G121: =COUNTIF(B121:F121,"🔴*")*2+COUNTIF(B121:F121,"🟡*")*1+COUNTIF(B121:F121,"❌*")*2 -> 3 | H121: =IF(G121<=1,"⭐ Excellent",IF(G121<=3,"✅ Favorable",IF(G121<=5,"⚠️ Moderate","🛑 Caution"))) -> ✅ Favorable
A122: FH Landed | B122: =IF(I19>$H$19,"✅ Yes","❌ No") -> ✅ Yes | C122: =IF(I28="Freehold","🟢 None",IF(I28<60,"🔴 High",IF(I28<80,"🟡 Medium","🟢 Low"))) -> 🟢 None | D122: =IF(I14>1500000,"🔴 Very High",IF(I14>1000000,"🟡 High",IF(I14>500000,"🟢 Medium","🟢 Low"))) -> 🔴 Very High | E122: =IF(I23>0.09,"🟢 Strong",IF(I23>0.07,"🟢 Good",IF(I23>0.05,"🟡 Fair","🔴 Weak"))) -> 🟢 Strong | F122: =IF(I33>500000,"🔴 Severe",IF(I33>300000,"🟡 Moderate",IF(I33>0,"🟢 Minor","🟢 None"))) -> 🟢 None | G122: =COUNTIF(B122:F122,"🔴*")*2+COUNTIF(B122:F122,"🟡*")*1+COUNTIF(B122:F122,"❌*")*2 -> 2 | H122: =IF(G122<=1,"⭐ Excellent",IF(G122<=3,"✅ Favorable",IF(G122<=5,"⚠️ Moderate","🛑 Caution"))) -> ✅ Favorable
A124: SCORE KEY: | B124: 0-1 = ⭐ Excellent | D124: 2-3 = ✅ Favorable | F124: 4-5 = ⚠️ Moderate | G124: 6+ = 🛑 Caution

Sheet Sensitivity Analysis
A1: SENSITIVITY ANALYSIS — TWO-WAY DATA TABLES
A3: PROPERTY SELECTOR | F3: CURRENT BASE CASE VALUES | L3: HELPER CALCS (selected property)
A4: Select Property: | C4: FH Condo | F4: Land Appreciation: | H4: {=INDEX(Assumptions!C34:H34,C5)} -> 0.04 | L4: Loan Amount | N4: =C6*Assumptions!C22 -> 2925000
A5: Property #: | C5: =MATCH(C4,{"HDB 1984","Condo 99LH","FH Condo","HDB 2005","HDB 2015","FH Landed (Prime)"},0) -> 3 | F5: Mortgage Rate: | H5: {=INDEX('Scenario Tables'!C27:H27,C5)} -> 0.01671 | L5: Bala Start | N5: {=INDEX(Assumptions!C33:H33,C5)} -> Freehold
A6: Purchase Price: | C6: {=INDEX(Assumptions!C31:H31,C5)} -> 3900000 | F6: Portfolio CAGR: | H6: =Assumptions!C54 -> 0.055 | L6: Bala End Factor | N6: =IF(OR(N5="Freehold",N5>=900),1,INDEX('Bala Table'!B:B,MATCH(N5-20,'Bala Table'!A:A,-1))) -> 1
L7: Bala Start Factor | N7: =IF(OR(N5="Freehold",N5>=900),1,INDEX('Bala Table'!B:B,MATCH(N5,'Bala Table'!A:A,-1))) -> 1
L8: Tenure | N8: =Assumptions!C26 -> 30
A9: TABLE 1: TERMINAL PROPERTY EQUITY ($) — Land Appreciation vs. Mortgage Rate | L9: CPF Accrued Int (Y20) | N9: =Assumptions!C8*((1+Assumptions!C9)^20-1)+Assumptions!C8*((1+Assumptions!C9)^20-1) -> 191584.93
A10: Land Appr. ↓ Mort. Rate → | C10: Table 1: Terminal Property Equity (Net of Loan & CPF) | D10: Mortgage Rate | L10: Total Equity at Risk | N10: {=C6*Assumptions!C24+INDEX(Assumptions!C49:H49,C5)+Assumptions!C8} -> 969000
C11: Land Appr. | D11: 0.015 | E11: 0.02 | F11: 0.025 | G11: 0.03 | H11: 0.035 | I11: 0.04 | J11: 0.05 | L11: Cumul. Net Rental CF (Y20) | N11: =CHOOSE(C5,'HDB 1984'!N35,'Condo 99LH'!N35,'FH Condo'!N35,'HDB 2005'!N35,'HDB 2015'!N35,'FH Landed (Prime)'!N35) -> 1227977.7
C12: -0.01 | D12: =(($C$6/$N$7)*(1+$C12)^20*$N$6)-(PV(D$11/12,($N$8-20)*12,-PMT(D$11/12,$N$8*12,-$N$4)))-$N$9 -> 1874006.9 | E12: =(($C$6/$N$7)*(1+$C12)^20*$N$6)-(PV(E$11/12,($N$8-20)*12,-PMT(E$11/12,$N$8*12,-$N$4)))-$N$9 -> 1823275.1 | F12: =(($C$6/$N$7)*(1+$C12)^20*$N$6)-(PV(F$11/12,($N$8-20)*12,-PMT(F$11/12,$N$8*12,-$N$4)))-$N$9 -> 1772273.7 | G12: =(($C$6/$N$7)*(1+$C12)^20*$N$6)-(PV(G$11/12,($N$8-20)*12,-PMT(G$11/12,$N$8*12,-$N$4)))-$N$9 -> 1721137.1 | H12: =(($C$6/$N$7)*(1+$C12)^20*$N$6)-(PV(H$11/12,($N$8-20)*12,-PMT(H$11/12,$N$8*12,-$N$4)))-$N$9 -> 1669997.9 | I12: =(($C$6/$N$7)*(1+$C12)^20*$N$6)-(PV(I$11/12,($N$8-20)*12,-PMT(I$11/12,$N$8*12,-$N$4)))-$N$9 -> 1618986.2 | J12: =(($C$6/$N$7)*(1+$C12)^20*$N$6)-(PV(J$11/12,($N$8-20)*12,-PMT(J$11/12,$N$8*12,-$N$4)))-$N$9 -> 1517843.3 | N12: HDB 1984
C13: 0 | D13: =(($C$6/$N$7)*(1+$C13)^20*$N$6)-(PV(D$11/12,($N$8-20)*12,-PMT(D$11/12,$N$8*12,-$N$4)))-$N$9 -> 2584169.9 | E13: =(($C$6/$N$7)*(1+$C13)^20*$N$6)-(PV(E$11/12,($N$8-20)*12,-PMT(E$11/12,$N$8*12,-$N$4)))-$N$9 -> 2533438 | F13: =(($C$6/$N$7)*(1+$C13)^20*$N$6)-(PV(F$11/12,($N$8-20)*12,-PMT(F$11/12,$N$8*12,-$N$4)))-$N$9 -> 2482436.7 | G13: =(($C$6/$N$7)*(1+$C13)^20*$N$6)-(PV(G$11/12,($N$8-20)*12,-PMT(G$11/12,$N$8*12,-$N$4)))-$N$9 -> 2431300 | H13: =(($C$6/$N$7)*(1+$C13)^20*$N$6)-(PV(H$11/12,($N$8-20)*12,-PMT(H$11/12,$N$8*12,-$N$4)))-$N$9 -> 2380160.8 | I13: =(($C$6/$N$7)*(1+$C13)^20*$N$6)-(PV(I$11/12,($N$8-20)*12,-PMT(I$11/12,$N$8*12,-$N$4)))-$N$9 -> 2329149.1 | J13: =(($C$6/$N$7)*(1+$C13)^20*$N$6)-(PV(J$11/12,($N$8-20)*12,-PMT(J$11/12,$N$8*12,-$N$4)))-$N$9 -> 2228006.2 | N13: Condo 99LH
C14: 0.02 | D14: =(($C$6/$N$7)*(1+$C14)^20*$N$6)-(PV(D$11/12,($N$8-20)*12,-PMT(D$11/12,$N$8*12,-$N$4)))-$N$9 -> 4479364.7 | E14: =(($C$6/$N$7)*(1+$C14)^20*$N$6)-(PV(E$11/12,($N$8-20)*12,-PMT(E$11/12,$N$8*12,-$N$4)))-$N$9 -> 4428632.9 | F14: =(($C$6/$N$7)*(1+$C14)^20*$N$6)-(PV(F$11/12,($N$8-20)*12,-PMT(F$11/12,$N$8*12,-$N$4)))-$N$9 -> 4377631.5 | G14: =(($C$6/$N$7)*(1+$C14)^20*$N$6)-(PV(G$11/12,($N$8-20)*12,-PMT(G$11/12,$N$8*12,-$N$4)))-$N$9 -> 4326494.9 | H14: =(($C$6/$N$7)*(1+$C14)^20*$N$6)-(PV(H$11/12,($N$8-20)*12,-PMT(H$11/12,$N$8*12,-$N$4)))-$N$9 -> 4275355.7 | I14: =(($C$6/$N$7)*(1+$C14)^20*$N$6)-(PV(I$11/12,($N$8-20)*12,-PMT(I$11/12,$N$8*12,-$N$4)))-$N$9 -> 4224343.9 | J14: =(($C$6/$N$7)*(1+$C14)^20*$N$6)-(PV(J$11/12,($N$8-20)*12,-PMT(J$11/12,$N$8*12,-$N$4)))-$N$9 -> 4123201.1 | N14: FH Condo
C15: 0.03 | D15: =(($C$6/$N$7)*(1+$C15)^20*$N$6)-(PV(D$11/12,($N$8-20)*12,-PMT(D$11/12,$N$8*12,-$N$4)))-$N$9 -> 5728003.7 | E15: =(($C$6/$N$7)*(1+$C15)^20*$N$6)-(PV(E$11/12,($N$8-20)*12,-PMT(E$11/12,$N$8*12,-$N$4)))-$N$9 -> 5677271.8 | F15: =(($C$6/$N$7)*(1+$C15)^20*$N$6)-(PV(F$11/12,($N$8-20)*12,-PMT(F$11/12,$N$8*12,-$N$4)))-$N$9 -> 5626270.5 | G15: =(($C$6/$N$7)*(1+$C15)^20*$N$6)-(PV(G$11/12,($N$8-20)*12,-PMT(G$11/12,$N$8*12,-$N$4)))-$N$9 -> 5575133.8 | H15: =(($C$6/$N$7)*(1+$C15)^20*$N$6)-(PV(H$11/12,($N$8-20)*12,-PMT(H$11/12,$N$8*12,-$N$4)))-$N$9 -> 5523994.7 | I15: =(($C$6/$N$7)*(1+$C15)^20*$N$6)-(PV(I$11/12,($N$8-20)*12,-PMT(I$11/12,$N$8*12,-$N$4)))-$N$9 -> 5472982.9 | J15: =(($C$6/$N$7)*(1+$C15)^20*$N$6)-(PV(J$11/12,($N$8-20)*12,-PMT(J$11/12,$N$8*12,-$N$4)))-$N$9 -> 5371840.1 | N15: HDB 2005
C16: 0.05 | D16: =(($C$6/$N$7)*(1+$C16)^20*$N$6)-(PV(D$11/12,($N$8-20)*12,-PMT(D$11/12,$N$8*12,-$N$4)))-$N$9 -> 9032030.9 | E16: =(($C$6/$N$7)*(1+$C16)^20*$N$6)-(PV(E$11/12,($N$8-20)*12,-PMT(E$11/12,$N$8*12,-$N$4)))-$N$9 -> 8981299.1 | F16: =(($C$6/$N$7)*(1+$C16)^20*$N$6)-(PV(F$11/12,($N$8-20)*12,-PMT(F$11/12,$N$8*12,-$N$4)))-$N$9 -> 8930297.7 | G16: =(($C$6/$N$7)*(1+$C16)^20*$N$6)-(PV(G$11/12,($N$8-20)*12,-PMT(G$11/12,$N$8*12,-$N$4)))-$N$9 -> 8879161.1 | H16: =(($C$6/$N$7)*(1+$C16)^20*$N$6)-(PV(H$11/12,($N$8-20)*12,-PMT(H$11/12,$N$8*12,-$N$4)))-$N$9 -> 8828021.9 | I16: =(($C$6/$N$7)*(1+$C16)^20*$N$6)-(PV(I$11/12,($N$8-20)*12,-PMT(I$11/12,$N$8*12,-$N$4)))-$N$9 -> 8777010.1 | J16: =(($C$6/$N$7)*(1+$C16)^20*$N$6)-(PV(J$11/12,($N$8-20)*12,-PMT(J$11/12,$N$8*12,-$N$4)))-$N$9 -> 8675867.3 | N16: HDB 2015
C17: 0.07 | D17: =(($C$6/$N$7)*(1+$C17)^20*$N$6)-(PV(D$11/12,($N$8-20)*12,-PMT(D$11/12,$N$8*12,-$N$4)))-$N$9 -> 13775939 | E17: =(($C$6/$N$7)*(1+$C17)^20*$N$6)-(PV(E$11/12,($N$8-20)*12,-PMT(E$11/12,$N$8*12,-$N$4)))-$N$9 -> 13725207 | F17: =(($C$6/$N$7)*(1+$C17)^20*$N$6)-(PV(F$11/12,($N$8-20)*12,-PMT(F$11/12,$N$8*12,-$N$4)))-$N$9 -> 13674206 | G17: =(($C$6/$N$7)*(1+$C17)^20*$N$6)-(PV(G$11/12,($N$8-20)*12,-PMT(G$11/12,$N$8*12,-$N$4)))-$N$9 -> 13623069 | H17: =(($C$6/$N$7)*(1+$C17)^20*$N$6)-(PV(H$11/12,($N$8-20)*12,-PMT(H$11/12,$N$8*12,-$N$4)))-$N$9 -> 13571930 | I17: =(($C$6/$N$7)*(1+$C17)^20*$N$6)-(PV(I$11/12,($N$8-20)*12,-PMT(I$11/12,$N$8*12,-$N$4)))-$N$9 -> 13520918 | J17: =(($C$6/$N$7)*(1+$C17)^20*$N$6)-(PV(J$11/12,($N$8-20)*12,-PMT(J$11/12,$N$8*12,-$N$4)))-$N$9 -> 13419776 | N17: FH Landed (Prime)
C18: 0.1 | D18: =(($C$6/$N$7)*(1+$C18)^20*$N$6)-(PV(D$11/12,($N$8-20)*12,-PMT(D$11/12,$N$8*12,-$N$4)))-$N$9 -> 24921420 | E18: =(($C$6/$N$7)*(1+$C18)^20*$N$6)-(PV(E$11/12,($N$8-20)*12,-PMT(E$11/12,$N$8*12,-$N$4)))-$N$9 -> 24870688 | F18: =(($C$6/$N$7)*(1+$C18)^20*$N$6)-(PV(F$11/12,($N$8-20)*12,-PMT(F$11/12,$N$8*12,-$N$4)))-$N$9 -> 24819686 | G18: =(($C$6/$N$7)*(1+$C18)^20*$N$6)-(PV(G$11/12,($N$8-20)*12,-PMT(G$11/12,$N$8*12,-$N$4)))-$N$9 -> 24768550 | H18: =(($C$6/$N$7)*(1+$C18)^20*$N$6)-(PV(H$11/12,($N$8-20)*12,-PMT(H$11/12,$N$8*12,-$N$4)))-$N$9 -> 24717411 | I18: =(($C$6/$N$7)*(1+$C18)^20*$N$6)-(PV(I$11/12,($N$8-20)*12,-PMT(I$11/12,$N$8*12,-$N$4)))-$N$9 -> 24666399 | J18: =(($C$6/$N$7)*(1+$C18)^20*$N$6)-(PV(J$11/12,($N$8-20)*12,-PMT(J$11/12,$N$8*12,-$N$4)))-$N$9 -> 24565256
C20: Table 2: Total Net Worth at Year 20 (Property Equity + Net Rental Cash Flow)
C21: Land Appr. ↓ Mortgage → | D21: 0.015 | E21: 0.02 | F21: 0.025 | G21: 0.03 | H21: 0.035 | I21: 0.04 | J21: 0.05
C22: -0.01 | D22: =D12+$N$11 -> 3101984.6 | E22: =E12+$N$11 -> 3051252.7 | F22: =F12+$N$11 -> 3000251.4 | G22: =G12+$N$11 -> 2949114.7 | H22: =H12+$N$11 -> 2897975.6 | I22: =I12+$N$11 -> 2846963.8 | J22: =J12+$N$11 -> 2745821
C23: 0 | D23: =D13+$N$11 -> 3812147.5 | E23: =E13+$N$11 -> 3761415.7 | F23: =F13+$N$11 -> 3710414.3 | G23: =G13+$N$11 -> 3659277.7 | H23: =H13+$N$11 -> 3608138.5 | I23: =I13+$N$11 -> 3557126.8 | J23: =J13+$N$11 -> 3455983.9
C24: 0.02 | D24: =D14+$N$11 -> 5707342.4 | E24: =E14+$N$11 -> 5656610.5 | F24: =F14+$N$11 -> 5605609.2 | G24: =G14+$N$11 -> 5554472.5 | H24: =H14+$N$11 -> 5503333.4 | I24: =I14+$N$11 -> 5452321.6 | J24: =J14+$N$11 -> 5351178.8
C25: 0.03 | D25: =D15+$N$11 -> 6955981.4 | E25: =E15+$N$11 -> 6905249.5 | F25: =F15+$N$11 -> 6854248.1 | G25: =G15+$N$11 -> 6803111.5 | H25: =H15+$N$11 -> 6751972.3 | I25: =I15+$N$11 -> 6700960.6 | J25: =J15+$N$11 -> 6599817.7
C26: 0.05 | D26: =D16+$N$11 -> 10260009 | E26: =E16+$N$11 -> 10209277 | F26: =F16+$N$11 -> 10158275 | G26: =G16+$N$11 -> 10107139 | H26: =H16+$N$11 -> 10056000 | I26: =I16+$N$11 -> 10004988 | J26: =J16+$N$11 -> 9903845
C27: 0.07 | D27: =D17+$N$11 -> 15003917 | E27: =E17+$N$11 -> 14953185 | F27: =F17+$N$11 -> 14902184 | G27: =G17+$N$11 -> 14851047 | H27: =H17+$N$11 -> 14799908 | I27: =I17+$N$11 -> 14748896 | J27: =J17+$N$11 -> 14647753
C28: 0.1 | D28: =D18+$N$11 -> 26149397 | E28: =E18+$N$11 -> 26098665 | F28: =F18+$N$11 -> 26047664 | G28: =G18+$N$11 -> 25996527 | H28: =H18+$N$11 -> 25945388 | I28: =I18+$N$11 -> 25894377 | J28: =J18+$N$11 -> 25793234
C30: Table 3: Property Advantage vs. Liquid Portfolio ($)
C31: Land Appr. ↓ Alt. CAGR → | D31: 0.03 | E31: 0.04 | F31: 0.05 | G31: 0.06 | H31: 0.07 | I31: 0.08 | J31: 0.1
C32: -0.01 | D32: =(($C$6/$N$7)*(1+$C32)^20*$N$6)-(PV($H$5/12,($N$8-20)*12,-PMT($H$5/12,$N$8*12,-$N$4)))-$N$9+$N$11-$N$10*(1+D$31)^20 -> 1334551.2 | E32: =(($C$6/$N$7)*(1+$C32)^20*$N$6)-(PV($H$5/12,($N$8-20)*12,-PMT($H$5/12,$N$8*12,-$N$4)))-$N$9+$N$11-$N$10*(1+E$31)^20 -> 961474.67 | F32: =(($C$6/$N$7)*(1+$C32)^20*$N$6)-(PV($H$5/12,($N$8-20)*12,-PMT($H$5/12,$N$8*12,-$N$4)))-$N$9+$N$11-$N$10*(1+F$31)^20 -> 513627.51 | G32: =(($C$6/$N$7)*(1+$C32)^20*$N$6)-(PV($H$5/12,($N$8-20)*12,-PMT($H$5/12,$N$8*12,-$N$4)))-$N$9+$N$11-$N$10*(1+G$31)^20 -> -23041.281 | H32: =(($C$6/$N$7)*(1+$C32)^20*$N$6)-(PV($H$5/12,($N$8-20)*12,-PMT($H$5/12,$N$8*12,-$N$4)))-$N$9+$N$11-$N$10*(1+H$31)^20 -> -665051.25 | I32: =(($C$6/$N$7)*(1+$C32)^20*$N$6)-(PV($H$5/12,($N$8-20)*12,-PMT($H$5/12,$N$8*12,-$N$4)))-$N$9+$N$11-$N$10*(1+I$31)^20 -> -1431794.5 | J32: =(($C$6/$N$7)*(1+$C32)^20*$N$6)-(PV($H$5/12,($N$8-20)*12,-PMT($H$5/12,$N$8*12,-$N$4)))-$N$9+$N$11-$N$10*(1+J$31)^20 -> -3434274.5
C33: 0 | D33: =(($C$6/$N$7)*(1+$C33)^20*$N$6)-(PV($H$5/12,($N$8-20)*12,-PMT($H$5/12,$N$8*12,-$N$4)))-$N$9+$N$11-$N$10*(1+D$31)^20 -> 2044714.1 | E33: =(($C$6/$N$7)*(1+$C33)^20*$N$6)-(PV($H$5/12,($N$8-20)*12,-PMT($H$5/12,$N$8*12,-$N$4)))-$N$9+$N$11-$N$10*(1+E$31)^20 -> 1671637.6 | F33: =(($C$6/$N$7)*(1+$C33)^20*$N$6)-(PV($H$5/12,($N$8-20)*12,-PMT($H$5/12,$N$8*12,-$N$4)))-$N$9+$N$11-$N$10*(1+F$31)^20 -> 1223790.5 | G33: =(($C$6/$N$7)*(1+$C33)^20*$N$6)-(PV($H$5/12,($N$8-20)*12,-PMT($H$5/12,$N$8*12,-$N$4)))-$N$9+$N$11-$N$10*(1+G$31)^20 -> 687121.66 | H33: =(($C$6/$N$7)*(1+$C33)^20*$N$6)-(PV($H$5/12,($N$8-20)*12,-PMT($H$5/12,$N$8*12,-$N$4)))-$N$9+$N$11-$N$10*(1+H$31)^20 -> 45111.69 | I33: =(($C$6/$N$7)*(1+$C33)^20*$N$6)-(PV($H$5/12,($N$8-20)*12,-PMT($H$5/12,$N$8*12,-$N$4)))-$N$9+$N$11-$N$10*(1+I$31)^20 -> -721631.54 | J33: =(($C$6/$N$7)*(1+$C33)^20*$N$6)-(PV($H$5/12,($N$8-20)*12,-PMT($H$5/12,$N$8*12,-$N$4)))-$N$9+$N$11-$N$10*(1+J$31)^20 -> -2724111.5
C34: 0.02 | D34: =(($C$6/$N$7)*(1+$C34)^20*$N$6)-(PV($H$5/12,($N$8-20)*12,-PMT($H$5/12,$N$8*12,-$N$4)))-$N$9+$N$11-$N$10*(1+D$31)^20 -> 3939909 | E34: =(($C$6/$N$7)*(1+$C34)^20*$N$6)-(PV($H$5/12,($N$8-20)*12,-PMT($H$5/12,$N$8*12,-$N$4)))-$N$9+$N$11-$N$10*(1+E$31)^20 -> 3566832.5 | F34: =(($C$6/$N$7)*(1+$C34)^20*$N$6)-(PV($H$5/12,($N$8-20)*12,-PMT($H$5/12,$N$8*12,-$N$4)))-$N$9+$N$11-$N$10*(1+F$31)^20 -> 3118985.3 | G34: =(($C$6/$N$7)*(1+$C34)^20*$N$6)-(PV($H$5/12,($N$8-20)*12,-PMT($H$5/12,$N$8*12,-$N$4)))-$N$9+$N$11-$N$10*(1+G$31)^20 -> 2582316.5 | H34: =(($C$6/$N$7)*(1+$C34)^20*$N$6)-(PV($H$5/12,($N$8-20)*12,-PMT($H$5/12,$N$8*12,-$N$4)))-$N$9+$N$11-$N$10*(1+H$31)^20 -> 1940306.5 | I34: =(($C$6/$N$7)*(1+$C34)^20*$N$6)-(PV($H$5/12,($N$8-20)*12,-PMT($H$5/12,$N$8*12,-$N$4)))-$N$9+$N$11-$N$10*(1+I$31)^20 -> 1173563.3 | J34: =(($C$6/$N$7)*(1+$C34)^20*$N$6)-(PV($H$5/12,($N$8-20)*12,-PMT($H$5/12,$N$8*12,-$N$4)))-$N$9+$N$11-$N$10*(1+J$31)^20 -> -828916.67
C35: 0.03 | D35: =(($C$6/$N$7)*(1+$C35)^20*$N$6)-(PV($H$5/12,($N$8-20)*12,-PMT($H$5/12,$N$8*12,-$N$4)))-$N$9+$N$11-$N$10*(1+D$31)^20 -> 5188548 | E35: =(($C$6/$N$7)*(1+$C35)^20*$N$6)-(PV($H$5/12,($N$8-20)*12,-PMT($H$5/12,$N$8*12,-$N$4)))-$N$9+$N$11-$N$10*(1+E$31)^20 -> 4815471.4 | F35: =(($C$6/$N$7)*(1+$C35)^20*$N$6)-(PV($H$5/12,($N$8-20)*12,-PMT($H$5/12,$N$8*12,-$N$4)))-$N$9+$N$11-$N$10*(1+F$31)^20 -> 4367624.3 | G35: =(($C$6/$N$7)*(1+$C35)^20*$N$6)-(PV($H$5/12,($N$8-20)*12,-PMT($H$5/12,$N$8*12,-$N$4)))-$N$9+$N$11-$N$10*(1+G$31)^20 -> 3830955.5 | H35: =(($C$6/$N$7)*(1+$C35)^20*$N$6)-(PV($H$5/12,($N$8-20)*12,-PMT($H$5/12,$N$8*12,-$N$4)))-$N$9+$N$11-$N$10*(1+H$31)^20 -> 3188945.5 | I35: =(($C$6/$N$7)*(1+$C35)^20*$N$6)-(PV($H$5/12,($N$8-20)*12,-PMT($H$5/12,$N$8*12,-$N$4)))-$N$9+$N$11-$N$10*(1+I$31)^20 -> 2422202.3 | J35: =(($C$6/$N$7)*(1+$C35)^20*$N$6)-(PV($H$5/12,($N$8-20)*12,-PMT($H$5/12,$N$8*12,-$N$4)))-$N$9+$N$11-$N$10*(1+J$31)^20 -> 419722.3
C36: 0.05 | D36: =(($C$6/$N$7)*(1+$C36)^20*$N$6)-(PV($H$5/12,($N$8-20)*12,-PMT($H$5/12,$N$8*12,-$N$4)))-$N$9+$N$11-$N$10*(1+D$31)^20 -> 8492575.2 | E36: =(($C$6/$N$7)*(1+$C36)^20*$N$6)-(PV($H$5/12,($N$8-20)*12,-PMT($H$5/12,$N$8*12,-$N$4)))-$N$9+$N$11-$N$10*(1+E$31)^20 -> 8119498.7 | F36: =(($C$6/$N$7)*(1+$C36)^20*$N$6)-(PV($H$5/12,($N$8-20)*12,-PMT($H$5/12,$N$8*12,-$N$4)))-$N$9+$N$11-$N$10*(1+F$31)^20 -> 7671651.5 | G36: =(($C$6/$N$7)*(1+$C36)^20*$N$6)-(PV($H$5/12,($N$8-20)*12,-PMT($H$5/12,$N$8*12,-$N$4)))-$N$9+$N$11-$N$10*(1+G$31)^20 -> 7134982.7 | H36: =(($C$6/$N$7)*(1+$C36)^20*$N$6)-(PV($H$5/12,($N$8-20)*12,-PMT($H$5/12,$N$8*12,-$N$4)))-$N$9+$N$11-$N$10*(1+H$31)^20 -> 6492972.7 | I36: =(($C$6/$N$7)*(1+$C36)^20*$N$6)-(PV($H$5/12,($N$8-20)*12,-PMT($H$5/12,$N$8*12,-$N$4)))-$N$9+$N$11-$N$10*(1+I$31)^20 -> 5726229.5 | J36: =(($C$6/$N$7)*(1+$C36)^20*$N$6)-(PV($H$5/12,($N$8-20)*12,-PMT($H$5/12,$N$8*12,-$N$4)))-$N$9+$N$11-$N$10*(1+J$31)^20 -> 3723749.5
C37: 0.07 | D37: =(($C$6/$N$7)*(1+$C37)^20*$N$6)-(PV($H$5/12,($N$8-20)*12,-PMT($H$5/12,$N$8*12,-$N$4)))-$N$9+$N$11-$N$10*(1+D$31)^20 -> 13236484 | E37: =(($C$6/$N$7)*(1+$C37)^20*$N$6)-(PV($H$5/12,($N$8-20)*12,-PMT($H$5/12,$N$8*12,-$N$4)))-$N$9+$N$11-$N$10*(1+E$31)^20 -> 12863407 | F37: =(($C$6/$N$7)*(1+$C37)^20*$N$6)-(PV($H$5/12,($N$8-20)*12,-PMT($H$5/12,$N$8*12,-$N$4)))-$N$9+$N$11-$N$10*(1+F$31)^20 -> 12415560 | G37: =(($C$6/$N$7)*(1+$C37)^20*$N$6)-(PV($H$5/12,($N$8-20)*12,-PMT($H$5/12,$N$8*12,-$N$4)))-$N$9+$N$11-$N$10*(1+G$31)^20 -> 11878891 | H37: =(($C$6/$N$7)*(1+$C37)^20*$N$6)-(PV($H$5/12,($N$8-20)*12,-PMT($H$5/12,$N$8*12,-$N$4)))-$N$9+$N$11-$N$10*(1+H$31)^20 -> 11236881 | I37: =(($C$6/$N$7)*(1+$C37)^20*$N$6)-(PV($H$5/12,($N$8-20)*12,-PMT($H$5/12,$N$8*12,-$N$4)))-$N$9+$N$11-$N$10*(1+I$31)^20 -> 10470138 | J37: =(($C$6/$N$7)*(1+$C37)^20*$N$6)-(PV($H$5/12,($N$8-20)*12,-PMT($H$5/12,$N$8*12,-$N$4)))-$N$9+$N$11-$N$10*(1+J$31)^20 -> 8467657.9
C38: 0.1 | D38: =(($C$6/$N$7)*(1+$C38)^20*$N$6)-(PV($H$5/12,($N$8-20)*12,-PMT($H$5/12,$N$8*12,-$N$4)))-$N$9+$N$11-$N$10*(1+D$31)^20 -> 24381964 | E38: =(($C$6/$N$7)*(1+$C38)^20*$N$6)-(PV($H$5/12,($N$8-20)*12,-PMT($H$5/12,$N$8*12,-$N$4)))-$N$9+$N$11-$N$10*(1+E$31)^20 -> 24008887 | F38: =(($C$6/$N$7)*(1+$C38)^20*$N$6)-(PV($H$5/12,($N$8-20)*12,-PMT($H$5/12,$N$8*12,-$N$4)))-$N$9+$N$11-$N$10*(1+F$31)^20 -> 23561040 | G38: =(($C$6/$N$7)*(1+$C38)^20*$N$6)-(PV($H$5/12,($N$8-20)*12,-PMT($H$5/12,$N$8*12,-$N$4)))-$N$9+$N$11-$N$10*(1+G$31)^20 -> 23024371 | H38: =(($C$6/$N$7)*(1+$C38)^20*$N$6)-(PV($H$5/12,($N$8-20)*12,-PMT($H$5/12,$N$8*12,-$N$4)))-$N$9+$N$11-$N$10*(1+H$31)^20 -> 22382361 | I38: =(($C$6/$N$7)*(1+$C38)^20*$N$6)-(PV($H$5/12,($N$8-20)*12,-PMT($H$5/12,$N$8*12,-$N$4)))-$N$9+$N$11-$N$10*(1+I$31)^20 -> 21615618 | J38: =(($C$6/$N$7)*(1+$C38)^20*$N$6)-(PV($H$5/12,($N$8-20)*12,-PMT($H$5/12,$N$8*12,-$N$4)))-$N$9+$N$11-$N$10*(1+J$31)^20 -> 19613138

Sheet Scenario Tables
A1: SCENARIO TABLES — Edit values below to customize each dropdown option
A3: 1. LAND APPRECIATION RATES (% p.a.)
A4: Scenario | B4: Active? | C4: HDB 1984 | D4: Condo 99LH | E4: FH Condo | F4: HDB 2005 | G4: HDB 2015 | H4: FH Landed (Prime)
A5: Pessimistic | B5: =IF(Assumptions!B34="Pessimistic","✔","") | C5: 0.01 | D5: 0.01 | E5: 0.01 | F5: 0.01 | G5: 0.01 | H5: 0.01
A6: Base | B6: =IF(Assumptions!B34="Base","✔","") | C6: 0.025 | D6: 0.025 | E6: 0.025 | F6: 0.025 | G6: 0.025 | H6: 0.025
A7: Optimistic | B7: =IF(Assumptions!B34="Optimistic","✔","") | C7: 0.04 | D7: 0.04 | E7: 0.04 | F7: 0.04 | G7: 0.04 | H7: 0.04
A8: Custom | B8: =IF(Assumptions!B34="Custom","✔","") -> ✔ | C8: 0.02 | D8: 0.03 | E8: 0.04 | F8: 0.03 | G8: 0.03 | H8: 0.05
A10: 2. MORTGAGE RATE SCENARIOS
A11: Scenario | B11: Active? | C11: Mortgage Rate | D11: Description
A12: Base | B12: =IF(Assumptions!C18="Base","✔","") -> ✔ | C12: =Assumptions!C15 -> 0.01671 | D12: SORA + Bank Spread (auto-calculated)
A13: Stress | B13: =IF(Assumptions!C18="Stress","✔","") | C13: =Assumptions!C16 -> 0.035 | D13: Edit in Assumptions!C16
A14: Severe | B14: =IF(Assumptions!C18="Severe","✔","") | C14: =Assumptions!C17 -> 0.05 | D14: Edit in Assumptions!C17
A16: 3. ABSD RATES BY RESIDENCY STATUS
A17: Residency Status | B17: Active? | C17: ABSD Rate | D17: Description
A18: SC 1st Property | B18: =IF(Assumptions!C10="SC 1st Property","✔","") -> ✔ | C18: 0 | D18: Singapore Citizen, 1st property
A19: SC 2nd Property | B19: =IF(Assumptions!C10="SC 2nd Property","✔","") | C19: 0.2 | D19: Singapore Citizen, 2nd property
A20: PR | B20: =IF(Assumptions!C10="PR","✔","") | C20: 0.05 | D20: Permanent Resident
A22: 4. MORTGAGE RATES BY PROPERTY
A23: Scenario | B23: Active? | C23: HDB 1984 | D23: Condo 99LH | E23: FH Condo | F23: HDB 2005 | G23: HDB 2015 | H23: FH Landed (Prime)
A24: Base | B24: =IF(Assumptions!C18="Base","✔","") -> ✔ | C24: 0.026 | D24: =Assumptions!C15 -> 0.01671 | E24: =Assumptions!C15 -> 0.01671 | F24: 0.026 | G24: 0.026 | H24: =Assumptions!C15 -> 0.01671
A25: Stress | B25: =IF(Assumptions!C18="Stress","✔","") | C25: 0.026 | D25: =Assumptions!C16 -> 0.035 | E25: =Assumptions!C16 -> 0.035 | F25: 0.026 | G25: 0.026 | H25: =Assumptions!C16 -> 0.035
A26: Severe | B26: =IF(Assumptions!C18="Severe","✔","") | C26: 0.026 | D26: =Assumptions!C17 -> 0.05 | E26: =Assumptions!C17 -> 0.05 | F26: 0.026 | G26: 0.026 | H26: =Assumptions!C17 -> 0.05
A27: → Active Rate | C27: =INDEX(C24:C26,MATCH(Assumptions!C18,A24:A26,0)) -> 0.026 | D27: =INDEX(D24:D26,MATCH(Assumptions!C18,A24:A26,0)) -> 0.01671 | E27: =INDEX(E24:E26,MATCH(Assumptions!C18,A24:A26,0)) -> 0.01671 | F27: =INDEX(F24:F26,MATCH(Assumptions!C18,A24:A26,0)) -> 0.026 | G27: =INDEX(G24:G26,MATCH(Assumptions!C18,A24:A26,0)) -> 0.026 | H27: =INDEX(H24:H26,MATCH(Assumptions!C18,A24:A26,0)) -> 0.01671
A33: HOW TO USE
A34: ① Edit blue values in the tables above to change what each scenario means.
A35: ② Switch scenarios using the dropdowns in the Assumptions sheet (B34, C18, C10).
A36: ③ The ✔ column shows which scenario is currently active — the model auto-reads from this table.
A37: ④ Land appreciation: each property can have its own rate per scenario (edit C5:H7 independently).
A38: ⑤ "Custom" row in Table 1 links to Assumptions!I34 — type your rate there or edit I34 directly.

Sheet Opportunity Cost
A1: OPPORTUNITY COST ANALYSIS — LIQUID CAPITAL DEPLOYMENT
A3: CAPITAL DEPLOYMENT SUMMARY
C4: HDB 1984 | D4: Condo 99LH | E4: FH Condo | G4: HDB 2005 | H4: HDB 2015 | I4: FH Landed (Prime)
A5: Total Net Worth | C5: =Assumptions!C7 -> 800000 | D5: =Assumptions!C7 -> 800000 | E5: =Assumptions!C7 -> 800000 | G5: =Assumptions!C7 -> 800000 | H5: =Assumptions!C7 -> 800000 | I5: =Assumptions!C7 -> 800000
A6: Cash Deployed in Property (Day 1) | C6: ='HDB 1984'!C9 -> 262200 | D6: ='Condo 99LH'!C9 -> 613200 | E6: ='FH Condo'!C9 -> 1061200 | G6: ='HDB 2005'!C9 -> 72200 | H6: ='HDB 2015'!C9 -> 262200 | I6: ='FH Landed (Prime)'!C9 -> 2053200
A7: CPF OA Deployed | C7: ='HDB 1984'!C7 -> 150000 | D7: ='Condo 99LH'!C7 -> 150000 | E7: ='FH Condo'!C7 -> 150000 | G7: ='HDB 2005'!C7 -> 150000 | H7: ='HDB 2015'!C7 -> 150000 | I7: ='FH Landed (Prime)'!C7 -> 150000
A8: Remaining Liquid Capital | C8: =C5-C6 -> 537800 | D8: =D5-D6 -> 186800 | E8: =E5-E6 -> -261200 | G8: =G5-G6 -> 727800 | H8: =H5-H6 -> 537800 | I8: =I5-I6 -> -1253200
A9: Benchmark Return (CAGR) | C9: =Assumptions!C54 -> 0.055 | D9: =Assumptions!C54 -> 0.055 | E9: =Assumptions!C54 -> 0.055 | G9: =Assumptions!C54 -> 0.055 | H9: =Assumptions!C54 -> 0.055 | I9: =Assumptions!C54 -> 0.055
A10: Annual Mortgage Cash Outflow | C10: ='HDB 1984'!C12 -> 50442.804 | D10: ='Condo 99LH'!C12 -> 79511.645 | E10: ='FH Condo'!C12 -> 124038.17 | G10: ='HDB 2005'!C12 -> 28103.848 | H10: ='HDB 2015'!C12 -> 50442.804 | I10: ='FH Landed (Prime)'!C12 -> 222632.61
A12: 20-YEAR LIQUID PORTFOLIO GROWTH
A13: Year | B13: Age | C13: HDB Liquid Portfolio | D13: Condo Liquid Portfolio | E13: FH Liquid Portfolio | F13: No Property Full Portfolio | G13: HDB 2005 Liquid Portfolio | H13: HDB 2015 Liquid Portfolio | I13: FH Landed Liquid Portfolio
A14: 0 | B14: =Assumptions!C4 -> 32 | C14: =$C$8 -> 537800 | D14: =$D$8 -> 186800 | E14: =$E$8 -> -261200 | F14: =Assumptions!C7 -> 800000 | G14: =$G$8 -> 727800 | H14: =$H$8 -> 537800 | I14: =$I$8 -> -1253200
A15: =A14+1 -> 1 | B15: =B14+1 -> 33 | C15: =C14*(1+$C$9)-$C$10 -> 516936.2 | D15: =D14*(1+$D$9)-$D$10 -> 117562.36 | E15: =E14*(1+$E$9)-$E$10 -> -399604.17 | F15: =F14*(1+Assumptions!$C$54) -> 844000 | G15: =G14*(1+$G$9)-$G$10 -> 739725.15 | H15: =H14*(1+$H$9)-$H$10 -> 516936.2 | I15: =I14*(1+$I$9)-$I$10 -> -1544758.6
A16: =A15+1 -> 2 | B16: =B15+1 -> 34 | C16: =C15*(1+$C$9)-$C$10 -> 494924.88 | D16: =D15*(1+$D$9)-$D$10 -> 44516.64 | E16: =E15*(1+$E$9)-$E$10 -> -545620.56 | F16: =F15*(1+Assumptions!$C$54) -> 890420 | G16: =G15*(1+$G$9)-$G$10 -> 752306.19 | H16: =H15*(1+$H$9)-$H$10 -> 494924.88 | I16: =I15*(1+$I$9)-$I$10 -> -1852352.9
A17: =A16+1 -> 3 | B17: =B16+1 -> 35 | C17: =C16*(1+$C$9)-$C$10 -> 471702.95 | D17: =D16*(1+$D$9)-$D$10 -> -32546.59 | E17: =E16*(1+$E$9)-$E$10 -> -699667.86 | F17: =F16*(1+Assumptions!$C$54) -> 939393.1 | G17: =G16*(1+$G$9)-$G$10 -> 765579.18 | H17: =H16*(1+$H$9)-$H$10 -> 471702.95 | I17: =I16*(1+$I$9)-$I$10 -> -2176865
A18: =A17+1 -> 4 | B18: =B17+1 -> 36 | C18: =C17*(1+$C$9)-$C$10 -> 447203.81 | D18: =D17*(1+$D$9)-$D$10 -> -113848.3 | E18: =E17*(1+$E$9)-$E$10 -> -862187.76 | F18: =F17*(1+Assumptions!$C$54) -> 991059.72 | G18: =G17*(1+$G$9)-$G$10 -> 779582.19 | H18: =H17*(1+$H$9)-$H$10 -> 447203.81 | I18: =I17*(1+$I$9)-$I$10 -> -2519225.1
A19: =A18+1 -> 5 | B19: =B18+1 -> 37 | C19: =C18*(1+$C$9)-$C$10 -> 421357.21 | D19: =D18*(1+$D$9)-$D$10 -> -199621.6 | E19: =E18*(1+$E$9)-$E$10 -> -1033646.2 | F19: =F18*(1+Assumptions!$C$54) -> 1045568 | G19: =G18*(1+$G$9)-$G$10 -> 794355.36 | H19: =H18*(1+$H$9)-$H$10 -> 421357.21 | I19: =I18*(1+$I$9)-$I$10 -> -2880415.1
A20: =A19+1 -> 6 | B20: =B19+1 -> 38 | C20: =C19*(1+$C$9)-$C$10 -> 394089.06 | D20: =D19*(1+$D$9)-$D$10 -> -290112.43 | E20: =E19*(1+$E$9)-$E$10 -> -1214535 | F20: =F19*(1+Assumptions!$C$54) -> 1103074.2 | G20: =G19*(1+$G$9)-$G$10 -> 809941.06 | H20: =H19*(1+$H$9)-$H$10 -> 394089.06 | I20: =I19*(1+$I$9)-$I$10 -> -3261470.6
A21: =A20+1 -> 7 | B21: =B20+1 -> 39 | C21: =C20*(1+$C$9)-$C$10 -> 365321.15 | D21: =D20*(1+$D$9)-$D$10 -> -385580.26 | E21: =E20*(1+$E$9)-$E$10 -> -1405372.5 | F21: =F20*(1+Assumptions!$C$54) -> 1163743.3 | G21: =G20*(1+$G$9)-$G$10 -> 826383.97 | H21: =H20*(1+$H$9)-$H$10 -> 365321.15 | I21: =I20*(1+$I$9)-$I$10 -> -3663484
A22: =A21+1 -> 8 | B22: =B21+1 -> 40 | C22: =C21*(1+$C$9)-$C$10 -> 334971.01 | D22: =D21*(1+$D$9)-$D$10 -> -486298.82 | E22: =E21*(1+$E$9)-$E$10 -> -1606706.2 | F22: =F21*(1+Assumptions!$C$54) -> 1227749.2 | G22: =G21*(1+$G$9)-$G$10 -> 843731.24 | H22: =H21*(1+$H$9)-$H$10 -> 334971.01 | I22: =I21*(1+$I$9)-$I$10 -> -4087608.3
A23: =A22+1 -> 9 | B23: =B22+1 -> 41 | C23: =C22*(1+$C$9)-$C$10 -> 302951.61 | D23: =D22*(1+$D$9)-$D$10 -> -592556.9 | E23: =E22*(1+$E$9)-$E$10 -> -1819113.2 | F23: =F22*(1+Assumptions!$C$54) -> 1295275.4 | G23: =G22*(1+$G$9)-$G$10 -> 862032.61 | H23: =H22*(1+$H$9)-$H$10 -> 302951.61 | I23: =I22*(1+$I$9)-$I$10 -> -4535059.3
A24: =A23+1 -> 10 | B24: =B23+1 -> 42 | C24: =C23*(1+$C$9)-$C$10 -> 269171.15 | D24: =D23*(1+$D$9)-$D$10 -> -704659.17 | E24: =E23*(1+$E$9)-$E$10 -> -2043202.6 | F24: =F23*(1+Assumptions!$C$54) -> 1366515.6 | G24: =G23*(1+$G$9)-$G$10 -> 881340.55 | H24: =H23*(1+$H$9)-$H$10 -> 269171.15 | I24: =I23*(1+$I$9)-$I$10 -> -5007120.2
A25: =A24+1 -> 11 | B25: =B24+1 -> 43 | C25: =C24*(1+$C$9)-$C$10 -> 233532.76 | D25: =D24*(1+$D$9)-$D$10 -> -822927.07 | E25: =E24*(1+$E$9)-$E$10 -> -2279616.9 | F25: =F24*(1+Assumptions!$C$54) -> 1441673.9 | G25: =G24*(1+$G$9)-$G$10 -> 901710.44 | H25: =H24*(1+$H$9)-$H$10 -> 233532.76 | I25: =I24*(1+$I$9)-$I$10 -> -5505144.4
A26: =A25+1 -> 12 | B26: =B25+1 -> 44 | C26: =C25*(1+$C$9)-$C$10 -> 195934.25 | D26: =D25*(1+$D$9)-$D$10 -> -947699.71 | E26: =E25*(1+$E$9)-$E$10 -> -2529034 | F26: =F25*(1+Assumptions!$C$54) -> 1520966 | G26: =G25*(1+$G$9)-$G$10 -> 923200.66 | H26: =H25*(1+$H$9)-$H$10 -> 195934.25 | I26: =I25*(1+$I$9)-$I$10 -> -6030560
... A34: =A33+1 -> 20 | B34: =B33+1 -> 52 | C34: =C33*(1+$C$9)-$C$10 -> -189685.74 | D34: =D33*(1+$D$9)-$D$10 -> -2227400.2 | E34: =E33*(1+$E$9)-$E$10 -> -5087120.5 | F34: =F33*(1+Assumptions!$C$54) -> 2334206 | G34: =G33*(1+$G$9)-$G$10 -> 1143610 | H34: =H33*(1+$H$9)-$H$10 -> -189685.74 | I34: =I33*(1+$I$9)-$I$10 -> -11419358
A36: TERMINAL NET WORTH COMPARISON (YEAR 20)
C37: HDB 1984 | D37: Condo 99LH | E37: FH Condo | F37: No Property | G37: HDB 2005 | H37: HDB 2015 | I37: FH Landed
A38: Liquid Portfolio (Year 20) | C38: =C34 -> -189685.74 | D38: =D34 -> -2227400.2 | E38: =E34 -> -5087120.5 | F38: =F34 -> 2334206 | G38: =G34 -> 1143610 | H38: =H34 -> -189685.74 | I38: =I34 -> -11419358
A39: Property Equity (Net of CPF) | C39: ='HDB 1984'!Q35 -> 872887.87 | D39: ='Condo 99LH'!Q35 -> 2979508.9 | E39: ='FH Condo'!Q35 -> 7212238.5 | F39: 0 | G39: ='HDB 2005'!Q35 -> 728542.06 | H39: ='HDB 2015'!Q35 -> 1531984.7 | I39: ='FH Landed (Prime)'!Q35 -> 16332551
A40: TOTAL NET WORTH | C40: =C38+C39 -> 683202.13 | D40: =D38+D39 -> 752108.73 | E40: =E38+E39 -> 2125118.1 | F40: =F38+F39 -> 2334206 | G40: =G38+G39 -> 1872152.1 | H40: =H38+H39 -> 1342299 | I40: =I38+I39 -> 4913192.7
A41: NW vs. No Property | C41: =C40-F40 -> -1651003.9 | D41: =D40-F40 -> -1582097.3 | E41: =E40-F40 -> -209087.94 | F41: - | G41: =G40-F40 -> -462053.93 | H41: =H40-F40 -> -991906.99 | I41: =I40-F40 -> 2578986.7
A42: NW CAGR (20yr) | C42: =(C40/Assumptions!C7)^(1/20)-1 -> -0.0078599961 | D42: =(D40/Assumptions!C7)^(1/20)-1 -> -0.0030817831 | E42: =(E40/Assumptions!C7)^(1/20)-1 -> 0.050061302 | F42: =(F40/Assumptions!C7)^(1/20)-1 -> 0.055 | G42: =(G40/Assumptions!C7)^(1/20)-1 -> 0.043428168 | H42: =(H40/Assumptions!C7)^(1/20)-1 -> 0.026214068 | I42: =(I40/Assumptions!C7)^(1/20)-1 -> 0.094998919
A44: ADVANCED PERFORMANCE METRICS
C45: HDB 1984 | D45: Condo 99LH | E45: FH Condo | F45: No Property | G45: HDB 2005 | H45: HDB 2015 | I45: FH Landed
A46: Annualized ROE on Equity | C46: ='HDB 1984'!I40 -> 0.048579418 | D46: ='Condo 99LH'!I40 -> 0.073812702 | E46: ='FH Condo'!I40 -> 0.094742578 | F46: - | G46: ='HDB 2005'!I40 -> 0.073631354 | H46: ='HDB 2015'!I40 -> 0.074152745 | I46: ='FH Landed (Prime)'!I40 -> 0.1059952
A47: Leverage Amplification (ROE ÷ Land Appr.) | C47: =C46/Assumptions!C34 -> 2.4289709 | D47: =D46/Assumptions!D34 -> 2.4604234 | E47: =E46/Assumptions!E34 -> 2.3685645 | F47: - | G47: =G46/Assumptions!F34 -> 2.4543785 | H47: =H46/Assumptions!G34 -> 2.4717582 | I47: =I46/Assumptions!H34 -> 2.119904
A48: Real NW CAGR (Inflation-Adj) | C48: =C42-Assumptions!C43 -> -0.032859996 | D48: =D42-Assumptions!C43 -> -0.028081783 | E48: =E42-Assumptions!C43 -> 0.025061302 | F48: =F42-Assumptions!C43 -> 0.03 | G48: =G42-Assumptions!C43 -> 0.018428168 | H48: =H42-Assumptions!C43 -> 0.0012140681 | I48: =I42-Assumptions!C43 -> 0.069998919
A49: Equity Multiple (Terminal / Day-1) | C49: =C39/'HDB 1984'!C10 -> 2.1176319 | D49: =D39/'Condo 99LH'!C10 -> 3.9039687 | E49: =E39/'FH Condo'!C10 -> 5.9546223 | F49: - | G49: =G39/'HDB 2005'!C10 -> 3.2787672 | H49: =H39/'HDB 2015'!C10 -> 3.7166054 | I49: =I39/'FH Landed (Prime)'!C10 -> 7.4131041
A51: 🏆 WINNER BY METRIC
A52: Highest Total NW | C52: =IF(C40=MAX(C40,D40,E40,F40,G40,H40,I40),"⭐","") | D52: =IF(D40=MAX(C40,D40,E40,F40,G40,H40,I40),"⭐","") | E52: =IF(E40=MAX(C40,D40,E40,F40,G40,H40,I40),"⭐","") | F52: =IF(F40=MAX(C40,D40,E40,F40,G40,H40,I40),"⭐","") | G52: =IF(G40=MAX(C40,D40,E40,F40,G40,H40,I40),"⭐","") | H52: =IF(H40=MAX(C40,D40,E40,F40,G40,H40,I40),"⭐","") | I52: =IF(I40=MAX(C40,D40,E40,F40,G40,H40,I40),"⭐","") -> ⭐
A53: Highest ROE | C53: =IF(C46=MAX(C46,D46,E46,G46,H46,I46),"⭐","") | D53: =IF(D46=MAX(C46,D46,E46,G46,H46,I46),"⭐","") | E53: =IF(E46=MAX(C46,D46,E46,G46,H46,I46),"⭐","") | F53: - | G53: =IF(G46=MAX(C46,D46,E46,G46,H46,I46),"⭐","") | H53: =IF(H46=MAX(C46,D46,E46,G46,H46,I46),"⭐","") | I53: =IF(I46=MAX(C46,D46,E46,G46,H46,I46),"⭐","") -> ⭐
A54: Best Leverage Amplification | C54: =IF(C47=MAX(C47,D47,E47,G47,H47,I47),"⭐","") | D54: =IF(D47=MAX(C47,D47,E47,G47,H47,I47),"⭐","") | E54: =IF(E47=MAX(C47,D47,E47,G47,H47,I47),"⭐","") | F54: - | G54: =IF(G47=MAX(C47,D47,E47,G47,H47,I47),"⭐","") | H54: =IF(H47=MAX(C47,D47,E47,G47,H47,I47),"⭐","") -> ⭐ | I54: =IF(I47=MAX(C47,D47,E47,G47,H47,I47),"⭐","")

Sheet Bala Table
A1: Remaining Lease (Years) | B1: % of Freehold Value | C1: Source: SLA Bala's Table | D1: Lending Restriction | E1: End-of-Horizon Restriction
A2: 99 | B2: 0.9 | D2: =IF(A2<20,"🚫 No bank financing",IF(A2<30,"⚠️ Very restricted; max 60% LTV",IF(A2<(95-Assumptions!$C$4),"⚠️ Tenure capped (loan+age ≤ lease)","✅ Standard lending"))) -> ✅ Standard lending | E2: =IF((A2-Assumptions!$C$5)<0,"🚫 Lease expired within horizon",IF((A2-Assumptions!$C$5)<20,"🚫 No bank financing",IF((A2-Assumptions!$C$5)<30,"⚠️ Very restricted; max 60% LTV",IF((A2-Assumptions!$C$5)<(95-(Assumptions!$C$4+Assumptions!$C$5)),"⚠️ Tenure capped (loan+age ≤ lease)","✅ Standard lending")))) -> ✅ Standard lending
A3: 98 | B3: 0.895 | D3: =IF(A3<20,"🚫 No bank financing",IF(A3<30,"⚠️ Very restricted; max 60% LTV",IF(A3<(95-Assumptions!$C$4),"⚠️ Tenure capped (loan+age ≤ lease)","✅ Standard lending"))) -> ✅ Standard lending | E3: =IF((A3-Assumptions!$C$5)<0,"🚫 Lease expired within horizon",IF((A3-Assumptions!$C$5)<20,"🚫 No bank financing",IF((A3-Assumptions!$C$5)<30,"⚠️ Very restricted; max 60% LTV",IF((A3-Assumptions!$C$5)<(95-(Assumptions!$C$4+Assumptions!$C$5)),"⚠️ Tenure capped (loan+age ≤ lease)","✅ Standard lending")))) -> ✅ Standard lending
A4: 97 | B4: 0.89 | D4: =IF(A4<20,"🚫 No bank financing",IF(A4<30,"⚠️ Very restricted; max 60% LTV",IF(A4<(95-Assumptions!$C$4),"⚠️ Tenure capped (loan+age ≤ lease)","✅ Standard lending"))) -> ✅ Standard lending | E4: =IF((A4-Assumptions!$C$5)<0,"🚫 Lease expired within horizon",IF((A4-Assumptions!$C$5)<20,"🚫 No bank financing",IF((A4-Assumptions!$C$5)<30,"⚠️ Very restricted; max 60% LTV",IF((A4-Assumptions!$C$5)<(95-(Assumptions!$C$4+Assumptions!$C$5)),"⚠️ Tenure capped (loan+age ≤ lease)","✅ Standard lending")))) -> ✅ Standard lending
A5: 96 | B5: 0.885 | D5: =IF(A5<20,"🚫 No bank financing",IF(A5<30,"⚠️ Very restricted; max 60% LTV",IF(A5<(95-Assumptions!$C$4),"⚠️ Tenure capped (loan+age ≤ lease)","✅ Standard lending"))) -> ✅ Standard lending | E5: =IF((A5-Assumptions!$C$5)<0,"🚫 Lease expired within horizon",IF((A5-Assumptions!$C$5)<20,"🚫 No bank financing",IF((A5-Assumptions!$C$5)<30,"⚠️ Very restricted; max 60% LTV",IF((A5-Assumptions!$C$5)<(95-(Assumptions!$C$4+Assumptions!$C$5)),"⚠️ Tenure capped (loan+age ≤ lease)","✅ Standard lending")))) -> ✅ Standard lending
A6: 95 | B6: 0.88 | D6: =IF(A6<20,"🚫 No bank financing",IF(A6<30,"⚠️ Very restricted; max 60% LTV",IF(A6<(95-Assumptions!$C$4),"⚠️ Tenure capped (loan+age ≤ lease)","✅ Standard lending"))) -> ✅ Standard lending | E6: =IF((A6-Assumptions!$C$5)<0,"🚫 Lease expired within horizon",IF((A6-Assumptions!$C$5)<20,"🚫 No bank financing",IF((A6-Assumptions!$C$5)<30,"⚠️ Very restricted; max 60% LTV",IF((A6-Assumptions!$C$5)<(95-(Assumptions!$C$4+Assumptions!$C$5)),"⚠️ Tenure capped (loan+age ≤ lease)","✅ Standard lending")))) -> ✅ Standard lending
A7: 94 | B7: 0.875 | D7: =IF(A7<20,"🚫 No bank financing",IF(A7<30,"⚠️ Very restricted; max 60% LTV",IF(A7<(95-Assumptions!$C$4),"⚠️ Tenure capped (loan+age ≤ lease)","✅ Standard lending"))) -> ✅ Standard lending | E7: =IF((A7-Assumptions!$C$5)<0,"🚫 Lease expired within horizon",IF((A7-Assumptions!$C$5)<20,"🚫 No bank financing",IF((A7-Assumptions!$C$5)<30,"⚠️ Very restricted; max 60% LTV",IF((A7-Assumptions!$C$5)<(95-(Assumptions!$C$4+Assumptions!$C$5)),"⚠️ Tenure capped (loan+age ≤ lease)","✅ Standard lending")))) -> ✅ Standard lending
A8: 93 | B8: 0.87 | D8: =IF(A8<20,"🚫 No bank financing",IF(A8<30,"⚠️ Very restricted; max 60% LTV",IF(A8<(95-Assumptions!$C$4),"⚠️ Tenure capped (loan+age ≤ lease)","✅ Standard lending"))) -> ✅ Standard lending | E8: =IF((A8-Assumptions!$C$5)<0,"🚫 Lease expired within horizon",IF((A8-Assumptions!$C$5)<20,"🚫 No bank financing",IF((A8-Assumptions!$C$5)<30,"⚠️ Very restricted; max 60% LTV",IF((A8-Assumptions!$C$5)<(95-(Assumptions!$C$4+Assumptions!$C$5)),"⚠️ Tenure capped (loan+age ≤ lease)","✅ Standard lending")))) -> ✅ Standard lending
A9: 92 | B9: 0.865 | D9: =IF(A9<20,"🚫 No bank financing",IF(A9<30,"⚠️ Very restricted; max 60% LTV",IF(A9<(95-Assumptions!$C$4),"⚠️ Tenure capped (loan+age ≤ lease)","✅ Standard lending"))) -> ✅ Standard lending | E9: =IF((A9-Assumptions!$C$5)<0,"🚫 Lease expired within horizon",IF((A9-Assumptions!$C$5)<20,"🚫 No bank financing",IF((A9-Assumptions!$C$5)<30,"⚠️ Very restricted; max 60% LTV",IF((A9-Assumptions!$C$5)<(95-(Assumptions!$C$4+Assumptions!$C$5)),"⚠️ Tenure capped (loan+age ≤ lease)","✅ Standard lending")))) -> ✅ Standard lending
A10: 91 | B10: 0.855 | D10: =IF(A10<20,"🚫 No bank financing",IF(A10<30,"⚠️ Very restricted; max 60% LTV",IF(A10<(95-Assumptions!$C$4),"⚠️ Tenure capped (loan+age ≤ lease)","✅ Standard lending"))) -> ✅ Standard lending | E10: =IF((A10-Assumptions!$C$5)<0,"🚫 Lease expired within horizon",IF((A10-Assumptions!$C$5)<20,"🚫 No bank financing",IF((A10-Assumptions!$C$5)<30,"⚠️ Very restricted; max 60% LTV",IF((A10-Assumptions!$C$5)<(95-(Assumptions!$C$4+Assumptions!$C$5)),"⚠️ Tenure capped (loan+age ≤ lease)","✅ Standard lending")))) -> ✅ Standard lending
A11: 90 | B11: 0.85 | D11: =IF(A11<20,"🚫 No bank financing",IF(A11<30,"⚠️ Very restricted; max 60% LTV",IF(A11<(95-Assumptions!$C$4),"⚠️ Tenure capped (loan+age ≤ lease)","✅ Standard lending"))) -> ✅ Standard lending | E11: =IF((A11-Assumptions!$C$5)<0,"🚫 Lease expired within horizon",IF((A11-Assumptions!$C$5)<20,"🚫 No bank financing",IF((A11-Assumptions!$C$5)<30,"⚠️ Very restricted; max 60% LTV",IF((A11-Assumptions!$C$5)<(95-(Assumptions!$C$4+Assumptions!$C$5)),"⚠️ Tenure capped (loan+age ≤ lease)","✅ Standard lending")))) -> ✅ Standard lending
A12: 89 | B12: 0.845 | D12: =IF(A12<20,"🚫 No bank financing",IF(A12<30,"⚠️ Very restricted; max 60% LTV",IF(A12<(95-Assumptions!$C$4),"⚠️ Tenure capped (loan+age ≤ lease)","✅ Standard lending"))) -> ✅ Standard lending | E12: =IF((A12-Assumptions!$C$5)<0,"🚫 Lease expired within horizon",IF((A12-Assumptions!$C$5)<20,"🚫 No bank financing",IF((A12-Assumptions!$C$5)<30,"⚠️ Very restricted; max 60% LTV",IF((A12-Assumptions!$C$5)<(95-(Assumptions!$C$4+Assumptions!$C$5)),"⚠️ Tenure capped (loan+age ≤ lease)","✅ Standard lending")))) -> ✅ Standard lending
A13: 88 | B13: 0.84 | D13: =IF(A13<20,"🚫 No bank financing",IF(A13<30,"⚠️ Very restricted; max 60% LTV",IF(A13<(95-Assumptions!$C$4),"⚠️ Tenure capped (loan+age ≤ lease)","✅ Standard lending"))) -> ✅ Standard lending | E13: =IF((A13-Assumptions!$C$5)<0,"🚫 Lease expired within horizon",IF((A13-Assumptions!$C$5)<20,"🚫 No bank financing",IF((A13-Assumptions!$C$5)<30,"⚠️ Very restricted; max 60% LTV",IF((A13-Assumptions!$C$5)<(95-(Assumptions!$C$4+Assumptions!$C$5)),"⚠️ Tenure capped (loan+age ≤ lease)","✅ Standard lending")))) -> ✅ Standard lending
... A101: 0 | B101: 0 | D101: =IF(A101<20,"🚫 No bank financing",IF(A101<30,"⚠️ Very restricted; max 60% LTV",IF(A101<(95-Assumptions!$C$4),"⚠️ Tenure capped (loan+age ≤ lease)","✅ Standard lending"))) -> 🚫 No bank financing | E101: =IF((A101-Assumptions!$C$5)<0,"🚫 Lease expired within horizon",IF((A101-Assumptions!$C$5)<20,"🚫 No bank financing",IF((A101-Assumptions!$C$5)<30,"⚠️ Very restricted; max 60% LTV",IF((A101-Assumptions!$C$5)<(95-(Assumptions!$C$4+Assumptions!$C$5)),"⚠️ Tenure capped (loan+age ≤ lease)","✅ Standard lending")))) -> 🚫 Lease expired within horizon

Sheet HDB 1984
A1: HDB 1984 — LEVERAGED PROPERTY ANALYSIS
A3: CAPITAL STRUCTURE
A4: Purchase Price | C4: =Assumptions!C31 -> 1400000
A5: Loan Amount (75% LTV) | C5: =Assumptions!C22*Assumptions!C31 -> 1050000
A6: Cash Downpayment | C6: =Assumptions!C23*Assumptions!C31-C7 -> 200000
A7: CPF OA Used | C7: =MIN(Assumptions!C24*Assumptions!C31,Assumptions!C8) -> 150000
A8: Total Upfront Costs | C8: =Assumptions!C51 -> 62200
A9: Total Cash Outlay (Day 1) | C9: =C6+C8 -> 262200
A10: Total Equity at Risk (Cash + CPF) | C10: =C6+C7+C8 -> 412200
A11: Monthly Mortgage Payment | C11: =PMT('Scenario Tables'!C$27/12,Assumptions!C26*12,-C5) -> 4203.567
A12: Annual Mortgage Payment | C12: =C11*12 -> 50442.804
A14: Year | B14: Age | C14: Remaining Lease | D14: Bala Factor (%FH) | E14: FH Equiv. Land Value | F14: Leasehold Market Value | G14: Loan Balance | H14: Property Equity | I14: Annual Interest | J14: Annual Principal | K14: Rent / Imputed Rent (Annual) | L14: Maintenance + Prop Tax (+Mgmt) | M14: Net Holding Benefit (After Tax) | N14: Cumulative Net Benefit | O14: ROE on Equity (%) | P14: CPF Accrued Interest | Q14: Net Equity After CPF | R14: Real Cumul. Net Benefit | S14: Real ROE (CAGR %)
A15: 0 | B15: =Assumptions!C4 -> 32 | C15: =Assumptions!C33 -> 57 | D15: =VLOOKUP(C15,'Bala Table'!A:B,2,FALSE) -> 0.64 | E15: =C4/D15 -> 2187500 | F15: =C4 -> 1400000 | G15: =C5 -> 1050000 | H15: =F15-G15 -> 350000 | I15: - | J15: - | K15: - | L15: - | M15: - | N15: - | O15: - | P15: 0 | Q15: =H15-P15 -> 350000 | R15: - | S15: -
A16: =A15+1 -> 1 | B16: =B15+1 -> 33 | C16: =C15-1 -> 56 | D16: =VLOOKUP(C16,'Bala Table'!$A:$B,2,FALSE) -> 0.632 | E16: =E15*(1+Assumptions!$C$34) -> 2231250 | F16: =E16*D16 -> 1410150 | G16: =IF(A16<=Assumptions!$C$26,PV('Scenario Tables'!C$27/12,(Assumptions!$C$26-A16)*12,-$C$11),0) -> 1026579.4 | H16: =F16-G16 -> 383570.59 | I16: =IF(A16<=Assumptions!$C$26,G15*'Scenario Tables'!C$27,0) -> 27300 | J16: =IF(A16<=Assumptions!$C$26,$C$12-I16,0) -> 23142.804 | K16: =IF(Assumptions!$C$39="Investment",Assumptions!$C$35*12*(1+Assumptions!$C$36)^(A16-1)*(1-Assumptions!$C$40),Assumptions!$C$35*12*(1+Assumptions!$C$36)^(A16-1)) -> 54000 | L16: =IF(Assumptions!$C$39="Investment",_xlfn.LET(_xlpm.gr,Assumptions!$C$35*12*(1+Assumptions!$C$36)^(A16-1),Assumptions!$C$37*(1+Assumptions!$C$36)^(A16-1)+MIN(_xlpm.gr,30000)*0.12+MAX(0,MIN(_xlpm.gr,45000)-30000)*0.2+MAX(0,MIN(_xlpm.gr,60000)-45000)*0.28+MAX(0,_xlpm.gr-60000)*0.36+K16*Assumptions!$C$41),Assumptions!$C$37*(1+Assumptions!$C$36)^(A16-1)+MAX(0,MIN(K16,25000)-12000)*0.04+MAX(0,MIN(K16,38000)-25000)*0.06+MAX(0,MIN(K16,50000)-38000)*0.08+MAX(0,MIN(K16,65000)-50000)*0.1+MAX(0,MIN(K16,80000)-65000)*0.12+MAX(0,MIN(K16,95000)-80000)*0.14+MAX(0,MIN(K16,110000)-95000)*0.16+MAX(0,K16-110000)*0.23) -> 3740 | M16: =IF(Assumptions!$C$39="Investment",(K16-I16-L16)*(1-Assumptions!$C$42),K16-I16-L16) -> 22960 | N16: =IF(A16=1,M16,N15+M16) -> 22960 | O16: =(H16-$C$10)/$C$10 -> -0.069455143 | P16: =Assumptions!$C$8*(1+Assumptions!$C$9)^A16-Assumptions!$C$8+$C$7*((1+Assumptions!$C$9)^A16-1) -> 7500 | Q16: =H16-P16 -> 376070.59 | R16: =N16/(1+Assumptions!$C$43)^A16 -> 22400 | S16: =((H16/$C$10)^(1/A16))/(1+Assumptions!$C$43)-1 -> -0.092151359
A17: =A16+1 -> 2 | B17: =B16+1 -> 34 | C17: =C16-1 -> 55 | D17: =VLOOKUP(C17,'Bala Table'!$A:$B,2,FALSE) -> 0.624 | E17: =E16*(1+Assumptions!$C$34) -> 2275875 | F17: =E17*D17 -> 1420146 | G17: =IF(A17<=Assumptions!$C$26,PV('Scenario Tables'!C$27/12,(Assumptions!$C$26-A17)*12,-$C$11),0) -> 1002542.6 | H17: =F17-G17 -> 417603.43 | I17: =IF(A17<=Assumptions!$C$26,G16*'Scenario Tables'!C$27,0) -> 26691.065 | J17: =IF(A17<=Assumptions!$C$26,$C$12-I17,0) -> 23751.739 | K17: =IF(Assumptions!$C$39="Investment",Assumptions!$C$35*12*(1+Assumptions!$C$36)^(A17-1)*(1-Assumptions!$C$40),Assumptions!$C$35*12*(1+Assumptions!$C$36)^(A17-1)) -> 55080 | L17: =IF(Assumptions!$C$39="Investment",_xlfn.LET(_xlpm.gr,Assumptions!$C$35*12*(1+Assumptions!$C$36)^(A17-1),Assumptions!$C$37*(1+Assumptions!$C$36)^(A17-1)+MIN(_xlpm.gr,30000)*0.12+MAX(0,MIN(_xlpm.gr,45000)-30000)*0.2+MAX(0,MIN(_xlpm.gr,60000)-45000)*0.28+MAX(0,_xlpm.gr-60000)*0.36+K17*Assumptions!$C$41),Assumptions!$C$37*(1+Assumptions!$C$36)^(A17-1)+MAX(0,MIN(K17,25000)-12000)*0.04+MAX(0,MIN(K17,38000)-25000)*0.06+MAX(0,MIN(K17,50000)-38000)*0.08+MAX(0,MIN(K17,65000)-50000)*0.1+MAX(0,MIN(K17,80000)-65000)*0.12+MAX(0,MIN(K17,95000)-80000)*0.14+MAX(0,MIN(K17,110000)-95000)*0.16+MAX(0,K17-110000)*0.23) -> 3869.6 | M17: =IF(Assumptions!$C$39="Investment",(K17-I17-L17)*(1-Assumptions!$C$42),K17-I17-L17) -> 24519.335 | N17: =IF(A17=1,M17,N16+M17) -> 47479.335 | O17: =(H17-$C$10)/$C$10 -> 0.013108746 | P17: =Assumptions!$C$8*(1+Assumptions!$C$9)^A17-Assumptions!$C$8+$C$7*((1+Assumptions!$C$9)^A17-1) -> 15187.5 | Q17: =H17-P17 -> 402415.93 | R17: =N17/(1+Assumptions!$C$43)^A17 -> 45191.515 | S17: =((H17/$C$10)^(1/A17))/(1+Assumptions!$C$43)-1 -> -0.018016554
A18: =A17+1 -> 3 | B18: =B17+1 -> 35 | C18: =C17-1 -> 54 | D18: =VLOOKUP(C18,'Bala Table'!$A:$B,2,FALSE) -> 0.616 | E18: =E17*(1+Assumptions!$C$34) -> 2321392.5 | F18: =E18*D18 -> 1429977.8 | G18: =IF(A18<=Assumptions!$C$26,PV('Scenario Tables'!C$27/12,(Assumptions!$C$26-A18)*12,-$C$11),0) -> 977873.28 | H18: =F18-G18 -> 452104.5 | I18: =IF(A18<=Assumptions!$C$26,G17*'Scenario Tables'!C$27,0) -> 26066.107 | J18: =IF(A18<=Assumptions!$C$26,$C$12-I18,0) -> 24376.697 | K18: =IF(Assumptions!$C$39="Investment",Assumptions!$C$35*12*(1+Assumptions!$C$36)^(A18-1)*(1-Assumptions!$C$40),Assumptions!$C$35*12*(1+Assumptions!$C$36)^(A18-1)) -> 56181.6 | L18: =IF(Assumptions!$C$39="Investment",_xlfn.LET(_xlpm.gr,Assumptions!$C$35*12*(1+Assumptions!$C$36)^(A18-1),Assumptions!$C$37*(1+Assumptions!$C$36)^(A18-1)+MIN(_xlpm.gr,30000)*0.12+MAX(0,MIN(_xlpm.gr,45000)-30000)*0.2+MAX(0,MIN(_xlpm.gr,60000)-45000)*0.28+MAX(0,_xlpm.gr-60000)*0.36+K18*Assumptions!$C$41),Assumptions!$C$37*(1+Assumptions!$C$36)^(A18-1)+MAX(0,MIN(K18,25000)-12000)*0.04+MAX(0,MIN(K18,38000)-25000)*0.06+MAX(0,MIN(K18,50000)-38000)*0.08+MAX(0,MIN(K18,65000)-50000)*0.1+MAX(0,MIN(K18,80000)-65000)*0.12+MAX(0,MIN(K18,95000)-80000)*0.14+MAX(0,MIN(K18,110000)-95000)*0.16+MAX(0,K18-110000)*0.23) -> 4001.792 | M18: =IF(Assumptions!$C$39="Investment",(K18-I18-L18)*(1-Assumptions!$C$42),K18-I18-L18) -> 26113.701 | N18: =IF(A18=1,M18,N17+M18) -> 73593.036 | O18: =(H18-$C$10)/$C$10 -> 0.096808585 | P18: =Assumptions!$C$8*(1+Assumptions!$C$9)^A18-Assumptions!$C$8+$C$7*((1+Assumptions!$C$9)^A18-1) -> 23067.187 | Q18: =H18-P18 -> 429037.31 | R18: =N18/(1+Assumptions!$C$43)^A18 -> 68338.45 | S18: =((H18/$C$10)^(1/A18))/(1+Assumptions!$C$43)-1 -> 0.0061276441
A19: =A18+1 -> 4 | B19: =B18+1 -> 36 | C19: =C18-1 -> 53 | D19: =VLOOKUP(C19,'Bala Table'!$A:$B,2,FALSE) -> 0.608 | E19: =E18*(1+Assumptions!$C$34) -> 2367820.4 | F19: =E19*D19 -> 1439634.8 | G19: =IF(A19<=Assumptions!$C$26,PV('Scenario Tables'!C$27/12,(Assumptions!$C$26-A19)*12,-$C$11),0) -> 952554.89 | H19: =F19-G19 -> 487079.89 | I19: =IF(A19<=Assumptions!$C$26,G18*'Scenario Tables'!C$27,0) -> 25424.705 | J19: =IF(A19<=Assumptions!$C$26,$C$12-I19,0) -> 25018.098 | K19: =IF(Assumptions!$C$39="Investment",Assumptions!$C$35*12*(1+Assumptions!$C$36)^(A19-1)*(1-Assumptions!$C$40),Assumptions!$C$35*12*(1+Assumptions!$C$36)^(A19-1)) -> 57305.232 | L19: =IF(Assumptions!$C$39="Investment",_xlfn.LET(_xlpm.gr,Assumptions!$C$35*12*(1+Assumptions!$C$36)^(A19-1),Assumptions!$C$37*(1+Assumptions!$C$36)^(A19-1)+MIN(_xlpm.gr,30000)*0.12+MAX(0,MIN(_xlpm.gr,45000)-30000)*0.2+MAX(0,MIN(_xlpm.gr,60000)-45000)*0.28+MAX(0,_xlpm.gr-60000)*0.36+K19*Assumptions!$C$41),Assumptions!$C$37*(1+Assumptions!$C$36)^(A19-1)+MAX(0,MIN(K19,25000)-12000)*0.04+MAX(0,MIN(K19,38000)-25000)*0.06+MAX(0,MIN(K19,50000)-38000)*0.08+MAX(0,MIN(K19,65000)-50000)*0.1+MAX(0,MIN(K19,80000)-65000)*0.12+MAX(0,MIN(K19,95000)-80000)*0.14+MAX(0,MIN(K19,110000)-95000)*0.16+MAX(0,K19-110000)*0.23) -> 4136.6278 | M19: =IF(Assumptions!$C$39="Investment",(K19-I19-L19)*(1-Assumptions!$C$42),K19-I19-L19) -> 27743.899 | N19: =IF(A19=1,M19,N18+M19) -> 101336.94 | O19: =(H19-$C$10)/$C$10 -> 0.18165911 | P19: =Assumptions!$C$8*(1+Assumptions!$C$9)^A19-Assumptions!$C$8+$C$7*((1+Assumptions!$C$9)^A19-1) -> 31143.867 | Q19: =H19-P19 -> 455936.02 | R19: =N19/(1+Assumptions!$C$43)^A19 -> 91806.262 | S19: =((H19/$C$10)^(1/A19))/(1+Assumptions!$C$43)-1 -> 0.017183219
A20: =A19+1 -> 5 | B20: =B19+1 -> 37 | C20: =C19-1 -> 52 | D20: =VLOOKUP(C20,'Bala Table'!$A:$B,2,FALSE) -> 0.6 | E20: =E19*(1+Assumptions!$C$34) -> 2415176.8 | F20: =E20*D20 -> 1449106.1 | G20: =IF(A20<=Assumptions!$C$26,PV('Scenario Tables'!C$27/12,(Assumptions!$C$26-A20)*12,-$C$11),0) -> 926570.31 | H20: =F20-G20 -> 522535.74 | I20: =IF(A20<=Assumptions!$C$26,G19*'Scenario Tables'!C$27,0) -> 24766.427 | J20: =IF(A20<=Assumptions!$C$26,$C$12-I20,0) -> 25676.377 | K20: =IF(Assumptions!$C$39="Investment",Assumptions!$C$35*12*(1+Assumptions!$C$36)^(A20-1)*(1-Assumptions!$C$40),Assumptions!$C$35*12*(1+Assumptions!$C$36)^(A20-1)) -> 58451.337 | L20: =IF(Assumptions!$C$39="Investment",_xlfn.LET(_xlpm.gr,Assumptions!$C$35*12*(1+Assumptions!$C$36)^(A20-1),Assumptions!$C$37*(1+Assumptions!$C$36)^(A20-1)+MIN(_xlpm.gr,30000)*0.12+MAX(0,MIN(_xlpm.gr,45000)-30000)*0.2+MAX(0,MIN(_xlpm.gr,60000)-45000)*0.28+MAX(0,_xlpm.gr-60000)*0.36+K20*Assumptions!$C$41),Assumptions!$C$37*(1+Assumptions!$C$36)^(A20-1)+MAX(0,MIN(K20,25000)-12000)*0.04+MAX(0,MIN(K20,38000)-25000)*0.06+MAX(0,MIN(K20,50000)-38000)*0.08+MAX(0,MIN(K20,65000)-50000)*0.1+MAX(0,MIN(K20,80000)-65000)*0.12+MAX(0,MIN(K20,95000)-80000)*0.14+MAX(0,MIN(K20,110000)-95000)*0.16+MAX(0,K20-110000)*0.23) -> 4274.1604 | M20: =IF(Assumptions!$C$39="Investment",(K20-I20-L20)*(1-Assumptions!$C$42),K20-I20-L20) -> 29410.749 | N20: =IF(A20=1,M20,N19+M20) -> 130747.68 | O20: =(H20-$C$10)/$C$10 -> 0.26767526 | P20: =Assumptions!$C$8*(1+Assumptions!$C$9)^A20-Assumptions!$C$8+$C$7*((1+Assumptions!$C$9)^A20-1) -> 39422.464 | Q20: =H20-P20 -> 483113.28 | R20: =N20/(1+Assumptions!$C$43)^A20 -> 115561.9 | S20: =((H20/$C$10)^(1/A20))/(1+Assumptions!$C$43)-1 -> 0.023004955
A21: =A20+1 -> 6 | B21: =B20+1 -> 38 | C21: =C20-1 -> 51 | D21: =VLOOKUP(C21,'Bala Table'!$A:$B,2,FALSE) -> 0.592 | E21: =E20*(1+Assumptions!$C$34) -> 2463480.3 | F21: =E21*D21 -> 1458380.3 | G21: =IF(A21<=Assumptions!$C$26,PV('Scenario Tables'!C$27/12,(Assumptions!$C$26-A21)*12,-$C$11),0) -> 899902.03 | H21: =F21-G21 -> 558478.3 | I21: =IF(A21<=Assumptions!$C$26,G20*'Scenario Tables'!C$27,0) -> 24090.828 | J21: =IF(A21<=Assumptions!$C$26,$C$12-I21,0) -> 26351.976 | K21: =IF(Assumptions!$C$39="Investment",Assumptions!$C$35*12*(1+Assumptions!$C$36)^(A21-1)*(1-Assumptions!$C$40),Assumptions!$C$35*12*(1+Assumptions!$C$36)^(A21-1)) -> 59620.363 | L21: =IF(Assumptions!$C$39="Investment",_xlfn.LET(_xlpm.gr,Assumptions!$C$35*12*(1+Assumptions!$C$36)^(A21-1),Assumptions!$C$37*(1+Assumptions!$C$36)^(A21-1)+MIN(_xlpm.gr,30000)*0.12+MAX(0,MIN(_xlpm.gr,45000)-30000)*0.2+MAX(0,MIN(_xlpm.gr,60000)-45000)*0.28+MAX(0,_xlpm.gr-60000)*0.36+K21*Assumptions!$C$41),Assumptions!$C$37*(1+Assumptions!$C$36)^(A21-1)+MAX(0,MIN(K21,25000)-12000)*0.04+MAX(0,MIN(K21,38000)-25000)*0.06+MAX(0,MIN(K21,50000)-38000)*0.08+MAX(0,MIN(K21,65000)-50000)*0.1+MAX(0,MIN(K21,80000)-65000)*0.12+MAX(0,MIN(K21,95000)-80000)*0.14+MAX(0,MIN(K21,110000)-95000)*0.16+MAX(0,K21-110000)*0.23) -> 4414.4436 | M21: =IF(Assumptions!$C$39="Investment",(K21-I21-L21)*(1-Assumptions!$C$42),K21-I21-L21) -> 31115.092 | N21: =IF(A21=1,M21,N20+M21) -> 161862.78 | O21: =(H21-$C$10)/$C$10 -> 0.35487216 | P21: =Assumptions!$C$8*(1+Assumptions!$C$9)^A21-Assumptions!$C$8+$C$7*((1+Assumptions!$C$9)^A21-1) -> 47908.025 | Q21: =H21-P21 -> 510570.28 | R21: =N21/(1+Assumptions!$C$43)^A21 -> 139573.76 | S21: =((H21/$C$10)^(1/A21))/(1+Assumptions!$C$43)-1 -> 0.026264219
A22: =A21+1 -> 7 | B22: =B21+1 -> 39 | C22: =C21-1 -> 50 | D22: =VLOOKUP(C22,'Bala Table'!$A:$B,2,FALSE) -> 0.584 | E22: =E21*(1+Assumptions!$C$34) -> 2512749.9 | F22: =E22*D22 -> 1467445.9 | G22: =IF(A22<=Assumptions!$C$26,PV('Scenario Tables'!C$27/12,(Assumptions!$C$26-A22)*12,-$C$11),0) -> 872532.05 | H22: =F22-G22 -> 594913.89 | I22: =IF(A22<=Assumptions!$C$26,G21*'Scenario Tables'!C$27,0) -> 23397.453 | J22: =IF(A22<=Assumptions!$C$26,$C$12-I22,0) -> 27045.351 | K22: =IF(Assumptions!$C$39="Investment",Assumptions!$C$35*12*(1+Assumptions!$C$36)^(A22-1)*(1-Assumptions!$C$40),Assumptions!$C$35*12*(1+Assumptions!$C$36)^(A22-1)) -> 60812.771 | L22: =IF(Assumptions!$C$39="Investment",_xlfn.LET(_xlpm.gr,Assumptions!$C$35*12*(1+Assumptions!$C$36)^(A22-1),Assumptions!$C$37*(1+Assumptions!$C$36)^(A22-1)+MIN(_xlpm.gr,30000)*0.12+MAX(0,MIN(_xlpm.gr,45000)-30000)*0.2+MAX(0,MIN(_xlpm.gr,60000)-45000)*0.28+MAX(0,_xlpm.gr-60000)*0.36+K22*Assumptions!$C$41),Assumptions!$C$37*(1+Assumptions!$C$36)^(A22-1)+MAX(0,MIN(K22,25000)-12000)*0.04+MAX(0,MIN(K22,38000)-25000)*0.06+MAX(0,MIN(K22,50000)-38000)*0.08+MAX(0,MIN(K22,65000)-50000)*0.1+MAX(0,MIN(K22,80000)-65000)*0.12+MAX(0,MIN(K22,95000)-80000)*0.14+MAX(0,MIN(K22,110000)-95000)*0.16+MAX(0,K22-110000)*0.23) -> 4557.5325 | M22: =IF(Assumptions!$C$39="Investment",(K22-I22-L22)*(1-Assumptions!$C$42),K22-I22-L22) -> 32857.785 | N22: =IF(A22=1,M22,N21+M22) -> 194720.56 | O22: =(H22-$C$10)/$C$10 -> 0.44326514 | P22: =Assumptions!$C$8*(1+Assumptions!$C$9)^A22-Assumptions!$C$8+$C$7*((1+Assumptions!$C$9)^A22-1) -> 56605.726 | Q22: =H22-P22 -> 538308.16 | R22: =N22/(1+Assumptions!$C$43)^A22 -> 163811.64 | S22: =((H22/$C$10)^(1/A22))/(1+Assumptions!$C$43)-1 -> 0.02811067
A23: =A22+1 -> 8 | B23: =B22+1 -> 40 | C23: =C22-1 -> 49 | D23: =VLOOKUP(C23,'Bala Table'!$A:$B,2,FALSE) -> 0.575 | E23: =E22*(1+Assumptions!$C$34) -> 2563004.9 | F23: =E23*D23 -> 1473727.8 | G23: =IF(A23<=Assumptions!$C$26,PV('Scenario Tables'!C$27/12,(Assumptions!$C$26-A23)*12,-$C$11),0) -> 844441.91 | H23: =F23-G23 -> 629285.91 | I23: =IF(A23<=Assumptions!$C$26,G22*'Scenario Tables'!C$27,0) -> 22685.833 | J23: =IF(A23<=Assumptions!$C$26,$C$12-I23,0) -> 27756.97 | K23: =IF(Assumptions!$C$39="Investment",Assumptions!$C$35*12*(1+Assumptions!$C$36)^(A23-1)*(1-Assumptions!$C$40),Assumptions!$C$35*12*(1+Assumptions!$C$36)^(A23-1)) -> 62029.026 | L23: =IF(Assumptions!$C$39="Investment",_xlfn.LET(_xlpm.gr,Assumptions!$C$35*12*(1+Assumptions!$C$36)^(A23-1),Assumptions!$C$37*(1+Assumptions!$C$36)^(A23-1)+MIN(_xlpm.gr,30000)*0.12+MAX(0,MIN(_xlpm.gr,45000)-30000)*0.2+MAX(0,MIN(_xlpm.gr,60000)-45000)*0.28+MAX(0,_xlpm.gr-60000)*0.36+K23*Assumptions!$C$41),Assumptions!$C$37*(1+Assumptions!$C$36)^(A23-1)+MAX(0,MIN(K23,25000)-12000)*0.04+MAX(0,MIN(K23,38000)-25000)*0.06+MAX(0,MIN(K23,50000)-38000)*0.08+MAX(0,MIN(K23,65000)-50000)*0.1+MAX(0,MIN(K23,80000)-65000)*0.12+MAX(0,MIN(K23,95000)-80000)*0.14+MAX(0,MIN(K23,110000)-95000)*0.16+MAX(0,K23-110000)*0.23) -> 4703.4831 | M23: =IF(Assumptions!$C$39="Investment",(K23-I23-L23)*(1-Assumptions!$C$42),K23-I23-L23) -> 34639.71 | N23: =IF(A23=1,M23,N22+M23) -> 229360.27 | O23: =(H23-$C$10)/$C$10 -> 0.52665188 | P23: =Assumptions!$C$8*(1+Assumptions!$C$9)^A23-Assumptions!$C$8+$C$7*((1+Assumptions!$C$9)^A23-1) -> 65520.869 | Q23: =H23-P23 -> 563765.04 | R23: =N23/(1+Assumptions!$C$43)^A23 -> 188246.66 | S23: =((H23/$C$10)^(1/A23))/(1+Assumptions!$C$43)-1 -> 0.028593172
A24: =A23+1 -> 9 | B24: =B23+1 -> 41 | C24: =C23-1 -> 48 | D24: =VLOOKUP(C24,'Bala Table'!$A:$B,2,FALSE) -> 0.566 | E24: =E23*(1+Assumptions!$C$34) -> 2614265 | F24: =E24*D24 -> 1479674 | G24: =IF(A24<=Assumptions!$C$26,PV('Scenario Tables'!C$27/12,(Assumptions!$C$26-A24)*12,-$C$11),0) -> 815612.66 | H24: =F24-G24 -> 664061.33 | I24: =IF(A24<=Assumptions!$C$26,G23*'Scenario Tables'!C$27,0) -> 21955.49 | J24: =IF(A24<=Assumptions!$C$26,$C$12-I24,0) -> 28487.314 | K24: =IF(Assumptions!$C$39="Investment",Assumptions!$C$35*12*(1+Assumptions!$C$36)^(A24-1)*(1-Assumptions!$C$40),Assumptions!$C$35*12*(1+Assumptions!$C$36)^(A24-1)) -> 63269.607 | L24: =IF(Assumptions!$C$39="Investment",_xlfn.LET(_xlpm.gr,Assumptions!$C$35*12*(1+Assumptions!$C$36)^(A24-1),Assumptions!$C$37*(1+Assumptions!$C$36)^(A24-1)+MIN(_xlpm.gr,30000)*0.12+MAX(0,MIN(_xlpm.gr,45000)-30000)*0.2+MAX(0,MIN(_xlpm.gr,60000)-45000)*0.28+MAX(0,_xlpm.gr-60000)*0.36+K24*Assumptions!$C$41),Assumptions!$C$37*(1+Assumptions!$C$36)^(A24-1)+MAX(0,MIN(K24,25000)-12000)*0.04+MAX(0,MIN(K24,38000)-25000)*0.06+MAX(0,MIN(K24,50000)-38000)*0.08+MAX(0,MIN(K24,65000)-50000)*0.1+MAX(0,MIN(K24,80000)-65000)*0.12+MAX(0,MIN(K24,95000)-80000)*0.14+MAX(0,MIN(K24,110000)-95000)*0.16+MAX(0,K24-110000)*0.23) -> 4852.3528 | M24: =IF(Assumptions!$C$39="Investment",(K24-I24-L24)*(1-Assumptions!$C$42),K24-I24-L24) -> 36461.764 | N24: =IF(A24=1,M24,N23+M24) -> 265822.04 | O24: =(H24-$C$10)/$C$10 -> 0.6110173 | P24: =Assumptions!$C$8*(1+Assumptions!$C$9)^A24-Assumptions!$C$8+$C$7*((1+Assumptions!$C$9)^A24-1) -> 74658.891 | Q24: =H24-P24 -> 589402.44 | R24: =N24/(1+Assumptions!$C$43)^A24 -> 212851.24 | S24: =((H24/$C$10)^(1/A24))/(1+Assumptions!$C$43)-1 -> 0.028696514
A25: =A24+1 -> 10 | B25: =B24+1 -> 42 | C25: =C24-1 -> 47 | D25: =VLOOKUP(C25,'Bala Table'!$A:$B,2,FALSE) -> 0.557 | E25: =E24*(1+Assumptions!$C$34) -> 2666550.3 | F25: =E25*D25 -> 1485268.5 | G25: =IF(A25<=Assumptions!$C$26,PV('Scenario Tables'!C$27/12,(Assumptions!$C$26-A25)*12,-$C$11),0) -> 786024.85 | H25: =F25-G25 -> 699243.67 | I25: =IF(A25<=Assumptions!$C$26,G24*'Scenario Tables'!C$27,0) -> 21205.929 | J25: =IF(A25<=Assumptions!$C$26,$C$12-I25,0) -> 29236.875 | K25: =IF(Assumptions!$C$39="Investment",Assumptions!$C$35*12*(1+Assumptions!$C$36)^(A25-1)*(1-Assumptions!$C$40),Assumptions!$C$35*12*(1+Assumptions!$C$36)^(A25-1)) -> 64534.999 | L25: =IF(Assumptions!$C$39="Investment",_xlfn.LET(_xlpm.gr,Assumptions!$C$35*12*(1+Assumptions!$C$36)^(A25-1),Assumptions!$C$37*(1+Assumptions!$C$36)^(A25-1)+MIN(_xlpm.gr,30000)*0.12+MAX(0,MIN(_xlpm.gr,45000)-30000)*0.2+MAX(0,MIN(_xlpm.gr,60000)-45000)*0.28+MAX(0,_xlpm.gr-60000)*0.36+K25*Assumptions!$C$41),Assumptions!$C$37*(1+Assumptions!$C$36)^(A25-1)+MAX(0,MIN(K25,25000)-12000)*0.04+MAX(0,MIN(K25,38000)-25000)*0.06+MAX(0,MIN(K25,50000)-38000)*0.08+MAX(0,MIN(K25,65000)-50000)*0.1+MAX(0,MIN(K25,80000)-65000)*0.12+MAX(0,MIN(K25,95000)-80000)*0.14+MAX(0,MIN(K25,110000)-95000)*0.16+MAX(0,K25-110000)*0.23) -> 5004.1998 | M25: =IF(Assumptions!$C$39="Investment",(K25-I25-L25)*(1-Assumptions!$C$42),K25-I25-L25) -> 38324.87 | N25: =IF(A25=1,M25,N24+M25) -> 304146.91 | O25: =(H25-$C$10)/$C$10 -> 0.69636988 | P25: =Assumptions!$C$8*(1+Assumptions!$C$9)^A25-Assumptions!$C$8+$C$7*((1+Assumptions!$C$9)^A25-1) -> 84025.363 | Q25: =H25-P25 -> 615218.3 | R25: =N25/(1+Assumptions!$C$43)^A25 -> 237599.08 | S25: =((H25/$C$10)^(1/A25))/(1+Assumptions!$C$43)-1 -> 0.028556587
A26: =A25+1 -> 11 | B26: =B25+1 -> 43 | C26: =C25-1 -> 46 | D26: =VLOOKUP(C26,'Bala Table'!$A:$B,2,FALSE) -> 0.548 | E26: =E25*(1+Assumptions!$C$34) -> 2719881.3 | F26: =E26*D26 -> 1490495 | G26: =IF(A26<=Assumptions!$C$26,PV('Scenario Tables'!C$27/12,(Assumptions!$C$26-A26)*12,-$C$11),0) -> 755658.52 | H26: =F26-G26 -> 734836.43 | I26: =IF(A26<=Assumptions!$C$26,G25*'Scenario Tables'!C$27,0) -> 20436.646 | J26: =IF(A26<=Assumptions!$C$26,$C$12-I26,0) -> 30006.158 | K26: =IF(Assumptions!$C$39="Investment",Assumptions!$C$35*12*(1+Assumptions!$C$36)^(A26-1)*(1-Assumptions!$C$40),Assumptions!$C$35*12*(1+Assumptions!$C$36)^(A26-1)) -> 65825.699 | L26: =IF(Assumptions!$C$39="Investment",_xlfn.LET(_xlpm.gr,Assumptions!$C$35*12*(1+Assumptions!$C$36)^(A26-1),Assumptions!$C$37*(1+Assumptions!$C$36)^(A26-1)+MIN(_xlpm.gr,30000)*0.12+MAX(0,MIN(_xlpm.gr,45000)-30000)*0.2+MAX(0,MIN(_xlpm.gr,60000)-45000)*0.28+MAX(0,_xlpm.gr-60000)*0.36+K26*Assumptions!$C$41),Assumptions!$C$37*(1+Assumptions!$C$36)^(A26-1)+MAX(0,MIN(K26,25000)-12000)*0.04+MAX(0,MIN(K26,38000)-25000)*0.06+MAX(0,MIN(K26,50000)-38000)*0.08+MAX(0,MIN(K26,65000)-50000)*0.1+MAX(0,MIN(K26,80000)-65000)*0.12+MAX(0,MIN(K26,95000)-80000)*0.14+MAX(0,MIN(K26,110000)-95000)*0.16+MAX(0,K26-110000)*0.23) -> 5175.5978 | M26: =IF(Assumptions!$C$39="Investment",(K26-I26-L26)*(1-Assumptions!$C$42),K26-I26-L26) -> 40213.455 | N26: =IF(A26=1,M26,N25+M26) -> 344360.36 | O26: =(H26-$C$10)/$C$10 -> 0.78271817 | P26: =Assumptions!$C$8*(1+Assumptions!$C$9)^A26-Assumptions!$C$8+$C$7*((1+Assumptions!$C$9)^A26-1) -> 93625.997 | Q26: =H26-P26 -> 641210.43 | R26: =N26/(1+Assumptions!$C$43)^A26 -> 262452.45 | S26: =((H26/$C$10)^(1/A26))/(1+Assumptions!$C$43)-1 -> 0.028257377
A27: =A26+1 -> 12 | B27: =B26+1 -> 44 | C27: =C26-1 -> 45 | D27: =VLOOKUP(C27,'Bala Table'!$A:$B,2,FALSE) -> 0.539 | E27: =E26*(1+Assumptions!$C$34) -> 2774278.9 | F27: =E27*D27 -> 1495336.3 | G27: =IF(A27<=Assumptions!$C$26,PV('Scenario Tables'!C$27/12,(Assumptions!$C$26-A27)*12,-$C$11),0) -> 724493.19 | H27: =F27-G27 -> 770843.15 | I27: =IF(A27<=Assumptions!$C$26,G26*'Scenario Tables'!C$27,0) -> 19647.122 | J27: =IF(A27<=Assumptions!$C$26,$C$12-I27,0) -> 30795.682 | K27: =IF(Assumptions!$C$39="Investment",Assumptions!$C$35*12*(1+Assumptions!$C$36)^(A27-1)*(1-Assumptions!$C$40),Assumptions!$C$35*12*(1+Assumptions!$C$36)^(A27-1)) -> 67142.213 | L27: =IF(Assumptions!$C$39="Investment",_xlfn.LET(_xlpm.gr,Assumptions!$C$35*12*(1+Assumptions!$C$36)^(A27-1),Assumptions!$C$37*(1+Assumptions!$C$36)^(A27-1)+MIN(_xlpm.gr,30000)*0.12+MAX(0,MIN(_xlpm.gr,45000)-30000)*0.2+MAX(0,MIN(_xlpm.gr,60000)-45000)*0.28+MAX(0,_xlpm.gr-60000)*0.36+K27*Assumptions!$C$41),Assumptions!$C$37*(1+Assumptions!$C$36)^(A27-1)+MAX(0,MIN(K27,25000)-12000)*0.04+MAX(0,MIN(K27,38000)-25000)*0.06+MAX(0,MIN(K27,50000)-38000)*0.08+MAX(0,MIN(K27,65000)-50000)*0.1+MAX(0,MIN(K27,80000)-65000)*0.12+MAX(0,MIN(K27,95000)-80000)*0.14+MAX(0,MIN(K27,110000)-95000)*0.16+MAX(0,K27-110000)*0.23) -> 5359.9098 | M27: =IF(Assumptions!$C$39="Investment",(K27-I27-L27)*(1-Assumptions!$C$42),K27-I27-L27) -> 42135.181 | N27: =IF(A27=1,M27,N26+M27) -> 386495.54 | O27: =(H27-$C$10)/$C$10 -> 0.87007071 | P27: =Assumptions!$C$8*(1+Assumptions!$C$9)^A27-Assumptions!$C$8+$C$7*((1+Assumptions!$C$9)^A27-1) -> 103466.65 | Q27: =H27-P27 -> 667376.5 | R27: =N27/(1+Assumptions!$C$43)^A27 -> 287381.03 | S27: =((H27/$C$10)^(1/A27))/(1+Assumptions!$C$43)-1 -> 0.027852911
... A35: =A34+1 -> 20 | B35: =B34+1 -> 52 | C35: =C34-1 -> 37 | D35: =VLOOKUP(C35,'Bala Table'!$A:$B,2,FALSE) -> 0.464 | E35: =E34*(1+Assumptions!$C$34) -> 3250509.9 | F35: =E35*D35 -> 1508236.6 | G35: =IF(A35<=Assumptions!$C$26,PV('Scenario Tables'!C$27/12,(Assumptions!$C$26-A35)*12,-$C$11),0) -> 443763.81 | H35: =F35-G35 -> 1064472.8 | I35: =IF(A35<=Assumptions!$C$26,G34*'Scenario Tables'!C$27,0) -> 12535.285 | J35: =IF(A35<=Assumptions!$C$26,$C$12-I35,0) -> 37907.519 | K35: =IF(Assumptions!$C$39="Investment",Assumptions!$C$35*12*(1+Assumptions!$C$36)^(A35-1)*(1-Assumptions!$C$40),Assumptions!$C$35*12*(1+Assumptions!$C$36)^(A35-1)) -> 78667.803 | L35: =IF(Assumptions!$C$39="Investment",_xlfn.LET(_xlpm.gr,Assumptions!$C$35*12*(1+Assumptions!$C$36)^(A35-1),Assumptions!$C$37*(1+Assumptions!$C$36)^(A35-1)+MIN(_xlpm.gr,30000)*0.12+MAX(0,MIN(_xlpm.gr,45000)-30000)*0.2+MAX(0,MIN(_xlpm.gr,60000)-45000)*0.28+MAX(0,_xlpm.gr-60000)*0.36+K35*Assumptions!$C$41),Assumptions!$C$37*(1+Assumptions!$C$36)^(A35-1)+MAX(0,MIN(K35,25000)-12000)*0.04+MAX(0,MIN(K35,38000)-25000)*0.06+MAX(0,MIN(K35,50000)-38000)*0.08+MAX(0,MIN(K35,65000)-50000)*0.1+MAX(0,MIN(K35,80000)-65000)*0.12+MAX(0,MIN(K35,95000)-80000)*0.14+MAX(0,MIN(K35,110000)-95000)*0.16+MAX(0,K35-110000)*0.23) -> 6973.4925 | M35: =IF(Assumptions!$C$39="Investment",(K35-I35-L35)*(1-Assumptions!$C$42),K35-I35-L35) -> 59159.026 | N35: =IF(A35=1,M35,N34+M35) -> 798185.23 | O35: =(H35-$C$10)/$C$10 -> 1.5824182 | P35: =Assumptions!$C$8*(1+Assumptions!$C$9)^A35-Assumptions!$C$8+$C$7*((1+Assumptions!$C$9)^A35-1) -> 191584.93 | Q35: =H35-P35 -> 872887.87 | R35: =N35/(1+Assumptions!$C$43)^A35 -> 487109.25 | S35: =((H35/$C$10)^(1/A35))/(1+Assumptions!$C$43)-1 -> 0.02300431
A37: SUMMARY METRICS
A38: Terminal Property Equity (Year 20) | E38: =H35 -> 1064472.8 | G38: Terminal Loan Balance | I38: =G35 -> 443763.81
A39: Net Equity After CPF Accrued Interest | E39: =Q35 -> 872887.87 | G39: Total CPF Accrued Interest Owed | I39: =P35 -> 191584.93
A40: ROE on Day-1 Equity (20yr) | E40: =O35 -> 1.5824182 | G40: Annualized ROE (CAGR) | I40: =(H35/$C$10)^(1/20)-1 -> 0.048579418
A41: Cumulative Net Holding Benefit | E41: =N35 -> 798185.23 | G41: Breakeven Year (Equity > Day-1 Outlay) | I41: {=IFERROR(MATCH(TRUE,INDEX(H16:H35>$C$10,0),0),"Never")} -> 2
A42: Real CAGR (Inflation-Adj) | E42: =S35 -> 0.02300431 | G42: Real Cumul. Net Benefit (Year 20) | I42: =R35 -> 487109.25
A43: Inflation Rate Assumed | E43: =Assumptions!$C$43 -> 0.025

Sheet HDB 2005
A1: HDB 2005 — LEVERAGED PROPERTY ANALYSIS
A3: CAPITAL STRUCTURE
A4: Purchase Price | C4: =Assumptions!F31 -> 780000
A5: Loan Amount (75% LTV) | C5: =Assumptions!C22*Assumptions!F31 -> 585000
A6: Cash Downpayment | C6: =Assumptions!C23*Assumptions!F31-C7 -> 45000
A7: CPF OA Used | C7: =MIN(Assumptions!C24*Assumptions!F31,Assumptions!C8) -> 150000
A8: Total Upfront Costs | C8: =Assumptions!F51 -> 27200
A9: Total Cash Outlay (Day 1) | C9: =C6+C8 -> 72200
A10: Total Equity at Risk (Cash + CPF) | C10: =C6+C7+C8 -> 222200
A11: Monthly Mortgage Payment | C11: =PMT('Scenario Tables'!F$27/12,Assumptions!C26*12,-C5) -> 2341.9873
A12: Annual Mortgage Payment | C12: =C11*12 -> 28103.848
A14: Year | B14: Age | C14: Remaining Lease | D14: Bala Factor (%FH) | E14: FH Equiv. Land Value | F14: Leasehold Market Value | G14: Loan Balance | H14: Property Equity | I14: Annual Interest | J14: Annual Principal | K14: Rent / Imputed Rent (Annual) | L14: Maintenance + Prop Tax (+Mgmt) | M14: Net Holding Benefit (After Tax) | N14: Cumulative Net Benefit | O14: ROE on Equity (%) | P14: CPF Accrued Interest | Q14: Net Equity After CPF | R14: Real Cumul. Net Benefit | S14: Real ROE (CAGR %)
A15: 0 | B15: =Assumptions!C4 -> 32 | C15: =Assumptions!F33 -> 78 | D15: =VLOOKUP(C15,'Bala Table'!A:B,2,FALSE) -> 0.782 | E15: =C4/D15 -> 997442.46 | F15: =C4 -> 780000 | G15: =C5 -> 585000 | H15: =F15-G15 -> 195000 | I15: - | J15: - | K15: - | L15: - | M15: - | N15: - | O15: - | P15: 0 | Q15: =H15-P15 -> 195000 | R15: - | S15: -
A16: =A15+1 -> 1 | B16: =B15+1 -> 33 | C16: =C15-1 -> 77 | D16: =VLOOKUP(C16,'Bala Table'!$A:$B,2,FALSE) -> 0.776 | E16: =E15*(1+Assumptions!$F$34) -> 1027365.7 | F16: =E16*D16 -> 797235.81 | G16: =IF(A16<=Assumptions!$C$26,PV('Scenario Tables'!F$27/12,(Assumptions!$C$26-A16)*12,-$C$11),0) -> 571951.39 | H16: =F16-G16 -> 225284.42 | I16: =IF(A16<=Assumptions!$C$26,G15*'Scenario Tables'!F$27,0) -> 15210 | J16: =IF(A16<=Assumptions!$C$26,$C$12-I16,0) -> 12893.848 | K16: =IF(Assumptions!$C$39="Investment",Assumptions!$F$35*12*(1+Assumptions!$F$36)^(A16-1)*(1-Assumptions!$C$40),Assumptions!$F$35*12*(1+Assumptions!$F$36)^(A16-1)) -> 54000 | L16: =IF(Assumptions!$C$39="Investment",_xlfn.LET(_xlpm.gr,Assumptions!$F$35*12*(1+Assumptions!$F$36)^(A16-1),Assumptions!$F$37*(1+Assumptions!$F$36)^(A16-1)+MIN(_xlpm.gr,30000)*0.12+MAX(0,MIN(_xlpm.gr,45000)-30000)*0.2+MAX(0,MIN(_xlpm.gr,60000)-45000)*0.28+MAX(0,_xlpm.gr-60000)*0.36+K16*Assumptions!$C$41),Assumptions!$F$37*(1+Assumptions!$F$36)^(A16-1)+MAX(0,MIN(K16,25000)-12000)*0.04+MAX(0,MIN(K16,38000)-25000)*0.06+MAX(0,MIN(K16,50000)-38000)*0.08+MAX(0,MIN(K16,65000)-50000)*0.1+MAX(0,MIN(K16,80000)-65000)*0.12+MAX(0,MIN(K16,95000)-80000)*0.14+MAX(0,MIN(K16,110000)-95000)*0.16+MAX(0,K16-110000)*0.23) -> 3860 | M16: =IF(Assumptions!$C$39="Investment",(K16-I16-L16)*(1-Assumptions!$C$42),K16-I16-L16) -> 34930 | N16: =IF(A16=1,M16,N15+M16) -> 34930 | O16: =(H16-$C$10)/$C$10 -> 0.013881279 | P16: =Assumptions!$C$8*(1+Assumptions!$C$9)^A16-Assumptions!$C$8+$C$7*((1+Assumptions!$C$9)^A16-1) -> 7500 | Q16: =H16-P16 -> 217784.42 | R16: =N16/(1+Assumptions!$C$43)^A16 -> 34078.049 | S16: =((H16/$C$10)^(1/A16))/(1+Assumptions!$C$43)-1 -> -0.010847533
A17: =A16+1 -> 2 | B17: =B16+1 -> 34 | C17: =C16-1 -> 76 | D17: =VLOOKUP(C17,'Bala Table'!$A:$B,2,FALSE) -> 0.77 | E17: =E16*(1+Assumptions!$F$34) -> 1058186.7 | F17: =E17*D17 -> 814803.76 | G17: =IF(A17<=Assumptions!$C$26,PV('Scenario Tables'!F$27/12,(Assumptions!$C$26-A17)*12,-$C$11),0) -> 558559.43 | H17: =F17-G17 -> 256244.32 | I17: =IF(A17<=Assumptions!$C$26,G16*'Scenario Tables'!F$27,0) -> 14870.736 | J17: =IF(A17<=Assumptions!$C$26,$C$12-I17,0) -> 13233.112 | K17: =IF(Assumptions!$C$39="Investment",Assumptions!$F$35*12*(1+Assumptions!$F$36)^(A17-1)*(1-Assumptions!$C$40),Assumptions!$F$35*12*(1+Assumptions!$F$36)^(A17-1)) -> 55080 | L17: =IF(Assumptions!$C$39="Investment",_xlfn.LET(_xlpm.gr,Assumptions!$F$35*12*(1+Assumptions!$F$36)^(A17-1),Assumptions!$F$37*(1+Assumptions!$F$36)^(A17-1)+MIN(_xlpm.gr,30000)*0.12+MAX(0,MIN(_xlpm.gr,45000)-30000)*0.2+MAX(0,MIN(_xlpm.gr,60000)-45000)*0.28+MAX(0,_xlpm.gr-60000)*0.36+K17*Assumptions!$C$41),Assumptions!$F$37*(1+Assumptions!$F$36)^(A17-1)+MAX(0,MIN(K17,25000)-12000)*0.04+MAX(0,MIN(K17,38000)-25000)*0.06+MAX(0,MIN(K17,50000)-38000)*0.08+MAX(0,MIN(K17,65000)-50000)*0.1+MAX(0,MIN(K17,80000)-65000)*0.12+MAX(0,MIN(K17,95000)-80000)*0.14+MAX(0,MIN(K17,110000)-95000)*0.16+MAX(0,K17-110000)*0.23) -> 3992 | M17: =IF(Assumptions!$C$39="Investment",(K17-I17-L17)*(1-Assumptions!$C$42),K17-I17-L17) -> 36217.264 | N17: =IF(A17=1,M17,N16+M17) -> 71147.264 | O17: =(H17-$C$10)/$C$10 -> 0.15321478 | P17: =Assumptions!$C$8*(1+Assumptions!$C$9)^A17-Assumptions!$C$8+$C$7*((1+Assumptions!$C$9)^A17-1) -> 15187.5 | Q17: =H17-P17 -> 241056.82 | R17: =N17/(1+Assumptions!$C$43)^A17 -> 67718.99 | S17: =((H17/$C$10)^(1/A17))/(1+Assumptions!$C$43)-1 -> 0.047686228
A18: =A17+1 -> 3 | B18: =B17+1 -> 35 | C18: =C17-1 -> 75 | D18: =VLOOKUP(C18,'Bala Table'!$A:$B,2,FALSE) -> 0.764 | E18: =E17*(1+Assumptions!$F$34) -> 1089932.3 | F18: =E18*D18 -> 832708.28 | G18: =IF(A18<=Assumptions!$C$26,PV('Scenario Tables'!F$27/12,(Assumptions!$C$26-A18)*12,-$C$11),0) -> 544815.11 | H18: =F18-G18 -> 287893.16 | I18: =IF(A18<=Assumptions!$C$26,G17*'Scenario Tables'!F$27,0) -> 14522.545 | J18: =IF(A18<=Assumptions!$C$26,$C$12-I18,0) -> 13581.302 | K18: =IF(Assumptions!$C$39="Investment",Assumptions!$F$35*12*(1+Assumptions!$F$36)^(A18-1)*(1-Assumptions!$C$40),Assumptions!$F$35*12*(1+Assumptions!$F$36)^(A18-1)) -> 56181.6 | L18: =IF(Assumptions!$C$39="Investment",_xlfn.LET(_xlpm.gr,Assumptions!$F$35*12*(1+Assumptions!$F$36)^(A18-1),Assumptions!$F$37*(1+Assumptions!$F$36)^(A18-1)+MIN(_xlpm.gr,30000)*0.12+MAX(0,MIN(_xlpm.gr,45000)-30000)*0.2+MAX(0,MIN(_xlpm.gr,60000)-45000)*0.28+MAX(0,_xlpm.gr-60000)*0.36+K18*Assumptions!$C$41),Assumptions!$F$37*(1+Assumptions!$F$36)^(A18-1)+MAX(0,MIN(K18,25000)-12000)*0.04+MAX(0,MIN(K18,38000)-25000)*0.06+MAX(0,MIN(K18,50000)-38000)*0.08+MAX(0,MIN(K18,65000)-50000)*0.1+MAX(0,MIN(K18,80000)-65000)*0.12+MAX(0,MIN(K18,95000)-80000)*0.14+MAX(0,MIN(K18,110000)-95000)*0.16+MAX(0,K18-110000)*0.23) -> 4126.64 | M18: =IF(Assumptions!$C$39="Investment",(K18-I18-L18)*(1-Assumptions!$C$42),K18-I18-L18) -> 37532.415 | N18: =IF(A18=1,M18,N17+M18) -> 108679.68 | O18: =(H18-$C$10)/$C$10 -> 0.29564881 | P18: =Assumptions!$C$8*(1+Assumptions!$C$9)^A18-Assumptions!$C$8+$C$7*((1+Assumptions!$C$9)^A18-1) -> 23067.187 | Q18: =H18-P18 -> 264825.98 | R18: =N18/(1+Assumptions!$C$43)^A18 -> 100919.89 | S18: =((H18/$C$10)^(1/A18))/(1+Assumptions!$C$43)-1 -> 0.063584259
A19: =A18+1 -> 4 | B19: =B18+1 -> 36 | C19: =C18-1 -> 74 | D19: =VLOOKUP(C19,'Bala Table'!$A:$B,2,FALSE) -> 0.758 | E19: =E18*(1+Assumptions!$F$34) -> 1122630.3 | F19: =E19*D19 -> 850953.75 | G19: =IF(A19<=Assumptions!$C$26,PV('Scenario Tables'!F$27/12,(Assumptions!$C$26-A19)*12,-$C$11),0) -> 530709.15 | H19: =F19-G19 -> 320244.59 | I19: =IF(A19<=Assumptions!$C$26,G18*'Scenario Tables'!F$27,0) -> 14165.193 | J19: =IF(A19<=Assumptions!$C$26,$C$12-I19,0) -> 13938.655 | K19: =IF(Assumptions!$C$39="Investment",Assumptions!$F$35*12*(1+Assumptions!$F$36)^(A19-1)*(1-Assumptions!$C$40),Assumptions!$F$35*12*(1+Assumptions!$F$36)^(A19-1)) -> 57305.232 | L19: =IF(Assumptions!$C$39="Investment",_xlfn.LET(_xlpm.gr,Assumptions!$F$35*12*(1+Assumptions!$F$36)^(A19-1),Assumptions!$F$37*(1+Assumptions!$F$36)^(A19-1)+MIN(_xlpm.gr,30000)*0.12+MAX(0,MIN(_xlpm.gr,45000)-30000)*0.2+MAX(0,MIN(_xlpm.gr,60000)-45000)*0.28+MAX(0,_xlpm.gr-60000)*0.36+K19*Assumptions!$C$41),Assumptions!$F$37*(1+Assumptions!$F$36)^(A19-1)+MAX(0,MIN(K19,25000)-12000)*0.04+MAX(0,MIN(K19,38000)-25000)*0.06+MAX(0,MIN(K19,50000)-38000)*0.08+MAX(0,MIN(K19,65000)-50000)*0.1+MAX(0,MIN(K19,80000)-65000)*0.12+MAX(0,MIN(K19,95000)-80000)*0.14+MAX(0,MIN(K19,110000)-95000)*0.16+MAX(0,K19-110000)*0.23) -> 4263.9728 | M19: =IF(Assumptions!$C$39="Investment",(K19-I19-L19)*(1-Assumptions!$C$42),K19-I19-L19) -> 38876.066 | N19: =IF(A19=1,M19,N18+M19) -> 147555.74 | O19: =(H19-$C$10)/$C$10 -> 0.4412448 | P19: =Assumptions!$C$8*(1+Assumptions!$C$9)^A19-Assumptions!$C$8+$C$7*((1+Assumptions!$C$9)^A19-1) -> 31143.867 | Q19: =H19-P19 -> 289100.73 | R19: =N19/(1+Assumptions!$C$43)^A19 -> 133678.22 | S19: =((H19/$C$10)^(1/A19))/(1+Assumptions!$C$43)-1 -> 0.06895783
A20: =A19+1 -> 5 | B20: =B19+1 -> 37 | C20: =C19-1 -> 73 | D20: =VLOOKUP(C20,'Bala Table'!$A:$B,2,FALSE) -> 0.752 | E20: =E19*(1+Assumptions!$F$34) -> 1156309.2 | F20: =E20*D20 -> 869544.5 | G20: =IF(A20<=Assumptions!$C$26,PV('Scenario Tables'!F$27/12,(Assumptions!$C$26-A20)*12,-$C$11),0) -> 516232.03 | H20: =F20-G20 -> 353312.47 | I20: =IF(A20<=Assumptions!$C$26,G19*'Scenario Tables'!F$27,0) -> 13798.438 | J20: =IF(A20<=Assumptions!$C$26,$C$12-I20,0) -> 14305.41 | K20: =IF(Assumptions!$C$39="Investment",Assumptions!$F$35*12*(1+Assumptions!$F$36)^(A20-1)*(1-Assumptions!$C$40),Assumptions!$F$35*12*(1+Assumptions!$F$36)^(A20-1)) -> 58451.337 | L20: =IF(Assumptions!$C$39="Investment",_xlfn.LET(_xlpm.gr,Assumptions!$F$35*12*(1+Assumptions!$F$36)^(A20-1),Assumptions!$F$37*(1+Assumptions!$F$36)^(A20-1)+MIN(_xlpm.gr,30000)*0.12+MAX(0,MIN(_xlpm.gr,45000)-30000)*0.2+MAX(0,MIN(_xlpm.gr,60000)-45000)*0.28+MAX(0,_xlpm.gr-60000)*0.36+K20*Assumptions!$C$41),Assumptions!$F$37*(1+Assumptions!$F$36)^(A20-1)+MAX(0,MIN(K20,25000)-12000)*0.04+MAX(0,MIN(K20,38000)-25000)*0.06+MAX(0,MIN(K20,50000)-38000)*0.08+MAX(0,MIN(K20,65000)-50000)*0.1+MAX(0,MIN(K20,80000)-65000)*0.12+MAX(0,MIN(K20,95000)-80000)*0.14+MAX(0,MIN(K20,110000)-95000)*0.16+MAX(0,K20-110000)*0.23) -> 4404.0523 | M20: =IF(Assumptions!$C$39="Investment",(K20-I20-L20)*(1-Assumptions!$C$42),K20-I20-L20) -> 40248.846 | N20: =IF(A20=1,M20,N19+M20) -> 187804.59 | O20: =(H20-$C$10)/$C$10 -> 0.59006513 | P20: =Assumptions!$C$8*(1+Assumptions!$C$9)^A20-Assumptions!$C$8+$C$7*((1+Assumptions!$C$9)^A20-1) -> 39422.464 | Q20: =H20-P20 -> 313890.01 | R20: =N20/(1+Assumptions!$C$43)^A20 -> 165991.89 | S20: =((H20/$C$10)^(1/A20))/(1+Assumptions!$C$43)-1 -> 0.070432083
A21: =A20+1 -> 6 | B21: =B20+1 -> 38 | C21: =C20-1 -> 72 | D21: =VLOOKUP(C21,'Bala Table'!$A:$B,2,FALSE) -> 0.746 | E21: =E20*(1+Assumptions!$F$34) -> 1190998.5 | F21: =E21*D21 -> 888484.85 | G21: =IF(A21<=Assumptions!$C$26,PV('Scenario Tables'!F$27/12,(Assumptions!$C$26-A21)*12,-$C$11),0) -> 501373.99 | H21: =F21-G21 -> 387110.86 | I21: =IF(A21<=Assumptions!$C$26,G20*'Scenario Tables'!F$27,0) -> 13422.033 | J21: =IF(A21<=Assumptions!$C$26,$C$12-I21,0) -> 14681.815 | K21: =IF(Assumptions!$C$39="Investment",Assumptions!$F$35*12*(1+Assumptions!$F$36)^(A21-1)*(1-Assumptions!$C$40),Assumptions!$F$35*12*(1+Assumptions!$F$36)^(A21-1)) -> 59620.363 | L21: =IF(Assumptions!$C$39="Investment",_xlfn.LET(_xlpm.gr,Assumptions!$F$35*12*(1+Assumptions!$F$36)^(A21-1),Assumptions!$F$37*(1+Assumptions!$F$36)^(A21-1)+MIN(_xlpm.gr,30000)*0.12+MAX(0,MIN(_xlpm.gr,45000)-30000)*0.2+MAX(0,MIN(_xlpm.gr,60000)-45000)*0.28+MAX(0,_xlpm.gr-60000)*0.36+K21*Assumptions!$C$41),Assumptions!$F$37*(1+Assumptions!$F$36)^(A21-1)+MAX(0,MIN(K21,25000)-12000)*0.04+MAX(0,MIN(K21,38000)-25000)*0.06+MAX(0,MIN(K21,50000)-38000)*0.08+MAX(0,MIN(K21,65000)-50000)*0.1+MAX(0,MIN(K21,80000)-65000)*0.12+MAX(0,MIN(K21,95000)-80000)*0.14+MAX(0,MIN(K21,110000)-95000)*0.16+MAX(0,K21-110000)*0.23) -> 4546.9333 | M21: =IF(Assumptions!$C$39="Investment",(K21-I21-L21)*(1-Assumptions!$C$42),K21-I21-L21) -> 41651.397 | N21: =IF(A21=1,M21,N20+M21) -> 229455.99 | O21: =(H21-$C$10)/$C$10 -> 0.74217308 | P21: =Assumptions!$C$8*(1+Assumptions!$C$9)^A21-Assumptions!$C$8+$C$7*((1+Assumptions!$C$9)^A21-1) -> 47908.025 | Q21: =H21-P21 -> 339202.83 | R21: =N21/(1+Assumptions!$C$43)^A21 -> 197859.18 | S21: =((H21/$C$10)^(1/A21))/(1+Assumptions!$C$43)-1 -> 0.070182926
A22: =A21+1 -> 7 | B22: =B21+1 -> 39 | C22: =C21-1 -> 71 | D22: =VLOOKUP(C22,'Bala Table'!$A:$B,2,FALSE) -> 0.74 | E22: =E21*(1+Assumptions!$F$34) -> 1226728.4 | F22: =E22*D22 -> 907779.02 | G22: =IF(A22<=Assumptions!$C$26,PV('Scenario Tables'!F$27/12,(Assumptions!$C$26-A22)*12,-$C$11),0) -> 486125 | H22: =F22-G22 -> 421654.02 | I22: =IF(A22<=Assumptions!$C$26,G21*'Scenario Tables'!F$27,0) -> 13035.724 | J22: =IF(A22<=Assumptions!$C$26,$C$12-I22,0) -> 15068.124 | K22: =IF(Assumptions!$C$39="Investment",Assumptions!$F$35*12*(1+Assumptions!$F$36)^(A22-1)*(1-Assumptions!$C$40),Assumptions!$F$35*12*(1+Assumptions!$F$36)^(A22-1)) -> 60812.771 | L22: =IF(Assumptions!$C$39="Investment",_xlfn.LET(_xlpm.gr,Assumptions!$F$35*12*(1+Assumptions!$F$36)^(A22-1),Assumptions!$F$37*(1+Assumptions!$F$36)^(A22-1)+MIN(_xlpm.gr,30000)*0.12+MAX(0,MIN(_xlpm.gr,45000)-30000)*0.2+MAX(0,MIN(_xlpm.gr,60000)-45000)*0.28+MAX(0,_xlpm.gr-60000)*0.36+K22*Assumptions!$C$41),Assumptions!$F$37*(1+Assumptions!$F$36)^(A22-1)+MAX(0,MIN(K22,25000)-12000)*0.04+MAX(0,MIN(K22,38000)-25000)*0.06+MAX(0,MIN(K22,50000)-38000)*0.08+MAX(0,MIN(K22,65000)-50000)*0.1+MAX(0,MIN(K22,80000)-65000)*0.12+MAX(0,MIN(K22,95000)-80000)*0.14+MAX(0,MIN(K22,110000)-95000)*0.16+MAX(0,K22-110000)*0.23) -> 4692.672 | M22: =IF(Assumptions!$C$39="Investment",(K22-I22-L22)*(1-Assumptions!$C$42),K22-I22-L22) -> 43084.375 | N22: =IF(A22=1,M22,N21+M22) -> 272540.36 | O22: =(H22-$C$10)/$C$10 -> 0.89763287 | P22: =Assumptions!$C$8*(1+Assumptions!$C$9)^A22-Assumptions!$C$8+$C$7*((1+Assumptions!$C$9)^A22-1) -> 56605.726 | Q22: =H22-P22 -> 365048.3 | R22: =N22/(1+Assumptions!$C$43)^A22 -> 229278.73 | S22: =((H22/$C$10)^(1/A22))/(1+Assumptions!$C$43)-1 -> 0.069105918
A23: =A22+1 -> 8 | B23: =B22+1 -> 40 | C23: =C22-1 -> 70 | D23: =VLOOKUP(C23,'Bala Table'!$A:$B,2,FALSE) -> 0.734 | E23: =E22*(1+Assumptions!$F$34) -> 1263530.3 | F23: =E23*D23 -> 927431.21 | G23: =IF(A23<=Assumptions!$C$26,PV('Scenario Tables'!F$27/12,(Assumptions!$C$26-A23)*12,-$C$11),0) -> 470474.78 | H23: =F23-G23 -> 456956.43 | I23: =IF(A23<=Assumptions!$C$26,G22*'Scenario Tables'!F$27,0) -> 12639.25 | J23: =IF(A23<=Assumptions!$C$26,$C$12-I23,0) -> 15464.598 | K23: =IF(Assumptions!$C$39="Investment",Assumptions!$F$35*12*(1+Assumptions!$F$36)^(A23-1)*(1-Assumptions!$C$40),Assumptions!$F$35*12*(1+Assumptions!$F$36)^(A23-1)) -> 62029.026 | L23: =IF(Assumptions!$C$39="Investment",_xlfn.LET(_xlpm.gr,Assumptions!$F$35*12*(1+Assumptions!$F$36)^(A23-1),Assumptions!$F$37*(1+Assumptions!$F$36)^(A23-1)+MIN(_xlpm.gr,30000)*0.12+MAX(0,MIN(_xlpm.gr,45000)-30000)*0.2+MAX(0,MIN(_xlpm.gr,60000)-45000)*0.28+MAX(0,_xlpm.gr-60000)*0.36+K23*Assumptions!$C$41),Assumptions!$F$37*(1+Assumptions!$F$36)^(A23-1)+MAX(0,MIN(K23,25000)-12000)*0.04+MAX(0,MIN(K23,38000)-25000)*0.06+MAX(0,MIN(K23,50000)-38000)*0.08+MAX(0,MIN(K23,65000)-50000)*0.1+MAX(0,MIN(K23,80000)-65000)*0.12+MAX(0,MIN(K23,95000)-80000)*0.14+MAX(0,MIN(K23,110000)-95000)*0.16+MAX(0,K23-110000)*0.23) -> 4841.3254 | M23: =IF(Assumptions!$C$39="Investment",(K23-I23-L23)*(1-Assumptions!$C$42),K23-I23-L23) -> 44548.451 | N23: =IF(A23=1,M23,N22+M23) -> 317088.81 | O23: =(H23-$C$10)/$C$10 -> 1.0565096 | P23: =Assumptions!$C$8*(1+Assumptions!$C$9)^A23-Assumptions!$C$8+$C$7*((1+Assumptions!$C$9)^A23-1) -> 65520.869 | Q23: =H23-P23 -> 391435.56 | R23: =N23/(1+Assumptions!$C$43)^A23 -> 260249.56 | S23: =((H23/$C$10)^(1/A23))/(1+Assumptions!$C$43)-1 -> 0.067621908
A24: =A23+1 -> 9 | B24: =B23+1 -> 41 | C24: =C23-1 -> 69 | D24: =VLOOKUP(C24,'Bala Table'!$A:$B,2,FALSE) -> 0.727 | E24: =E23*(1+Assumptions!$F$34) -> 1301436.2 | F24: =E24*D24 -> 946144.09 | G24: =IF(A24<=Assumptions!$C$26,PV('Scenario Tables'!F$27/12,(Assumptions!$C$26-A24)*12,-$C$11),0) -> 454412.77 | H24: =F24-G24 -> 491731.33 | I24: =IF(A24<=Assumptions!$C$26,G23*'Scenario Tables'!F$27,0) -> 12232.344 | J24: =IF(A24<=Assumptions!$C$26,$C$12-I24,0) -> 15871.504 | K24: =IF(Assumptions!$C$39="Investment",Assumptions!$F$35*12*(1+Assumptions!$F$36)^(A24-1)*(1-Assumptions!$C$40),Assumptions!$F$35*12*(1+Assumptions!$F$36)^(A24-1)) -> 63269.607 | L24: =IF(Assumptions!$C$39="Investment",_xlfn.LET(_xlpm.gr,Assumptions!$F$35*12*(1+Assumptions!$F$36)^(A24-1),Assumptions!$F$37*(1+Assumptions!$F$36)^(A24-1)+MIN(_xlpm.gr,30000)*0.12+MAX(0,MIN(_xlpm.gr,45000)-30000)*0.2+MAX(0,MIN(_xlpm.gr,60000)-45000)*0.28+MAX(0,_xlpm.gr-60000)*0.36+K24*Assumptions!$C$41),Assumptions!$F$37*(1+Assumptions!$F$36)^(A24-1)+MAX(0,MIN(K24,25000)-12000)*0.04+MAX(0,MIN(K24,38000)-25000)*0.06+MAX(0,MIN(K24,50000)-38000)*0.08+MAX(0,MIN(K24,65000)-50000)*0.1+MAX(0,MIN(K24,80000)-65000)*0.12+MAX(0,MIN(K24,95000)-80000)*0.14+MAX(0,MIN(K24,110000)-95000)*0.16+MAX(0,K24-110000)*0.23) -> 4992.9519 | M24: =IF(Assumptions!$C$39="Investment",(K24-I24-L24)*(1-Assumptions!$C$42),K24-I24-L24) -> 46044.31 | N24: =IF(A24=1,M24,N23+M24) -> 363133.12 | O24: =(H24-$C$10)/$C$10 -> 1.2130123 | P24: =Assumptions!$C$8*(1+Assumptions!$C$9)^A24-Assumptions!$C$8+$C$7*((1+Assumptions!$C$9)^A24-1) -> 74658.891 | Q24: =H24-P24 -> 417072.44 | R24: =N24/(1+Assumptions!$C$43)^A24 -> 290770.99 | S24: =((H24/$C$10)^(1/A24))/(1+Assumptions!$C$43)-1 -> 0.065633023
A25: =A24+1 -> 10 | B25: =B24+1 -> 42 | C25: =C24-1 -> 68 | D25: =VLOOKUP(C25,'Bala Table'!$A:$B,2,FALSE) -> 0.72 | E25: =E24*(1+Assumptions!$F$34) -> 1340479.3 | F25: =E25*D25 -> 965145.06 | G25: =IF(A25<=Assumptions!$C$26,PV('Scenario Tables'!F$27/12,(Assumptions!$C$26-A25)*12,-$C$11),0) -> 437928.13 | H25: =F25-G25 -> 527216.93 | I25: =IF(A25<=Assumptions!$C$26,G24*'Scenario Tables'!F$27,0) -> 11814.732 | J25: =IF(A25<=Assumptions!$C$26,$C$12-I25,0) -> 16289.116 | K25: =IF(Assumptions!$C$39="Investment",Assumptions!$F$35*12*(1+Assumptions!$F$36)^(A25-1)*(1-Assumptions!$C$40),Assumptions!$F$35*12*(1+Assumptions!$F$36)^(A25-1)) -> 64534.999 | L25: =IF(Assumptions!$C$39="Investment",_xlfn.LET(_xlpm.gr,Assumptions!$F$35*12*(1+Assumptions!$F$36)^(A25-1),Assumptions!$F$37*(1+Assumptions!$F$36)^(A25-1)+MIN(_xlpm.gr,30000)*0.12+MAX(0,MIN(_xlpm.gr,45000)-30000)*0.2+MAX(0,MIN(_xlpm.gr,60000)-45000)*0.28+MAX(0,_xlpm.gr-60000)*0.36+K25*Assumptions!$C$41),Assumptions!$F$37*(1+Assumptions!$F$36)^(A25-1)+MAX(0,MIN(K25,25000)-12000)*0.04+MAX(0,MIN(K25,38000)-25000)*0.06+MAX(0,MIN(K25,50000)-38000)*0.08+MAX(0,MIN(K25,65000)-50000)*0.1+MAX(0,MIN(K25,80000)-65000)*0.12+MAX(0,MIN(K25,95000)-80000)*0.14+MAX(0,MIN(K25,110000)-95000)*0.16+MAX(0,K25-110000)*0.23) -> 5147.611 | M25: =IF(Assumptions!$C$39="Investment",(K25-I25-L25)*(1-Assumptions!$C$42),K25-I25-L25) -> 47572.656 | N25: =IF(A25=1,M25,N24+M25) -> 410705.78 | O25: =(H25-$C$10)/$C$10 -> 1.3727135 | P25: =Assumptions!$C$8*(1+Assumptions!$C$9)^A25-Assumptions!$C$8+$C$7*((1+Assumptions!$C$9)^A25-1) -> 84025.363 | Q25: =H25-P25 -> 443191.57 | R25: =N25/(1+Assumptions!$C$43)^A25 -> 320842.7 | S25: =((H25/$C$10)^(1/A25))/(1+Assumptions!$C$43)-1 -> 0.063654702
A26: =A25+1 -> 11 | B26: =B25+1 -> 43 | C26: =C25-1 -> 67 | D26: =VLOOKUP(C26,'Bala Table'!$A:$B,2,FALSE) -> 0.713 | E26: =E25*(1+Assumptions!$F$34) -> 1380693.6 | F26: =E26*D26 -> 984434.56 | G26: =IF(A26<=Assumptions!$C$26,PV('Scenario Tables'!F$27/12,(Assumptions!$C$26-A26)*12,-$C$11),0) -> 421009.75 | H26: =F26-G26 -> 563424.81 | I26: =IF(A26<=Assumptions!$C$26,G25*'Scenario Tables'!F$27,0) -> 11386.131 | J26: =IF(A26<=Assumptions!$C$26,$C$12-I26,0) -> 16717.716 | K26: =IF(Assumptions!$C$39="Investment",Assumptions!$F$35*12*(1+Assumptions!$F$36)^(A26-1)*(1-Assumptions!$C$40),Assumptions!$F$35*12*(1+Assumptions!$F$36)^(A26-1)) -> 65825.699 | L26: =IF(Assumptions!$C$39="Investment",_xlfn.LET(_xlpm.gr,Assumptions!$F$35*12*(1+Assumptions!$F$36)^(A26-1),Assumptions!$F$37*(1+Assumptions!$F$36)^(A26-1)+MIN(_xlpm.gr,30000)*0.12+MAX(0,MIN(_xlpm.gr,45000)-30000)*0.2+MAX(0,MIN(_xlpm.gr,60000)-45000)*0.28+MAX(0,_xlpm.gr-60000)*0.36+K26*Assumptions!$C$41),Assumptions!$F$37*(1+Assumptions!$F$36)^(A26-1)+MAX(0,MIN(K26,25000)-12000)*0.04+MAX(0,MIN(K26,38000)-25000)*0.06+MAX(0,MIN(K26,50000)-38000)*0.08+MAX(0,MIN(K26,65000)-50000)*0.1+MAX(0,MIN(K26,80000)-65000)*0.12+MAX(0,MIN(K26,95000)-80000)*0.14+MAX(0,MIN(K26,110000)-95000)*0.16+MAX(0,K26-110000)*0.23) -> 5321.8771 | M26: =IF(Assumptions!$C$39="Investment",(K26-I26-L26)*(1-Assumptions!$C$42),K26-I26-L26) -> 49117.69 | N26: =IF(A26=1,M26,N25+M26) -> 459823.47 | O26: =(H26-$C$10)/$C$10 -> 1.5356652 | P26: =Assumptions!$C$8*(1+Assumptions!$C$9)^A26-Assumptions!$C$8+$C$7*((1+Assumptions!$C$9)^A26-1) -> 93625.997 | Q26: =H26-P26 -> 469798.81 | R26: =N26/(1+Assumptions!$C$43)^A26 -> 350452.06 | S26: =((H26/$C$10)^(1/A26))/(1+Assumptions!$C$43)-1 -> 0.061724314
A27: =A26+1 -> 12 | B27: =B26+1 -> 44 | C27: =C26-1 -> 66 | D27: =VLOOKUP(C27,'Bala Table'!$A:$B,2,FALSE) -> 0.706 | E27: =E26*(1+Assumptions!$F$34) -> 1422114.4 | F27: =E27*D27 -> 1004012.8 | G27: =IF(A27<=Assumptions!$C$26,PV('Scenario Tables'!F$27/12,(Assumptions!$C$26-A27)*12,-$C$11),0) -> 403646.21 | H27: =F27-G27 -> 600366.59 | I27: =IF(A27<=Assumptions!$C$26,G26*'Scenario Tables'!F$27,0) -> 10946.253 | J27: =IF(A27<=Assumptions!$C$26,$C$12-I27,0) -> 17157.594 | K27: =IF(Assumptions!$C$39="Investment",Assumptions!$F$35*12*(1+Assumptions!$F$36)^(A27-1)*(1-Assumptions!$C$40),Assumptions!$F$35*12*(1+Assumptions!$F$36)^(A27-1)) -> 67142.213 | L27: =IF(Assumptions!$C$39="Investment",_xlfn.LET(_xlpm.gr,Assumptions!$F$35*12*(1+Assumptions!$F$36)^(A27-1),Assumptions!$F$37*(1+Assumptions!$F$36)^(A27-1)+MIN(_xlpm.gr,30000)*0.12+MAX(0,MIN(_xlpm.gr,45000)-30000)*0.2+MAX(0,MIN(_xlpm.gr,60000)-45000)*0.28+MAX(0,_xlpm.gr-60000)*0.36+K27*Assumptions!$C$41),Assumptions!$F$37*(1+Assumptions!$F$36)^(A27-1)+MAX(0,MIN(K27,25000)-12000)*0.04+MAX(0,MIN(K27,38000)-25000)*0.06+MAX(0,MIN(K27,50000)-38000)*0.08+MAX(0,MIN(K27,65000)-50000)*0.1+MAX(0,MIN(K27,80000)-65000)*0.12+MAX(0,MIN(K27,95000)-80000)*0.14+MAX(0,MIN(K27,110000)-95000)*0.16+MAX(0,K27-110000)*0.23) -> 5509.1147 | M27: =IF(Assumptions!$C$39="Investment",(K27-I27-L27)*(1-Assumptions!$C$42),K27-I27-L27) -> 50686.845 | N27: =IF(A27=1,M27,N26+M27) -> 510510.32 | O27: =(H27-$C$10)/$C$10 -> 1.7019198 | P27: =Assumptions!$C$8*(1+Assumptions!$C$9)^A27-Assumptions!$C$8+$C$7*((1+Assumptions!$C$9)^A27-1) -> 103466.65 | Q27: =H27-P27 -> 496899.94 | R27: =N27/(1+Assumptions!$C$43)^A27 -> 379592.95 | S27: =((H27/$C$10)^(1/A27))/(1+Assumptions!$C$43)-1 -> 0.059860824
... A35: =A34+1 -> 20 | B35: =B34+1 -> 52 | C35: =C34-1 -> 58 | D35: =VLOOKUP(C35,'Bala Table'!$A:$B,2,FALSE) -> 0.648 | E35: =E34*(1+Assumptions!$F$34) -> 1801492 | F35: =E35*D35 -> 1167366.8 | G35: =IF(A35<=Assumptions!$C$26,PV('Scenario Tables'!F$27/12,(Assumptions!$C$26-A35)*12,-$C$11),0) -> 247239.84 | H35: =F35-G35 -> 920127 | I35: =IF(A35<=Assumptions!$C$26,G34*'Scenario Tables'!F$27,0) -> 6983.9444 | J35: =IF(A35<=Assumptions!$C$26,$C$12-I35,0) -> 21119.903 | K35: =IF(Assumptions!$C$39="Investment",Assumptions!$F$35*12*(1+Assumptions!$F$36)^(A35-1)*(1-Assumptions!$C$40),Assumptions!$F$35*12*(1+Assumptions!$F$36)^(A35-1)) -> 78667.803 | L35: =IF(Assumptions!$C$39="Investment",_xlfn.LET(_xlpm.gr,Assumptions!$F$35*12*(1+Assumptions!$F$36)^(A35-1),Assumptions!$F$37*(1+Assumptions!$F$36)^(A35-1)+MIN(_xlpm.gr,30000)*0.12+MAX(0,MIN(_xlpm.gr,45000)-30000)*0.2+MAX(0,MIN(_xlpm.gr,60000)-45000)*0.28+MAX(0,_xlpm.gr-60000)*0.36+K35*Assumptions!$C$41),Assumptions!$F$37*(1+Assumptions!$F$36)^(A35-1)+MAX(0,MIN(K35,25000)-12000)*0.04+MAX(0,MIN(K35,38000)-25000)*0.06+MAX(0,MIN(K35,50000)-38000)*0.08+MAX(0,MIN(K35,65000)-50000)*0.1+MAX(0,MIN(K35,80000)-65000)*0.12+MAX(0,MIN(K35,95000)-80000)*0.14+MAX(0,MIN(K35,110000)-95000)*0.16+MAX(0,K35-110000)*0.23) -> 7148.3098 | M35: =IF(Assumptions!$C$39="Investment",(K35-I35-L35)*(1-Assumptions!$C$42),K35-I35-L35) -> 64535.549 | N35: =IF(A35=1,M35,N34+M35) -> 976756.98 | O35: =(H35-$C$10)/$C$10 -> 3.1409856 | P35: =Assumptions!$C$8*(1+Assumptions!$C$9)^A35-Assumptions!$C$8+$C$7*((1+Assumptions!$C$9)^A35-1) -> 191584.93 | Q35: =H35-P35 -> 728542.06 | R35: =N35/(1+Assumptions!$C$43)^A35 -> 596086.4 | S35: =((H35/$C$10)^(1/A35))/(1+Assumptions!$C$43)-1 -> 0.047445223
A37: SUMMARY METRICS
A38: Terminal Property Equity (Year 20) | E38: =H35 -> 920127 | G38: Terminal Loan Balance | I38: =G35 -> 247239.84
A39: Net Equity After CPF Accrued Interest | E39: =Q35 -> 728542.06 | G39: Total CPF Accrued Interest Owed | I39: =P35 -> 191584.93
A40: ROE on Day-1 Equity (20yr) | E40: =O35 -> 3.1409856 | G40: Annualized ROE (CAGR) | I40: =(H35/$C$10)^(1/20)-1 -> 0.073631354
A41: Cumulative Net Holding Benefit | E41: =N35 -> 976756.98 | G41: Breakeven Year (Equity > Day-1 Outlay) | I41: {=IFERROR(MATCH(TRUE,INDEX(H16:H35>$C$10,0),0),"Never")} -> 1
A42: Real CAGR (Inflation-Adj) | E42: =S35 -> 0.047445223 | G42: Real Cumul. Net Benefit (Year 20) | I42: =R35 -> 596086.4
A43: Inflation Rate Assumed | E43: =Assumptions!$C$43 -> 0.025

Sheet HDB 2015
A1: HDB 2015 — LEVERAGED PROPERTY ANALYSIS
A3: CAPITAL STRUCTURE
A4: Purchase Price | C4: =Assumptions!G31 -> 1400000
A5: Loan Amount (75% LTV) | C5: =Assumptions!C22*Assumptions!G31 -> 1050000
A6: Cash Downpayment | C6: =Assumptions!C23*Assumptions!G31-C7 -> 200000
A7: CPF OA Used | C7: =MIN(Assumptions!C24*Assumptions!G31,Assumptions!C8) -> 150000
A8: Total Upfront Costs | C8: =Assumptions!G51 -> 62200
A9: Total Cash Outlay (Day 1) | C9: =C6+C8 -> 262200
A10: Total Equity at Risk (Cash + CPF) | C10: =C6+C7+C8 -> 412200
A11: Monthly Mortgage Payment | C11: =PMT('Scenario Tables'!G$27/12,Assumptions!C26*12,-C5) -> 4203.567
A12: Annual Mortgage Payment | C12: =C11*12 -> 50442.804
A14: Year | B14: Age | C14: Remaining Lease | D14: Bala Factor (%FH) | E14: FH Equiv. Land Value | F14: Leasehold Market Value | G14: Loan Balance | H14: Property Equity | I14: Annual Interest | J14: Annual Principal | K14: Rent / Imputed Rent (Annual) | L14: Maintenance + Prop Tax (+Mgmt) | M14: Net Holding Benefit (After Tax) | N14: Cumulative Net Benefit | O14: ROE on Equity (%) | P14: CPF Accrued Interest | Q14: Net Equity After CPF | R14: Real Cumul. Net Benefit | S14: Real ROE (CAGR %)
A15: 0 | B15: =Assumptions!C4 -> 32 | C15: =Assumptions!G33 -> 88 | D15: =VLOOKUP(C15,'Bala Table'!A:B,2,FALSE) -> 0.84 | E15: =C4/D15 -> 1666666.7 | F15: =C4 -> 1400000 | G15: =C5 -> 1050000 | H15: =F15-G15 -> 350000 | I15: - | J15: - | K15: - | L15: - | M15: - | N15: - | O15: - | P15: 0 | Q15: =H15-P15 -> 350000 | R15: - | S15: -
A16: =A15+1 -> 1 | B16: =B15+1 -> 33 | C16: =C15-1 -> 87 | D16: =VLOOKUP(C16,'Bala Table'!$A:$B,2,FALSE) -> 0.835 | E16: =E15*(1+Assumptions!$G$34) -> 1716666.7 | F16: =E16*D16 -> 1433416.7 | G16: =IF(A16<=Assumptions!$C$26,PV('Scenario Tables'!G$27/12,(Assumptions!$C$26-A16)*12,-$C$11),0) -> 1026579.4 | H16: =F16-G16 -> 406837.26 | I16: =IF(A16<=Assumptions!$C$26,G15*'Scenario Tables'!G$27,0) -> 27300 | J16: =IF(A16<=Assumptions!$C$26,$C$12-I16,0) -> 23142.804 | K16: =IF(Assumptions!$C$39="Investment",Assumptions!$G$35*12*(1+Assumptions!$G$36)^(A16-1)*(1-Assumptions!$C$40),Assumptions!$G$35*12*(1+Assumptions!$G$36)^(A16-1)) -> 54000 | L16: =IF(Assumptions!$C$39="Investment",_xlfn.LET(_xlpm.gr,Assumptions!$G$35*12*(1+Assumptions!$G$36)^(A16-1),Assumptions!$G$37*(1+Assumptions!$G$36)^(A16-1)+MIN(_xlpm.gr,30000)*0.12+MAX(0,MIN(_xlpm.gr,45000)-30000)*0.2+MAX(0,MIN(_xlpm.gr,60000)-45000)*0.28+MAX(0,_xlpm.gr-60000)*0.36+K16*Assumptions!$C$41),Assumptions!$G$37*(1+Assumptions!$G$36)^(A16-1)+MAX(0,MIN(K16,25000)-12000)*0.04+MAX(0,MIN(K16,38000)-25000)*0.06+MAX(0,MIN(K16,50000)-38000)*0.08+MAX(0,MIN(K16,65000)-50000)*0.1+MAX(0,MIN(K16,80000)-65000)*0.12+MAX(0,MIN(K16,95000)-80000)*0.14+MAX(0,MIN(K16,110000)-95000)*0.16+MAX(0,K16-110000)*0.23) -> 3980 | M16: =IF(Assumptions!$C$39="Investment",(K16-I16-L16)*(1-Assumptions!$C$42),K16-I16-L16) -> 22720 | N16: =IF(A16=1,M16,N15+M16) -> 22720 | O16: =(H16-$C$10)/$C$10 -> -0.013010051 | P16: =Assumptions!$C$8*(1+Assumptions!$C$9)^A16-Assumptions!$C$8+$C$7*((1+Assumptions!$C$9)^A16-1) -> 7500 | Q16: =H16-P16 -> 399337.26 | R16: =N16/(1+Assumptions!$C$43)^A16 -> 22165.854 | S16: =((H16/$C$10)^(1/A16))/(1+Assumptions!$C$43)-1 -> -0.037082977
A17: =A16+1 -> 2 | B17: =B16+1 -> 34 | C17: =C16-1 -> 86 | D17: =VLOOKUP(C17,'Bala Table'!$A:$B,2,FALSE) -> 0.83 | E17: =E16*(1+Assumptions!$G$34) -> 1768166.7 | F17: =E17*D17 -> 1467578.3 | G17: =IF(A17<=Assumptions!$C$26,PV('Scenario Tables'!G$27/12,(Assumptions!$C$26-A17)*12,-$C$11),0) -> 1002542.6 | H17: =F17-G17 -> 465035.76 | I17: =IF(A17<=Assumptions!$C$26,G16*'Scenario Tables'!G$27,0) -> 26691.065 | J17: =IF(A17<=Assumptions!$C$26,$C$12-I17,0) -> 23751.739 | K17: =IF(Assumptions!$C$39="Investment",Assumptions!$G$35*12*(1+Assumptions!$G$36)^(A17-1)*(1-Assumptions!$C$40),Assumptions!$G$35*12*(1+Assumptions!$G$36)^(A17-1)) -> 55080 | L17: =IF(Assumptions!$C$39="Investment",_xlfn.LET(_xlpm.gr,Assumptions!$G$35*12*(1+Assumptions!$G$36)^(A17-1),Assumptions!$G$37*(1+Assumptions!$G$36)^(A17-1)+MIN(_xlpm.gr,30000)*0.12+MAX(0,MIN(_xlpm.gr,45000)-30000)*0.2+MAX(0,MIN(_xlpm.gr,60000)-45000)*0.28+MAX(0,_xlpm.gr-60000)*0.36+K17*Assumptions!$C$41),Assumptions!$G$37*(1+Assumptions!$G$36)^(A17-1)+MAX(0,MIN(K17,25000)-12000)*0.04+MAX(0,MIN(K17,38000)-25000)*0.06+MAX(0,MIN(K17,50000)-38000)*0.08+MAX(0,MIN(K17,65000)-50000)*0.1+MAX(0,MIN(K17,80000)-65000)*0.12+MAX(0,MIN(K17,95000)-80000)*0.14+MAX(0,MIN(K17,110000)-95000)*0.16+MAX(0,K17-110000)*0.23) -> 4114.4 | M17: =IF(Assumptions!$C$39="Investment",(K17-I17-L17)*(1-Assumptions!$C$42),K17-I17-L17) -> 24274.535 | N17: =IF(A17=1,M17,N16+M17) -> 46994.535 | O17: =(H17-$C$10)/$C$10 -> 0.12817991 | P17: =Assumptions!$C$8*(1+Assumptions!$C$9)^A17-Assumptions!$C$8+$C$7*((1+Assumptions!$C$9)^A17-1) -> 15187.5 | Q17: =H17-P17 -> 449848.26 | R17: =N17/(1+Assumptions!$C$43)^A17 -> 44730.075 | S17: =((H17/$C$10)^(1/A17))/(1+Assumptions!$C$43)-1 -> 0.036251841
A18: =A17+1 -> 3 | B18: =B17+1 -> 35 | C18: =C17-1 -> 85 | D18: =VLOOKUP(C18,'Bala Table'!$A:$B,2,FALSE) -> 0.824 | E18: =E17*(1+Assumptions!$G$34) -> 1821211.7 | F18: =E18*D18 -> 1500678.4 | G18: =IF(A18<=Assumptions!$C$26,PV('Scenario Tables'!G$27/12,(Assumptions!$C$26-A18)*12,-$C$11),0) -> 977873.28 | H18: =F18-G18 -> 522805.13 | I18: =IF(A18<=Assumptions!$C$26,G17*'Scenario Tables'!G$27,0) -> 26066.107 | J18: =IF(A18<=Assumptions!$C$26,$C$12-I18,0) -> 24376.697 | K18: =IF(Assumptions!$C$39="Investment",Assumptions!$G$35*12*(1+Assumptions!$G$36)^(A18-1)*(1-Assumptions!$C$40),Assumptions!$G$35*12*(1+Assumptions!$G$36)^(A18-1)) -> 56181.6 | L18: =IF(Assumptions!$C$39="Investment",_xlfn.LET(_xlpm.gr,Assumptions!$G$35*12*(1+Assumptions!$G$36)^(A18-1),Assumptions!$G$37*(1+Assumptions!$G$36)^(A18-1)+MIN(_xlpm.gr,30000)*0.12+MAX(0,MIN(_xlpm.gr,45000)-30000)*0.2+MAX(0,MIN(_xlpm.gr,60000)-45000)*0.28+MAX(0,_xlpm.gr-60000)*0.36+K18*Assumptions!$C$41),Assumptions!$G$37*(1+Assumptions!$G$36)^(A18-1)+MAX(0,MIN(K18,25000)-12000)*0.04+MAX(0,MIN(K18,38000)-25000)*0.06+MAX(0,MIN(K18,50000)-38000)*0.08+MAX(0,MIN(K18,65000)-50000)*0.1+MAX(0,MIN(K18,80000)-65000)*0.12+MAX(0,MIN(K18,95000)-80000)*0.14+MAX(0,MIN(K18,110000)-95000)*0.16+MAX(0,K18-110000)*0.23) -> 4251.488 | M18: =IF(Assumptions!$C$39="Investment",(K18-I18-L18)*(1-Assumptions!$C$42),K18-I18-L18) -> 25864.005 | N18: =IF(A18=1,M18,N17+M18) -> 72858.54 | O18: =(H18-$C$10)/$C$10 -> 0.2683288 | P18: =Assumptions!$C$8*(1+Assumptions!$C$9)^A18-Assumptions!$C$8+$C$7*((1+Assumptions!$C$9)^A18-1) -> 23067.187 | Q18: =H18-P18 -> 499737.94 | R18: =N18/(1+Assumptions!$C$43)^A18 -> 67656.398 | S18: =((H18/$C$10)^(1/A18))/(1+Assumptions!$C$43)-1 -> 0.056055525
A19: =A18+1 -> 4 | B19: =B18+1 -> 36 | C19: =C18-1 -> 84 | D19: =VLOOKUP(C19,'Bala Table'!$A:$B,2,FALSE) -> 0.818 | E19: =E18*(1+Assumptions!$G$34) -> 1875848 | F19: =E19*D19 -> 1534443.7 | G19: =IF(A19<=Assumptions!$C$26,PV('Scenario Tables'!G$27/12,(Assumptions!$C$26-A19)*12,-$C$11),0) -> 952554.89 | H19: =F19-G19 -> 581888.79 | I19: =IF(A19<=Assumptions!$C$26,G18*'Scenario Tables'!G$27,0) -> 25424.705 | J19: =IF(A19<=Assumptions!$C$26,$C$12-I19,0) -> 25018.098 | K19: =IF(Assumptions!$C$39="Investment",Assumptions!$G$35*12*(1+Assumptions!$G$36)^(A19-1)*(1-Assumptions!$C$40),Assumptions!$G$35*12*(1+Assumptions!$G$36)^(A19-1)) -> 57305.232 | L19: =IF(Assumptions!$C$39="Investment",_xlfn.LET(_xlpm.gr,Assumptions!$G$35*12*(1+Assumptions!$G$36)^(A19-1),Assumptions!$G$37*(1+Assumptions!$G$36)^(A19-1)+MIN(_xlpm.gr,30000)*0.12+MAX(0,MIN(_xlpm.gr,45000)-30000)*0.2+MAX(0,MIN(_xlpm.gr,60000)-45000)*0.28+MAX(0,_xlpm.gr-60000)*0.36+K19*Assumptions!$C$41),Assumptions!$G$37*(1+Assumptions!$G$36)^(A19-1)+MAX(0,MIN(K19,25000)-12000)*0.04+MAX(0,MIN(K19,38000)-25000)*0.06+MAX(0,MIN(K19,50000)-38000)*0.08+MAX(0,MIN(K19,65000)-50000)*0.1+MAX(0,MIN(K19,80000)-65000)*0.12+MAX(0,MIN(K19,95000)-80000)*0.14+MAX(0,MIN(K19,110000)-95000)*0.16+MAX(0,K19-110000)*0.23) -> 4391.3178 | M19: =IF(Assumptions!$C$39="Investment",(K19-I19-L19)*(1-Assumptions!$C$42),K19-I19-L19) -> 27489.209 | N19: =IF(A19=1,M19,N18+M19) -> 100347.75 | O19: =(H19-$C$10)/$C$10 -> 0.41166616 | P19: =Assumptions!$C$8*(1+Assumptions!$C$9)^A19-Assumptions!$C$8+$C$7*((1+Assumptions!$C$9)^A19-1) -> 31143.867 | Q19: =H19-P19 -> 550744.92 | R19: =N19/(1+Assumptions!$C$43)^A19 -> 90910.108 | S19: =((H19/$C$10)^(1/A19))/(1+Assumptions!$C$43)-1 -> 0.063430558
A20: =A19+1 -> 5 | B20: =B19+1 -> 37 | C20: =C19-1 -> 83 | D20: =VLOOKUP(C20,'Bala Table'!$A:$B,2,FALSE) -> 0.812 | E20: =E19*(1+Assumptions!$G$34) -> 1932123.5 | F20: =E20*D20 -> 1568884.2 | G20: =IF(A20<=Assumptions!$C$26,PV('Scenario Tables'!G$27/12,(Assumptions!$C$26-A20)*12,-$C$11),0) -> 926570.31 | H20: =F20-G20 -> 642313.93 | I20: =IF(A20<=Assumptions!$C$26,G19*'Scenario Tables'!G$27,0) -> 24766.427 | J20: =IF(A20<=Assumptions!$C$26,$C$12-I20,0) -> 25676.377 | K20: =IF(Assumptions!$C$39="Investment",Assumptions!$G$35*12*(1+Assumptions!$G$36)^(A20-1)*(1-Assumptions!$C$40),Assumptions!$G$35*12*(1+Assumptions!$G$36)^(A20-1)) -> 58451.337 | L20: =IF(Assumptions!$C$39="Investment",_xlfn.LET(_xlpm.gr,Assumptions!$G$35*12*(1+Assumptions!$G$36)^(A20-1),Assumptions!$G$37*(1+Assumptions!$G$36)^(A20-1)+MIN(_xlpm.gr,30000)*0.12+MAX(0,MIN(_xlpm.gr,45000)-30000)*0.2+MAX(0,MIN(_xlpm.gr,60000)-45000)*0.28+MAX(0,_xlpm.gr-60000)*0.36+K20*Assumptions!$C$41),Assumptions!$G$37*(1+Assumptions!$G$36)^(A20-1)+MAX(0,MIN(K20,25000)-12000)*0.04+MAX(0,MIN(K20,38000)-25000)*0.06+MAX(0,MIN(K20,50000)-38000)*0.08+MAX(0,MIN(K20,65000)-50000)*0.1+MAX(0,MIN(K20,80000)-65000)*0.12+MAX(0,MIN(K20,95000)-80000)*0.14+MAX(0,MIN(K20,110000)-95000)*0.16+MAX(0,K20-110000)*0.23) -> 4533.9441 | M20: =IF(Assumptions!$C$39="Investment",(K20-I20-L20)*(1-Assumptions!$C$42),K20-I20-L20) -> 29150.965 | N20: =IF(A20=1,M20,N19+M20) -> 129498.71 | O20: =(H20-$C$10)/$C$10 -> 0.55825797 | P20: =Assumptions!$C$8*(1+Assumptions!$C$9)^A20-Assumptions!$C$8+$C$7*((1+Assumptions!$C$9)^A20-1) -> 39422.464 | Q20: =H20-P20 -> 602891.47 | R20: =N20/(1+Assumptions!$C$43)^A20 -> 114457.99 | S20: =((H20/$C$10)^(1/A20))/(1+Assumptions!$C$43)-1 -> 0.066114882
A21: =A20+1 -> 6 | B21: =B20+1 -> 38 | C21: =C20-1 -> 82 | D21: =VLOOKUP(C21,'Bala Table'!$A:$B,2,FALSE) -> 0.806 | E21: =E20*(1+Assumptions!$G$34) -> 1990087.2 | F21: =E21*D21 -> 1604010.3 | G21: =IF(A21<=Assumptions!$C$26,PV('Scenario Tables'!G$27/12,(Assumptions!$C$26-A21)*12,-$C$11),0) -> 899902.03 | H21: =F21-G21 -> 704108.22 | I21: =IF(A21<=Assumptions!$C$26,G20*'Scenario Tables'!G$27,0) -> 24090.828 | J21: =IF(A21<=Assumptions!$C$26,$C$12-I21,0) -> 26351.976 | K21: =IF(Assumptions!$C$39="Investment",Assumptions!$G$35*12*(1+Assumptions!$G$36)^(A21-1)*(1-Assumptions!$C$40),Assumptions!$G$35*12*(1+Assumptions!$G$36)^(A21-1)) -> 59620.363 | L21: =IF(Assumptions!$C$39="Investment",_xlfn.LET(_xlpm.gr,Assumptions!$G$35*12*(1+Assumptions!$G$36)^(A21-1),Assumptions!$G$37*(1+Assumptions!$G$36)^(A21-1)+MIN(_xlpm.gr,30000)*0.12+MAX(0,MIN(_xlpm.gr,45000)-30000)*0.2+MAX(0,MIN(_xlpm.gr,60000)-45000)*0.28+MAX(0,_xlpm.gr-60000)*0.36+K21*Assumptions!$C$41),Assumptions!$G$37*(1+Assumptions!$G$36)^(A21-1)+MAX(0,MIN(K21,25000)-12000)*0.04+MAX(0,MIN(K21,38000)-25000)*0.06+MAX(0,MIN(K21,50000)-38000)*0.08+MAX(0,MIN(K21,65000)-50000)*0.1+MAX(0,MIN(K21,80000)-65000)*0.12+MAX(0,MIN(K21,95000)-80000)*0.14+MAX(0,MIN(K21,110000)-95000)*0.16+MAX(0,K21-110000)*0.23) -> 4679.423 | M21: =IF(Assumptions!$C$39="Investment",(K21-I21-L21)*(1-Assumptions!$C$42),K21-I21-L21) -> 30850.112 | N21: =IF(A21=1,M21,N20+M21) -> 160348.83 | O21: =(H21-$C$10)/$C$10 -> 0.70817133 | P21: =Assumptions!$C$8*(1+Assumptions!$C$9)^A21-Assumptions!$C$8+$C$7*((1+Assumptions!$C$9)^A21-1) -> 47908.025 | Q21: =H21-P21 -> 656200.2 | R21: =N21/(1+Assumptions!$C$43)^A21 -> 138268.29 | S21: =((H21/$C$10)^(1/A21))/(1+Assumptions!$C$43)-1 -> 0.066673173
A22: =A21+1 -> 7 | B22: =B21+1 -> 39 | C22: =C21-1 -> 81 | D22: =VLOOKUP(C22,'Bala Table'!$A:$B,2,FALSE) -> 0.8 | E22: =E21*(1+Assumptions!$G$34) -> 2049789.8 | F22: =E22*D22 -> 1639831.8 | G22: =IF(A22<=Assumptions!$C$26,PV('Scenario Tables'!G$27/12,(Assumptions!$C$26-A22)*12,-$C$11),0) -> 872532.05 | H22: =F22-G22 -> 767299.77 | I22: =IF(A22<=Assumptions!$C$26,G21*'Scenario Tables'!G$27,0) -> 23397.453 | J22: =IF(A22<=Assumptions!$C$26,$C$12-I22,0) -> 27045.351 | K22: =IF(Assumptions!$C$39="Investment",Assumptions!$G$35*12*(1+Assumptions!$G$36)^(A22-1)*(1-Assumptions!$C$40),Assumptions!$G$35*12*(1+Assumptions!$G$36)^(A22-1)) -> 60812.771 | L22: =IF(Assumptions!$C$39="Investment",_xlfn.LET(_xlpm.gr,Assumptions!$G$35*12*(1+Assumptions!$G$36)^(A22-1),Assumptions!$G$37*(1+Assumptions!$G$36)^(A22-1)+MIN(_xlpm.gr,30000)*0.12+MAX(0,MIN(_xlpm.gr,45000)-30000)*0.2+MAX(0,MIN(_xlpm.gr,60000)-45000)*0.28+MAX(0,_xlpm.gr-60000)*0.36+K22*Assumptions!$C$41),Assumptions!$G$37*(1+Assumptions!$G$36)^(A22-1)+MAX(0,MIN(K22,25000)-12000)*0.04+MAX(0,MIN(K22,38000)-25000)*0.06+MAX(0,MIN(K22,50000)-38000)*0.08+MAX(0,MIN(K22,65000)-50000)*0.1+MAX(0,MIN(K22,80000)-65000)*0.12+MAX(0,MIN(K22,95000)-80000)*0.14+MAX(0,MIN(K22,110000)-95000)*0.16+MAX(0,K22-110000)*0.23) -> 4827.8115 | M22: =IF(Assumptions!$C$39="Investment",(K22-I22-L22)*(1-Assumptions!$C$42),K22-I22-L22) -> 32587.506 | N22: =IF(A22=1,M22,N21+M22) -> 192936.33 | O22: =(H22-$C$10)/$C$10 -> 0.86147446 | P22: =Assumptions!$C$8*(1+Assumptions!$C$9)^A22-Assumptions!$C$8+$C$7*((1+Assumptions!$C$9)^A22-1) -> 56605.726 | Q22: =H22-P22 -> 710694.04 | R22: =N22/(1+Assumptions!$C$43)^A22 -> 162310.63 | S22: =((H22/$C$10)^(1/A22))/(1+Assumptions!$C$43)-1 -> 0.066171689
A23: =A22+1 -> 8 | B23: =B22+1 -> 40 | C23: =C22-1 -> 80 | D23: =VLOOKUP(C23,'Bala Table'!$A:$B,2,FALSE) -> 0.794 | E23: =E22*(1+Assumptions!$G$34) -> 2111283.5 | F23: =E23*D23 -> 1676359.1 | G23: =IF(A23<=Assumptions!$C$26,PV('Scenario Tables'!G$27/12,(Assumptions!$C$26-A23)*12,-$C$11),0) -> 844441.91 | H23: =F23-G23 -> 831917.17 | I23: =IF(A23<=Assumptions!$C$26,G22*'Scenario Tables'!G$27,0) -> 22685.833 | J23: =IF(A23<=Assumptions!$C$26,$C$12-I23,0) -> 27756.97 | K23: =IF(Assumptions!$C$39="Investment",Assumptions!$G$35*12*(1+Assumptions!$G$36)^(A23-1)*(1-Assumptions!$C$40),Assumptions!$G$35*12*(1+Assumptions!$G$36)^(A23-1)) -> 62029.026 | L23: =IF(Assumptions!$C$39="Investment",_xlfn.LET(_xlpm.gr,Assumptions!$G$35*12*(1+Assumptions!$G$36)^(A23-1),Assumptions!$G$37*(1+Assumptions!$G$36)^(A23-1)+MIN(_xlpm.gr,30000)*0.12+MAX(0,MIN(_xlpm.gr,45000)-30000)*0.2+MAX(0,MIN(_xlpm.gr,60000)-45000)*0.28+MAX(0,_xlpm.gr-60000)*0.36+K23*Assumptions!$C$41),Assumptions!$G$37*(1+Assumptions!$G$36)^(A23-1)+MAX(0,MIN(K23,25000)-12000)*0.04+MAX(0,MIN(K23,38000)-25000)*0.06+MAX(0,MIN(K23,50000)-38000)*0.08+MAX(0,MIN(K23,65000)-50000)*0.1+MAX(0,MIN(K23,80000)-65000)*0.12+MAX(0,MIN(K23,95000)-80000)*0.14+MAX(0,MIN(K23,110000)-95000)*0.16+MAX(0,K23-110000)*0.23) -> 4979.1677 | M23: =IF(Assumptions!$C$39="Investment",(K23-I23-L23)*(1-Assumptions!$C$42),K23-I23-L23) -> 34364.025 | N23: =IF(A23=1,M23,N22+M23) -> 227300.36 | O23: =(H23-$C$10)/$C$10 -> 1.0182367 | P23: =Assumptions!$C$8*(1+Assumptions!$C$9)^A23-Assumptions!$C$8+$C$7*((1+Assumptions!$C$9)^A23-1) -> 65520.869 | Q23: =H23-P23 -> 766396.3 | R23: =N23/(1+Assumptions!$C$43)^A23 -> 186555.99 | S23: =((H23/$C$10)^(1/A23))/(1+Assumptions!$C$43)-1 -> 0.065117811
A24: =A23+1 -> 9 | B24: =B23+1 -> 41 | C24: =C23-1 -> 79 | D24: =VLOOKUP(C24,'Bala Table'!$A:$B,2,FALSE) -> 0.788 | E24: =E23*(1+Assumptions!$G$34) -> 2174622 | F24: =E24*D24 -> 1713602.1 | G24: =IF(A24<=Assumptions!$C$26,PV('Scenario Tables'!G$27/12,(Assumptions!$C$26-A24)*12,-$C$11),0) -> 815612.66 | H24: =F24-G24 -> 897989.46 | I24: =IF(A24<=Assumptions!$C$26,G23*'Scenario Tables'!G$27,0) -> 21955.49 | J24: =IF(A24<=Assumptions!$C$26,$C$12-I24,0) -> 28487.314 | K24: =IF(Assumptions!$C$39="Investment",Assumptions!$G$35*12*(1+Assumptions!$G$36)^(A24-1)*(1-Assumptions!$C$40),Assumptions!$G$35*12*(1+Assumptions!$G$36)^(A24-1)) -> 63269.607 | L24: =IF(Assumptions!$C$39="Investment",_xlfn.LET(_xlpm.gr,Assumptions!$G$35*12*(1+Assumptions!$G$36)^(A24-1),Assumptions!$G$37*(1+Assumptions!$G$36)^(A24-1)+MIN(_xlpm.gr,30000)*0.12+MAX(0,MIN(_xlpm.gr,45000)-30000)*0.2+MAX(0,MIN(_xlpm.gr,60000)-45000)*0.28+MAX(0,_xlpm.gr-60000)*0.36+K24*Assumptions!$C$41),Assumptions!$G$37*(1+Assumptions!$G$36)^(A24-1)+MAX(0,MIN(K24,25000)-12000)*0.04+MAX(0,MIN(K24,38000)-25000)*0.06+MAX(0,MIN(K24,50000)-38000)*0.08+MAX(0,MIN(K24,65000)-50000)*0.1+MAX(0,MIN(K24,80000)-65000)*0.12+MAX(0,MIN(K24,95000)-80000)*0.14+MAX(0,MIN(K24,110000)-95000)*0.16+MAX(0,K24-110000)*0.23) -> 5133.551 | M24: =IF(Assumptions!$C$39="Investment",(K24-I24-L24)*(1-Assumptions!$C$42),K24-I24-L24) -> 36180.566 | N24: =IF(A24=1,M24,N23+M24) -> 263480.92 | O24: =(H24-$C$10)/$C$10 -> 1.1785285 | P24: =Assumptions!$C$8*(1+Assumptions!$C$9)^A24-Assumptions!$C$8+$C$7*((1+Assumptions!$C$9)^A24-1) -> 74658.891 | Q24: =H24-P24 -> 823330.57 | R24: =N24/(1+Assumptions!$C$43)^A24 -> 210976.65 | S24: =((H24/$C$10)^(1/A24))/(1+Assumptions!$C$43)-1 -> 0.063775121
A25: =A24+1 -> 10 | B25: =B24+1 -> 42 | C25: =C24-1 -> 78 | D25: =VLOOKUP(C25,'Bala Table'!$A:$B,2,FALSE) -> 0.782 | E25: =E24*(1+Assumptions!$G$34) -> 2239860.6 | F25: =E25*D25 -> 1751571 | G25: =IF(A25<=Assumptions!$C$26,PV('Scenario Tables'!G$27/12,(Assumptions!$C$26-A25)*12,-$C$11),0) -> 786024.85 | H25: =F25-G25 -> 965546.17 | I25: =IF(A25<=Assumptions!$C$26,G24*'Scenario Tables'!G$27,0) -> 21205.929 | J25: =IF(A25<=Assumptions!$C$26,$C$12-I25,0) -> 29236.875 | K25: =IF(Assumptions!$C$39="Investment",Assumptions!$G$35*12*(1+Assumptions!$G$36)^(A25-1)*(1-Assumptions!$C$40),Assumptions!$G$35*12*(1+Assumptions!$G$36)^(A25-1)) -> 64534.999 | L25: =IF(Assumptions!$C$39="Investment",_xlfn.LET(_xlpm.gr,Assumptions!$G$35*12*(1+Assumptions!$G$36)^(A25-1),Assumptions!$G$37*(1+Assumptions!$G$36)^(A25-1)+MIN(_xlpm.gr,30000)*0.12+MAX(0,MIN(_xlpm.gr,45000)-30000)*0.2+MAX(0,MIN(_xlpm.gr,60000)-45000)*0.28+MAX(0,_xlpm.gr-60000)*0.36+K25*Assumptions!$C$41),Assumptions!$G$37*(1+Assumptions!$G$36)^(A25-1)+MAX(0,MIN(K25,25000)-12000)*0.04+MAX(0,MIN(K25,38000)-25000)*0.06+MAX(0,MIN(K25,50000)-38000)*0.08+MAX(0,MIN(K25,65000)-50000)*0.1+MAX(0,MIN(K25,80000)-65000)*0.12+MAX(0,MIN(K25,95000)-80000)*0.14+MAX(0,MIN(K25,110000)-95000)*0.16+MAX(0,K25-110000)*0.23) -> 5291.0221 | M25: =IF(Assumptions!$C$39="Investment",(K25-I25-L25)*(1-Assumptions!$C$42),K25-I25-L25) -> 38038.048 | N25: =IF(A25=1,M25,N24+M25) -> 301518.97 | O25: =(H25-$C$10)/$C$10 -> 1.3424216 | P25: =Assumptions!$C$8*(1+Assumptions!$C$9)^A25-Assumptions!$C$8+$C$7*((1+Assumptions!$C$9)^A25-1) -> 84025.363 | Q25: =H25-P25 -> 881520.8 | R25: =N25/(1+Assumptions!$C$43)^A25 -> 235546.14 | S25: =((H25/$C$10)^(1/A25))/(1+Assumptions!$C$43)-1 -> 0.062288892
A26: =A25+1 -> 11 | B26: =B25+1 -> 43 | C26: =C25-1 -> 77 | D26: =VLOOKUP(C26,'Bala Table'!$A:$B,2,FALSE) -> 0.776 | E26: =E25*(1+Assumptions!$G$34) -> 2307056.5 | F26: =E26*D26 -> 1790275.8 | G26: =IF(A26<=Assumptions!$C$26,PV('Scenario Tables'!G$27/12,(Assumptions!$C$26-A26)*12,-$C$11),0) -> 755658.52 | H26: =F26-G26 -> 1034617.3 | I26: =IF(A26<=Assumptions!$C$26,G25*'Scenario Tables'!G$27,0) -> 20436.646 | J26: =IF(A26<=Assumptions!$C$26,$C$12-I26,0) -> 30006.158 | K26: =IF(Assumptions!$C$39="Investment",Assumptions!$G$35*12*(1+Assumptions!$G$36)^(A26-1)*(1-Assumptions!$C$40),Assumptions!$G$35*12*(1+Assumptions!$G$36)^(A26-1)) -> 65825.699 | L26: =IF(Assumptions!$C$39="Investment",_xlfn.LET(_xlpm.gr,Assumptions!$G$35*12*(1+Assumptions!$G$36)^(A26-1),Assumptions!$G$37*(1+Assumptions!$G$36)^(A26-1)+MIN(_xlpm.gr,30000)*0.12+MAX(0,MIN(_xlpm.gr,45000)-30000)*0.2+MAX(0,MIN(_xlpm.gr,60000)-45000)*0.28+MAX(0,_xlpm.gr-60000)*0.36+K26*Assumptions!$C$41),Assumptions!$G$37*(1+Assumptions!$G$36)^(A26-1)+MAX(0,MIN(K26,25000)-12000)*0.04+MAX(0,MIN(K26,38000)-25000)*0.06+MAX(0,MIN(K26,50000)-38000)*0.08+MAX(0,MIN(K26,65000)-50000)*0.1+MAX(0,MIN(K26,80000)-65000)*0.12+MAX(0,MIN(K26,95000)-80000)*0.14+MAX(0,MIN(K26,110000)-95000)*0.16+MAX(0,K26-110000)*0.23) -> 5468.1565 | M26: =IF(Assumptions!$C$39="Investment",(K26-I26-L26)*(1-Assumptions!$C$42),K26-I26-L26) -> 39920.896 | N26: =IF(A26=1,M26,N25+M26) -> 341439.87 | O26: =(H26-$C$10)/$C$10 -> 1.5099886 | P26: =Assumptions!$C$8*(1+Assumptions!$C$9)^A26-Assumptions!$C$8+$C$7*((1+Assumptions!$C$9)^A26-1) -> 93625.997 | Q26: =H26-P26 -> 940991.29 | R26: =N26/(1+Assumptions!$C$43)^A26 -> 260226.61 | S26: =((H26/$C$10)^(1/A26))/(1+Assumptions!$C$43)-1 -> 0.060742401
A27: =A26+1 -> 12 | B27: =B26+1 -> 44 | C27: =C26-1 -> 76 | D27: =VLOOKUP(C27,'Bala Table'!$A:$B,2,FALSE) -> 0.77 | E27: =E26*(1+Assumptions!$G$34) -> 2376268.1 | F27: =E27*D27 -> 1829726.5 | G27: =IF(A27<=Assumptions!$C$26,PV('Scenario Tables'!G$27/12,(Assumptions!$C$26-A27)*12,-$C$11),0) -> 724493.19 | H27: =F27-G27 -> 1105233.3 | I27: =IF(A27<=Assumptions!$C$26,G26*'Scenario Tables'!G$27,0) -> 19647.122 | J27: =IF(A27<=Assumptions!$C$26,$C$12-I27,0) -> 30795.682 | K27: =IF(Assumptions!$C$39="Investment",Assumptions!$G$35*12*(1+Assumptions!$G$36)^(A27-1)*(1-Assumptions!$C$40),Assumptions!$G$35*12*(1+Assumptions!$G$36)^(A27-1)) -> 67142.213 | L27: =IF(Assumptions!$C$39="Investment",_xlfn.LET(_xlpm.gr,Assumptions!$G$35*12*(1+Assumptions!$G$36)^(A27-1),Assumptions!$G$37*(1+Assumptions!$G$36)^(A27-1)+MIN(_xlpm.gr,30000)*0.12+MAX(0,MIN(_xlpm.gr,45000)-30000)*0.2+MAX(0,MIN(_xlpm.gr,60000)-45000)*0.28+MAX(0,_xlpm.gr-60000)*0.36+K27*Assumptions!$C$41),Assumptions!$G$37*(1+Assumptions!$G$36)^(A27-1)+MAX(0,MIN(K27,25000)-12000)*0.04+MAX(0,MIN(K27,38000)-25000)*0.06+MAX(0,MIN(K27,50000)-38000)*0.08+MAX(0,MIN(K27,65000)-50000)*0.1+MAX(0,MIN(K27,80000)-65000)*0.12+MAX(0,MIN(K27,95000)-80000)*0.14+MAX(0,MIN(K27,110000)-95000)*0.16+MAX(0,K27-110000)*0.23) -> 5658.3196 | M27: =IF(Assumptions!$C$39="Investment",(K27-I27-L27)*(1-Assumptions!$C$42),K27-I27-L27) -> 41836.771 | N27: =IF(A27=1,M27,N26+M27) -> 383276.64 | O27: =(H27-$C$10)/$C$10 -> 1.6813034 | P27: =Assumptions!$C$8*(1+Assumptions!$C$9)^A27-Assumptions!$C$8+$C$7*((1+Assumptions!$C$9)^A27-1) -> 103466.65 | Q27: =H27-P27 -> 1001766.6 | R27: =N27/(1+Assumptions!$C$43)^A27 -> 284987.6 | S27: =((H27/$C$10)^(1/A27))/(1+Assumptions!$C$43)-1 -> 0.059184537
... A35: =A34+1 -> 20 | B35: =B34+1 -> 52 | C35: =C34-1 -> 68 | D35: =VLOOKUP(C35,'Bala Table'!$A:$B,2,FALSE) -> 0.72 | E35: =E34*(1+Assumptions!$G$34) -> 3010185.4 | F35: =E35*D35 -> 2167333.5 | G35: =IF(A35<=Assumptions!$C$26,PV('Scenario Tables'!G$27/12,(Assumptions!$C$26-A35)*12,-$C$11),0) -> 443763.81 | H35: =F35-G35 -> 1723569.7 | I35: =IF(A35<=Assumptions!$C$26,G34*'Scenario Tables'!G$27,0) -> 12535.285 | J35: =IF(A35<=Assumptions!$C$26,$C$12-I35,0) -> 37907.519 | K35: =IF(Assumptions!$C$39="Investment",Assumptions!$G$35*12*(1+Assumptions!$G$36)^(A35-1)*(1-Assumptions!$C$40),Assumptions!$G$35*12*(1+Assumptions!$G$36)^(A35-1)) -> 78667.803 | L35: =IF(Assumptions!$C$39="Investment",_xlfn.LET(_xlpm.gr,Assumptions!$G$35*12*(1+Assumptions!$G$36)^(A35-1),Assumptions!$G$37*(1+Assumptions!$G$36)^(A35-1)+MIN(_xlpm.gr,30000)*0.12+MAX(0,MIN(_xlpm.gr,45000)-30000)*0.2+MAX(0,MIN(_xlpm.gr,60000)-45000)*0.28+MAX(0,_xlpm.gr-60000)*0.36+K35*Assumptions!$C$41),Assumptions!$G$37*(1+Assumptions!$G$36)^(A35-1)+MAX(0,MIN(K35,25000)-12000)*0.04+MAX(0,MIN(K35,38000)-25000)*0.06+MAX(0,MIN(K35,50000)-38000)*0.08+MAX(0,MIN(K35,65000)-50000)*0.1+MAX(0,MIN(K35,80000)-65000)*0.12+MAX(0,MIN(K35,95000)-80000)*0.14+MAX(0,MIN(K35,110000)-95000)*0.16+MAX(0,K35-110000)*0.23) -> 7323.1271 | M35: =IF(Assumptions!$C$39="Investment",(K35-I35-L35)*(1-Assumptions!$C$42),K35-I35-L35) -> 58809.391 | N35: =IF(A35=1,M35,N34+M35) -> 792353.86 | O35: =(H35-$C$10)/$C$10 -> 3.1813917 | P35: =Assumptions!$C$8*(1+Assumptions!$C$9)^A35-Assumptions!$C$8+$C$7*((1+Assumptions!$C$9)^A35-1) -> 191584.93 | Q35: =H35-P35 -> 1531984.7 | R35: =N35/(1+Assumptions!$C$43)^A35 -> 483550.54 | S35: =((H35/$C$10)^(1/A35))/(1+Assumptions!$C$43)-1 -> 0.047953898
A37: SUMMARY METRICS
A38: Terminal Property Equity (Year 20) | E38: =H35 -> 1723569.7 | G38: Terminal Loan Balance | I38: =G35 -> 443763.81
A39: Net Equity After CPF Accrued Interest | E39: =Q35 -> 1531984.7 | G39: Total CPF Accrued Interest Owed | I39: =P35 -> 191584.93
A40: ROE on Day-1 Equity (20yr) | E40: =O35 -> 3.1813917 | G40: Annualized ROE (CAGR) | I40: =(H35/$C$10)^(1/20)-1 -> 0.074152745
A41: Cumulative Net Holding Benefit | E41: =N35 -> 792353.86 | G41: Breakeven Year (Equity > Day-1 Outlay) | I41: {=IFERROR(MATCH(TRUE,INDEX(H16:H35>$C$10,0),0),"Never")} -> 2
A42: Real CAGR (Inflation-Adj) | E42: =S35 -> 0.047953898 | G42: Real Cumul. Net Benefit (Year 20) | I42: =R35 -> 483550.54
A43: Inflation Rate Assumed | E43: =Assumptions!$C$43 -> 0.025

Sheet Condo 99LH
A1: CONDO 99-YEAR LEASEHOLD (2020 BUILD) — 20-YEAR ANALYSIS
A3: CAPITAL STRUCTURE
A4: Purchase Price | C4: =Assumptions!D31 -> 2500000
A5: Loan Amount (75% LTV) | C5: =Assumptions!C22*Assumptions!D31 -> 1875000
A6: Cash Downpayment | C6: =Assumptions!C23*Assumptions!D31-C7 -> 475000
A7: CPF OA Used | C7: =MIN(Assumptions!C24*Assumptions!D31,Assumptions!C8) -> 150000
A8: Total Upfront Costs | C8: =Assumptions!D51 -> 138200
A9: Total Cash Outlay (Day 1) | C9: =C6+C8 -> 613200
A10: Total Equity at Risk (Cash + CPF) | C10: =C6+C7+C8 -> 763200
A11: Monthly Mortgage Payment | C11: =PMT('Scenario Tables'!D$27/12,Assumptions!C26*12,-C5) -> 6625.9704
A12: Annual Mortgage Payment | C12: =C11*12 -> 79511.645
A14: Year | B14: Age | C14: Remaining Lease | D14: Bala Factor (%FH) | E14: FH Equiv. Land Value | F14: Leasehold Market Value | G14: Loan Balance | H14: Property Equity | I14: Annual Interest | J14: Annual Principal | K14: Rent / Imputed Rent (Annual) | L14: Maintenance + Prop Tax (+Mgmt) | M14: Net Holding Benefit (After Tax) | N14: Cumulative Net Benefit | O14: ROE on Equity (%) | P14: CPF Accrued Interest | Q14: Net Equity After CPF | R14: Real Cumul. Net Benefit | S14: Real ROE (CAGR %)
A15: 0 | B15: =Assumptions!C4 -> 32 | C15: =Assumptions!D33 -> 93 | D15: =VLOOKUP(C15,'Bala Table'!A:B,2,FALSE) -> 0.87 | E15: =C4/D15 -> 2873563.2 | F15: =C4 -> 2500000 | G15: =C5 -> 1875000 | H15: =F15-G15 -> 625000 | I15: - | J15: - | K15: - | L15: - | M15: - | N15: - | O15: - | P15: 0 | Q15: =H15-P15 -> 625000 | R15: - | S15: -
A16: =A15+1 -> 1 | B16: =B15+1 -> 33 | C16: =C15-1 -> 92 | D16: =VLOOKUP(C16,'Bala Table'!$A:$B,2,FALSE) -> 0.865 | E16: =E15*(1+Assumptions!$D$34) -> 2959770.1 | F16: =E16*D16 -> 2560201.1 | G16: =IF(A16<=Assumptions!$C$26,PV('Scenario Tables'!D$27/12,(Assumptions!$C$26-A16)*12,-$C$11),0) -> 1826448.9 | H16: =F16-G16 -> 733752.26 | I16: =IF(A16<=Assumptions!$C$26,G15*'Scenario Tables'!D$27,0) -> 31331.25 | J16: =IF(A16<=Assumptions!$C$26,$C$12-I16,0) -> 48180.395 | K16: =IF(Assumptions!$C$39="Investment",Assumptions!$D$35*12*(1+Assumptions!$D$36)^(A16-1)*(1-Assumptions!$C$40),Assumptions!$D$35*12*(1+Assumptions!$D$36)^(A16-1)) -> 62400 | L16: =IF(Assumptions!$C$39="Investment",_xlfn.LET(_xlpm.gr,Assumptions!$D$35*12*(1+Assumptions!$D$36)^(A16-1),Assumptions!$D$37*(1+Assumptions!$D$36)^(A16-1)+MIN(_xlpm.gr,30000)*0.12+MAX(0,MIN(_xlpm.gr,45000)-30000)*0.2+MAX(0,MIN(_xlpm.gr,60000)-45000)*0.28+MAX(0,_xlpm.gr-60000)*0.36+K16*Assumptions!$C$41),Assumptions!$D$37*(1+Assumptions!$D$36)^(A16-1)+MAX(0,MIN(K16,25000)-12000)*0.04+MAX(0,MIN(K16,38000)-25000)*0.06+MAX(0,MIN(K16,50000)-38000)*0.08+MAX(0,MIN(K16,65000)-50000)*0.1+MAX(0,MIN(K16,80000)-65000)*0.12+MAX(0,MIN(K16,95000)-80000)*0.14+MAX(0,MIN(K16,110000)-95000)*0.16+MAX(0,K16-110000)*0.23) -> 9500 | M16: =IF(Assumptions!$C$39="Investment",(K16-I16-L16)*(1-Assumptions!$C$42),K16-I16-L16) -> 21568.75 | N16: =IF(A16=1,M16,N15+M16) -> 21568.75 | O16: =(H16-$C$10)/$C$10 -> -0.03858456 | P16: =Assumptions!$C$8*(1+Assumptions!$C$9)^A16-Assumptions!$C$8+$C$7*((1+Assumptions!$C$9)^A16-1) -> 7500 | Q16: =H16-P16 -> 726252.26 | R16: =N16/(1+Assumptions!$C$43)^A16 -> 21042.683 | S16: =((H16/$C$10)^(1/A16))/(1+Assumptions!$C$43)-1 -> -0.062033717
A17: =A16+1 -> 2 | B17: =B16+1 -> 34 | C17: =C16-1 -> 91 | D17: =VLOOKUP(C17,'Bala Table'!$A:$B,2,FALSE) -> 0.855 | E17: =E16*(1+Assumptions!$D$34) -> 3048563.2 | F17: =E17*D17 -> 2606521.6 | G17: =IF(A17<=Assumptions!$C$26,PV('Scenario Tables'!D$27/12,(Assumptions!$C$26-A17)*12,-$C$11),0) -> 1777080.2 | H17: =F17-G17 -> 829441.31 | I17: =IF(A17<=Assumptions!$C$26,G16*'Scenario Tables'!D$27,0) -> 30519.961 | J17: =IF(A17<=Assumptions!$C$26,$C$12-I17,0) -> 48991.684 | K17: =IF(Assumptions!$C$39="Investment",Assumptions!$D$35*12*(1+Assumptions!$D$36)^(A17-1)*(1-Assumptions!$C$40),Assumptions!$D$35*12*(1+Assumptions!$D$36)^(A17-1)) -> 63648 | L17: =IF(Assumptions!$C$39="Investment",_xlfn.LET(_xlpm.gr,Assumptions!$D$35*12*(1+Assumptions!$D$36)^(A17-1),Assumptions!$D$37*(1+Assumptions!$D$36)^(A17-1)+MIN(_xlpm.gr,30000)*0.12+MAX(0,MIN(_xlpm.gr,45000)-30000)*0.2+MAX(0,MIN(_xlpm.gr,60000)-45000)*0.28+MAX(0,_xlpm.gr-60000)*0.36+K17*Assumptions!$C$41),Assumptions!$D$37*(1+Assumptions!$D$36)^(A17-1)+MAX(0,MIN(K17,25000)-12000)*0.04+MAX(0,MIN(K17,38000)-25000)*0.06+MAX(0,MIN(K17,50000)-38000)*0.08+MAX(0,MIN(K17,65000)-50000)*0.1+MAX(0,MIN(K17,80000)-65000)*0.12+MAX(0,MIN(K17,95000)-80000)*0.14+MAX(0,MIN(K17,110000)-95000)*0.16+MAX(0,K17-110000)*0.23) -> 9744.8 | M17: =IF(Assumptions!$C$39="Investment",(K17-I17-L17)*(1-Assumptions!$C$42),K17-I17-L17) -> 23383.239 | N17: =IF(A17=1,M17,N16+M17) -> 44951.989 | O17: =(H17-$C$10)/$C$10 -> 0.086794173 | P17: =Assumptions!$C$8*(1+Assumptions!$C$9)^A17-Assumptions!$C$8+$C$7*((1+Assumptions!$C$9)^A17-1) -> 15187.5 | Q17: =H17-P17 -> 814253.81 | R17: =N17/(1+Assumptions!$C$43)^A17 -> 42785.95 | S17: =((H17/$C$10)^(1/A17))/(1+Assumptions!$C$43)-1 -> 0.01706752
A18: =A17+1 -> 3 | B18: =B17+1 -> 35 | C18: =C17-1 -> 90 | D18: =VLOOKUP(C18,'Bala Table'!$A:$B,2,FALSE) -> 0.85 | E18: =E17*(1+Assumptions!$D$34) -> 3140020.1 | F18: =E18*D18 -> 2669017.1 | G18: =IF(A18<=Assumptions!$C$26,PV('Scenario Tables'!D$27/12,(Assumptions!$C$26-A18)*12,-$C$11),0) -> 1726880.3 | H18: =F18-G18 -> 942136.8 | I18: =IF(A18<=Assumptions!$C$26,G17*'Scenario Tables'!D$27,0) -> 29695.011 | J18: =IF(A18<=Assumptions!$C$26,$C$12-I18,0) -> 49816.634 | K18: =IF(Assumptions!$C$39="Investment",Assumptions!$D$35*12*(1+Assumptions!$D$36)^(A18-1)*(1-Assumptions!$C$40),Assumptions!$D$35*12*(1+Assumptions!$D$36)^(A18-1)) -> 64920.96 | L18: =IF(Assumptions!$C$39="Investment",_xlfn.LET(_xlpm.gr,Assumptions!$D$35*12*(1+Assumptions!$D$36)^(A18-1),Assumptions!$D$37*(1+Assumptions!$D$36)^(A18-1)+MIN(_xlpm.gr,30000)*0.12+MAX(0,MIN(_xlpm.gr,45000)-30000)*0.2+MAX(0,MIN(_xlpm.gr,60000)-45000)*0.28+MAX(0,_xlpm.gr-60000)*0.36+K18*Assumptions!$C$41),Assumptions!$D$37*(1+Assumptions!$D$36)^(A18-1)+MAX(0,MIN(K18,25000)-12000)*0.04+MAX(0,MIN(K18,38000)-25000)*0.06+MAX(0,MIN(K18,50000)-38000)*0.08+MAX(0,MIN(K18,65000)-50000)*0.1+MAX(0,MIN(K18,80000)-65000)*0.12+MAX(0,MIN(K18,95000)-80000)*0.14+MAX(0,MIN(K18,110000)-95000)*0.16+MAX(0,K18-110000)*0.23) -> 9994.496 | M18: =IF(Assumptions!$C$39="Investment",(K18-I18-L18)*(1-Assumptions!$C$42),K18-I18-L18) -> 25231.453 | N18: =IF(A18=1,M18,N17+M18) -> 70183.442 | O18: =(H18-$C$10)/$C$10 -> 0.23445598 | P18: =Assumptions!$C$8*(1+Assumptions!$C$9)^A18-Assumptions!$C$8+$C$7*((1+Assumptions!$C$9)^A18-1) -> 23067.187 | Q18: =H18-P18 -> 919069.62 | R18: =N18/(1+Assumptions!$C$43)^A18 -> 65172.303 | S18: =((H18/$C$10)^(1/A18))/(1+Assumptions!$C$43)-1 -> 0.04656933
A19: =A18+1 -> 4 | B19: =B18+1 -> 36 | C19: =C18-1 -> 89 | D19: =VLOOKUP(C19,'Bala Table'!$A:$B,2,FALSE) -> 0.845 | E19: =E18*(1+Assumptions!$D$34) -> 3234220.7 | F19: =E19*D19 -> 2732916.5 | G19: =IF(A19<=Assumptions!$C$26,PV('Scenario Tables'!D$27/12,(Assumptions!$C$26-A19)*12,-$C$11),0) -> 1675835.1 | H19: =F19-G19 -> 1057081.5 | I19: =IF(A19<=Assumptions!$C$26,G18*'Scenario Tables'!D$27,0) -> 28856.17 | J19: =IF(A19<=Assumptions!$C$26,$C$12-I19,0) -> 50655.475 | K19: =IF(Assumptions!$C$39="Investment",Assumptions!$D$35*12*(1+Assumptions!$D$36)^(A19-1)*(1-Assumptions!$C$40),Assumptions!$D$35*12*(1+Assumptions!$D$36)^(A19-1)) -> 66219.379 | L19: =IF(Assumptions!$C$39="Investment",_xlfn.LET(_xlpm.gr,Assumptions!$D$35*12*(1+Assumptions!$D$36)^(A19-1),Assumptions!$D$37*(1+Assumptions!$D$36)^(A19-1)+MIN(_xlpm.gr,30000)*0.12+MAX(0,MIN(_xlpm.gr,45000)-30000)*0.2+MAX(0,MIN(_xlpm.gr,60000)-45000)*0.28+MAX(0,_xlpm.gr-60000)*0.36+K19*Assumptions!$C$41),Assumptions!$D$37*(1+Assumptions!$D$36)^(A19-1)+MAX(0,MIN(K19,25000)-12000)*0.04+MAX(0,MIN(K19,38000)-25000)*0.06+MAX(0,MIN(K19,50000)-38000)*0.08+MAX(0,MIN(K19,65000)-50000)*0.1+MAX(0,MIN(K19,80000)-65000)*0.12+MAX(0,MIN(K19,95000)-80000)*0.14+MAX(0,MIN(K19,110000)-95000)*0.16+MAX(0,K19-110000)*0.23) -> 10273.574 | M19: =IF(Assumptions!$C$39="Investment",(K19-I19-L19)*(1-Assumptions!$C$42),K19-I19-L19) -> 27089.636 | N19: =IF(A19=1,M19,N18+M19) -> 97273.078 | O19: =(H19-$C$10)/$C$10 -> 0.38506479 | P19: =Assumptions!$C$8*(1+Assumptions!$C$9)^A19-Assumptions!$C$8+$C$7*((1+Assumptions!$C$9)^A19-1) -> 31143.867 | Q19: =H19-P19 -> 1025937.6 | R19: =N19/(1+Assumptions!$C$43)^A19 -> 88124.608 | S19: =((H19/$C$10)^(1/A19))/(1+Assumptions!$C$43)-1 -> 0.058384954
A20: =A19+1 -> 5 | B20: =B19+1 -> 37 | C20: =C19-1 -> 88 | D20: =VLOOKUP(C20,'Bala Table'!$A:$B,2,FALSE) -> 0.84 | E20: =E19*(1+Assumptions!$D$34) -> 3331247.3 | F20: =E20*D20 -> 2798247.8 | G20: =IF(A20<=Assumptions!$C$26,PV('Scenario Tables'!D$27/12,(Assumptions!$C$26-A20)*12,-$C$11),0) -> 1623930.3 | H20: =F20-G20 -> 1174317.5 | I20: =IF(A20<=Assumptions!$C$26,G19*'Scenario Tables'!D$27,0) -> 28003.204 | J20: =IF(A20<=Assumptions!$C$26,$C$12-I20,0) -> 51508.441 | K20: =IF(Assumptions!$C$39="Investment",Assumptions!$D$35*12*(1+Assumptions!$D$36)^(A20-1)*(1-Assumptions!$C$40),Assumptions!$D$35*12*(1+Assumptions!$D$36)^(A20-1)) -> 67543.767 | L20: =IF(Assumptions!$C$39="Investment",_xlfn.LET(_xlpm.gr,Assumptions!$D$35*12*(1+Assumptions!$D$36)^(A20-1),Assumptions!$D$37*(1+Assumptions!$D$36)^(A20-1)+MIN(_xlpm.gr,30000)*0.12+MAX(0,MIN(_xlpm.gr,45000)-30000)*0.2+MAX(0,MIN(_xlpm.gr,60000)-45000)*0.28+MAX(0,_xlpm.gr-60000)*0.36+K20*Assumptions!$C$41),Assumptions!$D$37*(1+Assumptions!$D$36)^(A20-1)+MAX(0,MIN(K20,25000)-12000)*0.04+MAX(0,MIN(K20,38000)-25000)*0.06+MAX(0,MIN(K20,50000)-38000)*0.08+MAX(0,MIN(K20,65000)-50000)*0.1+MAX(0,MIN(K20,80000)-65000)*0.12+MAX(0,MIN(K20,95000)-80000)*0.14+MAX(0,MIN(K20,110000)-95000)*0.16+MAX(0,K20-110000)*0.23) -> 10559.845 | M20: =IF(Assumptions!$C$39="Investment",(K20-I20-L20)*(1-Assumptions!$C$42),K20-I20-L20) -> 28980.718 | N20: =IF(A20=1,M20,N19+M20) -> 126253.8 | O20: =(H20-$C$10)/$C$10 -> 0.53867594 | P20: =Assumptions!$C$8*(1+Assumptions!$C$9)^A20-Assumptions!$C$8+$C$7*((1+Assumptions!$C$9)^A20-1) -> 39422.464 | Q20: =H20-P20 -> 1134895 | R20: =N20/(1+Assumptions!$C$43)^A20 -> 111589.96 | S20: =((H20/$C$10)^(1/A20))/(1+Assumptions!$C$43)-1 -> 0.06342182
A21: =A20+1 -> 6 | B21: =B20+1 -> 38 | C21: =C20-1 -> 87 | D21: =VLOOKUP(C21,'Bala Table'!$A:$B,2,FALSE) -> 0.835 | E21: =E20*(1+Assumptions!$D$34) -> 3431184.8 | F21: =E21*D21 -> 2865039.3 | G21: =IF(A21<=Assumptions!$C$26,PV('Scenario Tables'!D$27/12,(Assumptions!$C$26-A21)*12,-$C$11),0) -> 1571151.5 | H21: =F21-G21 -> 1293887.8 | I21: =IF(A21<=Assumptions!$C$26,G20*'Scenario Tables'!D$27,0) -> 27135.875 | J21: =IF(A21<=Assumptions!$C$26,$C$12-I21,0) -> 52375.77 | K21: =IF(Assumptions!$C$39="Investment",Assumptions!$D$35*12*(1+Assumptions!$D$36)^(A21-1)*(1-Assumptions!$C$40),Assumptions!$D$35*12*(1+Assumptions!$D$36)^(A21-1)) -> 68894.642 | L21: =IF(Assumptions!$C$39="Investment",_xlfn.LET(_xlpm.gr,Assumptions!$D$35*12*(1+Assumptions!$D$36)^(A21-1),Assumptions!$D$37*(1+Assumptions!$D$36)^(A21-1)+MIN(_xlpm.gr,30000)*0.12+MAX(0,MIN(_xlpm.gr,45000)-30000)*0.2+MAX(0,MIN(_xlpm.gr,60000)-45000)*0.28+MAX(0,_xlpm.gr-60000)*0.36+K21*Assumptions!$C$41),Assumptions!$D$37*(1+Assumptions!$D$36)^(A21-1)+MAX(0,MIN(K21,25000)-12000)*0.04+MAX(0,MIN(K21,38000)-25000)*0.06+MAX(0,MIN(K21,50000)-38000)*0.08+MAX(0,MIN(K21,65000)-50000)*0.1+MAX(0,MIN(K21,80000)-65000)*0.12+MAX(0,MIN(K21,95000)-80000)*0.14+MAX(0,MIN(K21,110000)-95000)*0.16+MAX(0,K21-110000)*0.23) -> 10851.842 | M21: =IF(Assumptions!$C$39="Investment",(K21-I21-L21)*(1-Assumptions!$C$42),K21-I21-L21) -> 30906.925 | N21: =IF(A21=1,M21,N20+M21) -> 157160.72 | O21: =(H21-$C$10)/$C$10 -> 0.69534559 | P21: =Assumptions!$C$8*(1+Assumptions!$C$9)^A21-Assumptions!$C$8+$C$7*((1+Assumptions!$C$9)^A21-1) -> 47908.025 | Q21: =H21-P21 -> 1245979.7 | R21: =N21/(1+Assumptions!$C$43)^A21 -> 135519.2 | S21: =((H21/$C$10)^(1/A21))/(1+Assumptions!$C$43)-1 -> 0.065334132
A22: =A21+1 -> 7 | B22: =B21+1 -> 39 | C22: =C21-1 -> 86 | D22: =VLOOKUP(C22,'Bala Table'!$A:$B,2,FALSE) -> 0.83 | E22: =E21*(1+Assumptions!$D$34) -> 3534120.3 | F22: =E22*D22 -> 2933319.9 | G22: =IF(A22<=Assumptions!$C$26,PV('Scenario Tables'!D$27/12,(Assumptions!$C$26-A22)*12,-$C$11),0) -> 1517484 | H22: =F22-G22 -> 1415835.8 | I22: =IF(A22<=Assumptions!$C$26,G21*'Scenario Tables'!D$27,0) -> 26253.942 | J22: =IF(A22<=Assumptions!$C$26,$C$12-I22,0) -> 53257.703 | K22: =IF(Assumptions!$C$39="Investment",Assumptions!$D$35*12*(1+Assumptions!$D$36)^(A22-1)*(1-Assumptions!$C$40),Assumptions!$D$35*12*(1+Assumptions!$D$36)^(A22-1)) -> 70272.535 | L22: =IF(Assumptions!$C$39="Investment",_xlfn.LET(_xlpm.gr,Assumptions!$D$35*12*(1+Assumptions!$D$36)^(A22-1),Assumptions!$D$37*(1+Assumptions!$D$36)^(A22-1)+MIN(_xlpm.gr,30000)*0.12+MAX(0,MIN(_xlpm.gr,45000)-30000)*0.2+MAX(0,MIN(_xlpm.gr,60000)-45000)*0.28+MAX(0,_xlpm.gr-60000)*0.36+K22*Assumptions!$C$41),Assumptions!$D$37*(1+Assumptions!$D$36)^(A22-1)+MAX(0,MIN(K22,25000)-12000)*0.04+MAX(0,MIN(K22,38000)-25000)*0.06+MAX(0,MIN(K22,50000)-38000)*0.08+MAX(0,MIN(K22,65000)-50000)*0.1+MAX(0,MIN(K22,80000)-65000)*0.12+MAX(0,MIN(K22,95000)-80000)*0.14+MAX(0,MIN(K22,110000)-95000)*0.16+MAX(0,K22-110000)*0.23) -> 11149.679 | M22: =IF(Assumptions!$C$39="Investment",(K22-I22-L22)*(1-Assumptions!$C$42),K22-I22-L22) -> 32868.914 | N22: =IF(A22=1,M22,N21+M22) -> 190029.64 | O22: =(H22-$C$10)/$C$10 -> 0.8551308 | P22: =Assumptions!$C$8*(1+Assumptions!$C$9)^A22-Assumptions!$C$8+$C$7*((1+Assumptions!$C$9)^A22-1) -> 56605.726 | Q22: =H22-P22 -> 1359230.1 | R22: =N22/(1+Assumptions!$C$43)^A22 -> 159865.33 | S22: =((H22/$C$10)^(1/A22))/(1+Assumptions!$C$43)-1 -> 0.065651876
A23: =A22+1 -> 8 | B23: =B22+1 -> 40 | C23: =C22-1 -> 85 | D23: =VLOOKUP(C23,'Bala Table'!$A:$B,2,FALSE) -> 0.824 | E23: =E22*(1+Assumptions!$D$34) -> 3640143.9 | F23: =E23*D23 -> 2999478.6 | G23: =IF(A23<=Assumptions!$C$26,PV('Scenario Tables'!D$27/12,(Assumptions!$C$26-A23)*12,-$C$11),0) -> 1462912.9 | H23: =F23-G23 -> 1536565.7 | I23: =IF(A23<=Assumptions!$C$26,G22*'Scenario Tables'!D$27,0) -> 25357.158 | J23: =IF(A23<=Assumptions!$C$26,$C$12-I23,0) -> 54154.487 | K23: =IF(Assumptions!$C$39="Investment",Assumptions!$D$35*12*(1+Assumptions!$D$36)^(A23-1)*(1-Assumptions!$C$40),Assumptions!$D$35*12*(1+Assumptions!$D$36)^(A23-1)) -> 71677.986 | L23: =IF(Assumptions!$C$39="Investment",_xlfn.LET(_xlpm.gr,Assumptions!$D$35*12*(1+Assumptions!$D$36)^(A23-1),Assumptions!$D$37*(1+Assumptions!$D$36)^(A23-1)+MIN(_xlpm.gr,30000)*0.12+MAX(0,MIN(_xlpm.gr,45000)-30000)*0.2+MAX(0,MIN(_xlpm.gr,60000)-45000)*0.28+MAX(0,_xlpm.gr-60000)*0.36+K23*Assumptions!$C$41),Assumptions!$D$37*(1+Assumptions!$D$36)^(A23-1)+MAX(0,MIN(K23,25000)-12000)*0.04+MAX(0,MIN(K23,38000)-25000)*0.06+MAX(0,MIN(K23,50000)-38000)*0.08+MAX(0,MIN(K23,65000)-50000)*0.1+MAX(0,MIN(K23,80000)-65000)*0.12+MAX(0,MIN(K23,95000)-80000)*0.14+MAX(0,MIN(K23,110000)-95000)*0.16+MAX(0,K23-110000)*0.23) -> 11453.472 | M23: =IF(Assumptions!$C$39="Investment",(K23-I23-L23)*(1-Assumptions!$C$42),K23-I23-L23) -> 34867.355 | N23: =IF(A23=1,M23,N22+M23) -> 224896.99 | O23: =(H23-$C$10)/$C$10 -> 1.0133199 | P23: =Assumptions!$C$8*(1+Assumptions!$C$9)^A23-Assumptions!$C$8+$C$7*((1+Assumptions!$C$9)^A23-1) -> 65520.869 | Q23: =H23-P23 -> 1471044.9 | R23: =N23/(1+Assumptions!$C$43)^A23 -> 184583.43 | S23: =((H23/$C$10)^(1/A23))/(1+Assumptions!$C$43)-1 -> 0.06479311
A24: =A23+1 -> 9 | B24: =B23+1 -> 41 | C24: =C23-1 -> 84 | D24: =VLOOKUP(C24,'Bala Table'!$A:$B,2,FALSE) -> 0.818 | E24: =E23*(1+Assumptions!$D$34) -> 3749348.2 | F24: =E24*D24 -> 3066966.9 | G24: =IF(A24<=Assumptions!$C$26,PV('Scenario Tables'!D$27/12,(Assumptions!$C$26-A24)*12,-$C$11),0) -> 1407422.8 | H24: =F24-G24 -> 1659544.1 | I24: =IF(A24<=Assumptions!$C$26,G23*'Scenario Tables'!D$27,0) -> 24445.274 | J24: =IF(A24<=Assumptions!$C$26,$C$12-I24,0) -> 55066.371 | K24: =IF(Assumptions!$C$39="Investment",Assumptions!$D$35*12*(1+Assumptions!$D$36)^(A24-1)*(1-Assumptions!$C$40),Assumptions!$D$35*12*(1+Assumptions!$D$36)^(A24-1)) -> 73111.545 | L24: =IF(Assumptions!$C$39="Investment",_xlfn.LET(_xlpm.gr,Assumptions!$D$35*12*(1+Assumptions!$D$36)^(A24-1),Assumptions!$D$37*(1+Assumptions!$D$36)^(A24-1)+MIN(_xlpm.gr,30000)*0.12+MAX(0,MIN(_xlpm.gr,45000)-30000)*0.2+MAX(0,MIN(_xlpm.gr,60000)-45000)*0.28+MAX(0,_xlpm.gr-60000)*0.36+K24*Assumptions!$C$41),Assumptions!$D$37*(1+Assumptions!$D$36)^(A24-1)+MAX(0,MIN(K24,25000)-12000)*0.04+MAX(0,MIN(K24,38000)-25000)*0.06+MAX(0,MIN(K24,50000)-38000)*0.08+MAX(0,MIN(K24,65000)-50000)*0.1+MAX(0,MIN(K24,80000)-65000)*0.12+MAX(0,MIN(K24,95000)-80000)*0.14+MAX(0,MIN(K24,110000)-95000)*0.16+MAX(0,K24-110000)*0.23) -> 11763.342 | M24: =IF(Assumptions!$C$39="Investment",(K24-I24-L24)*(1-Assumptions!$C$42),K24-I24-L24) -> 36902.93 | N24: =IF(A24=1,M24,N23+M24) -> 261799.92 | O24: =(H24-$C$10)/$C$10 -> 1.174455 | P24: =Assumptions!$C$8*(1+Assumptions!$C$9)^A24-Assumptions!$C$8+$C$7*((1+Assumptions!$C$9)^A24-1) -> 74658.891 | Q24: =H24-P24 -> 1584885.2 | R24: =N24/(1+Assumptions!$C$43)^A24 -> 209630.62 | S24: =((H24/$C$10)^(1/A24))/(1+Assumptions!$C$43)-1 -> 0.063553927
A25: =A24+1 -> 10 | B25: =B24+1 -> 42 | C25: =C24-1 -> 83 | D25: =VLOOKUP(C25,'Bala Table'!$A:$B,2,FALSE) -> 0.812 | E25: =E24*(1+Assumptions!$D$34) -> 3861828.7 | F25: =E25*D25 -> 3135804.9 | G25: =IF(A25<=Assumptions!$C$26,PV('Scenario Tables'!D$27/12,(Assumptions!$C$26-A25)*12,-$C$11),0) -> 1350998.3 | H25: =F25-G25 -> 1784806.6 | I25: =IF(A25<=Assumptions!$C$26,G24*'Scenario Tables'!D$27,0) -> 23518.035 | J25: =IF(A25<=Assumptions!$C$26,$C$12-I25,0) -> 55993.61 | K25: =IF(Assumptions!$C$39="Investment",Assumptions!$D$35*12*(1+Assumptions!$D$36)^(A25-1)*(1-Assumptions!$C$40),Assumptions!$D$35*12*(1+Assumptions!$D$36)^(A25-1)) -> 74573.776 | L25: =IF(Assumptions!$C$39="Investment",_xlfn.LET(_xlpm.gr,Assumptions!$D$35*12*(1+Assumptions!$D$36)^(A25-1),Assumptions!$D$37*(1+Assumptions!$D$36)^(A25-1)+MIN(_xlpm.gr,30000)*0.12+MAX(0,MIN(_xlpm.gr,45000)-30000)*0.2+MAX(0,MIN(_xlpm.gr,60000)-45000)*0.28+MAX(0,_xlpm.gr-60000)*0.36+K25*Assumptions!$C$41),Assumptions!$D$37*(1+Assumptions!$D$36)^(A25-1)+MAX(0,MIN(K25,25000)-12000)*0.04+MAX(0,MIN(K25,38000)-25000)*0.06+MAX(0,MIN(K25,50000)-38000)*0.08+MAX(0,MIN(K25,65000)-50000)*0.1+MAX(0,MIN(K25,80000)-65000)*0.12+MAX(0,MIN(K25,95000)-80000)*0.14+MAX(0,MIN(K25,110000)-95000)*0.16+MAX(0,K25-110000)*0.23) -> 12079.409 | M25: =IF(Assumptions!$C$39="Investment",(K25-I25-L25)*(1-Assumptions!$C$42),K25-I25-L25) -> 38976.333 | N25: =IF(A25=1,M25,N24+M25) -> 300776.25 | O25: =(H25-$C$10)/$C$10 -> 1.338583 | P25: =Assumptions!$C$8*(1+Assumptions!$C$9)^A25-Assumptions!$C$8+$C$7*((1+Assumptions!$C$9)^A25-1) -> 84025.363 | Q25: =H25-P25 -> 1700781.2 | R25: =N25/(1+Assumptions!$C$43)^A25 -> 234965.93 | S25: =((H25/$C$10)^(1/A25))/(1+Assumptions!$C$43)-1 -> 0.062114685
A26: =A25+1 -> 11 | B26: =B25+1 -> 43 | C26: =C25-1 -> 82 | D26: =VLOOKUP(C26,'Bala Table'!$A:$B,2,FALSE) -> 0.806 | E26: =E25*(1+Assumptions!$D$34) -> 3977683.5 | F26: =E26*D26 -> 3206012.9 | G26: =IF(A26<=Assumptions!$C$26,PV('Scenario Tables'!D$27/12,(Assumptions!$C$26-A26)*12,-$C$11),0) -> 1293623.8 | H26: =F26-G26 -> 1912389.2 | I26: =IF(A26<=Assumptions!$C$26,G25*'Scenario Tables'!D$27,0) -> 22575.182 | J26: =IF(A26<=Assumptions!$C$26,$C$12-I26,0) -> 56936.463 | K26: =IF(Assumptions!$C$39="Investment",Assumptions!$D$35*12*(1+Assumptions!$D$36)^(A26-1)*(1-Assumptions!$C$40),Assumptions!$D$35*12*(1+Assumptions!$D$36)^(A26-1)) -> 76065.252 | L26: =IF(Assumptions!$C$39="Investment",_xlfn.LET(_xlpm.gr,Assumptions!$D$35*12*(1+Assumptions!$D$36)^(A26-1),Assumptions!$D$37*(1+Assumptions!$D$36)^(A26-1)+MIN(_xlpm.gr,30000)*0.12+MAX(0,MIN(_xlpm.gr,45000)-30000)*0.2+MAX(0,MIN(_xlpm.gr,60000)-45000)*0.28+MAX(0,_xlpm.gr-60000)*0.36+K26*Assumptions!$C$41),Assumptions!$D$37*(1+Assumptions!$D$36)^(A26-1)+MAX(0,MIN(K26,25000)-12000)*0.04+MAX(0,MIN(K26,38000)-25000)*0.06+MAX(0,MIN(K26,50000)-38000)*0.08+MAX(0,MIN(K26,65000)-50000)*0.1+MAX(0,MIN(K26,80000)-65000)*0.12+MAX(0,MIN(K26,95000)-80000)*0.14+MAX(0,MIN(K26,110000)-95000)*0.16+MAX(0,K26-110000)*0.23) -> 12401.797 | M26: =IF(Assumptions!$C$39="Investment",(K26-I26-L26)*(1-Assumptions!$C$42),K26-I26-L26) -> 41088.273 | N26: =IF(A26=1,M26,N25+M26) -> 341864.53 | O26: =(H26-$C$10)/$C$10 -> 1.505751 | P26: =Assumptions!$C$8*(1+Assumptions!$C$9)^A26-Assumptions!$C$8+$C$7*((1+Assumptions!$C$9)^A26-1) -> 93625.997 | Q26: =H26-P26 -> 1818763.2 | R26: =N26/(1+Assumptions!$C$43)^A26 -> 260550.27 | S26: =((H26/$C$10)^(1/A26))/(1+Assumptions!$C$43)-1 -> 0.060579473
A27: =A26+1 -> 12 | B27: =B26+1 -> 44 | C27: =C26-1 -> 81 | D27: =VLOOKUP(C27,'Bala Table'!$A:$B,2,FALSE) -> 0.8 | E27: =E26*(1+Assumptions!$D$34) -> 4097014 | F27: =E27*D27 -> 3277611.2 | G27: =IF(A27<=Assumptions!$C$26,PV('Scenario Tables'!D$27/12,(Assumptions!$C$26-A27)*12,-$C$11),0) -> 1235283.1 | H27: =F27-G27 -> 2042328.1 | I27: =IF(A27<=Assumptions!$C$26,G26*'Scenario Tables'!D$27,0) -> 21616.453 | J27: =IF(A27<=Assumptions!$C$26,$C$12-I27,0) -> 57895.192 | K27: =IF(Assumptions!$C$39="Investment",Assumptions!$D$35*12*(1+Assumptions!$D$36)^(A27-1)*(1-Assumptions!$C$40),Assumptions!$D$35*12*(1+Assumptions!$D$36)^(A27-1)) -> 77586.557 | L27: =IF(Assumptions!$C$39="Investment",_xlfn.LET(_xlpm.gr,Assumptions!$D$35*12*(1+Assumptions!$D$36)^(A27-1),Assumptions!$D$37*(1+Assumptions!$D$36)^(A27-1)+MIN(_xlpm.gr,30000)*0.12+MAX(0,MIN(_xlpm.gr,45000)-30000)*0.2+MAX(0,MIN(_xlpm.gr,60000)-45000)*0.28+MAX(0,_xlpm.gr-60000)*0.36+K27*Assumptions!$C$41),Assumptions!$D$37*(1+Assumptions!$D$36)^(A27-1)+MAX(0,MIN(K27,25000)-12000)*0.04+MAX(0,MIN(K27,38000)-25000)*0.06+MAX(0,MIN(K27,50000)-38000)*0.08+MAX(0,MIN(K27,65000)-50000)*0.1+MAX(0,MIN(K27,80000)-65000)*0.12+MAX(0,MIN(K27,95000)-80000)*0.14+MAX(0,MIN(K27,110000)-95000)*0.16+MAX(0,K27-110000)*0.23) -> 12730.633 | M27: =IF(Assumptions!$C$39="Investment",(K27-I27-L27)*(1-Assumptions!$C$42),K27-I27-L27) -> 43239.471 | N27: =IF(A27=1,M27,N26+M27) -> 385104 | O27: =(H27-$C$10)/$C$10 -> 1.6760064 | P27: =Assumptions!$C$8*(1+Assumptions!$C$9)^A27-Assumptions!$C$8+$C$7*((1+Assumptions!$C$9)^A27-1) -> 103466.65 | Q27: =H27-P27 -> 1938861.5 | R27: =N27/(1+Assumptions!$C$43)^A27 -> 286346.34 | S27: =((H27/$C$10)^(1/A27))/(1+Assumptions!$C$43)-1 -> 0.059010008
... A35: =A34+1 -> 20 | B35: =B34+1 -> 52 | C35: =C34-1 -> 73 | D35: =VLOOKUP(C35,'Bala Table'!$A:$B,2,FALSE) -> 0.752 | E35: =E34*(1+Assumptions!$D$34) -> 5189974.8 | F35: =E35*D35 -> 3902861.1 | G35: =IF(A35<=Assumptions!$C$26,PV('Scenario Tables'!D$27/12,(Assumptions!$C$26-A35)*12,-$C$11),0) -> 731767.18 | H35: =F35-G35 -> 3171093.9 | I35: =IF(A35<=Assumptions!$C$26,G34*'Scenario Tables'!D$27,0) -> 13342.031 | J35: =IF(A35<=Assumptions!$C$26,$C$12-I35,0) -> 66169.614 | K35: =IF(Assumptions!$C$39="Investment",Assumptions!$D$35*12*(1+Assumptions!$D$36)^(A35-1)*(1-Assumptions!$C$40),Assumptions!$D$35*12*(1+Assumptions!$D$36)^(A35-1)) -> 90905.017 | L35: =IF(Assumptions!$C$39="Investment",_xlfn.LET(_xlpm.gr,Assumptions!$D$35*12*(1+Assumptions!$D$36)^(A35-1),Assumptions!$D$37*(1+Assumptions!$D$36)^(A35-1)+MIN(_xlpm.gr,30000)*0.12+MAX(0,MIN(_xlpm.gr,45000)-30000)*0.2+MAX(0,MIN(_xlpm.gr,60000)-45000)*0.28+MAX(0,_xlpm.gr-60000)*0.36+K35*Assumptions!$C$41),Assumptions!$D$37*(1+Assumptions!$D$36)^(A35-1)+MAX(0,MIN(K35,25000)-12000)*0.04+MAX(0,MIN(K35,38000)-25000)*0.06+MAX(0,MIN(K35,50000)-38000)*0.08+MAX(0,MIN(K35,65000)-50000)*0.1+MAX(0,MIN(K35,80000)-65000)*0.12+MAX(0,MIN(K35,95000)-80000)*0.14+MAX(0,MIN(K35,110000)-95000)*0.16+MAX(0,K35-110000)*0.23) -> 15827.569 | M35: =IF(Assumptions!$C$39="Investment",(K35-I35-L35)*(1-Assumptions!$C$42),K35-I35-L35) -> 61735.416 | N35: =IF(A35=1,M35,N34+M35) -> 812620.85 | O35: =(H35-$C$10)/$C$10 -> 3.1549972 | P35: =Assumptions!$C$8*(1+Assumptions!$C$9)^A35-Assumptions!$C$8+$C$7*((1+Assumptions!$C$9)^A35-1) -> 191584.93 | Q35: =H35-P35 -> 2979508.9 | R35: =N35/(1+Assumptions!$C$43)^A35 -> 495918.9 | S35: =((H35/$C$10)^(1/A35))/(1+Assumptions!$C$43)-1 -> 0.047622148
A37: SUMMARY METRICS
A38: Terminal Property Equity (Year 20) | E38: =H35 -> 3171093.9 | G38: Terminal Loan Balance | I38: =G35 -> 731767.18
A39: Net Equity After CPF Accrued Interest | E39: =Q35 -> 2979508.9 | G39: Total CPF Accrued Interest Owed | I39: =P35 -> 191584.93
A40: ROE on Day-1 Equity (20yr) | E40: =O35 -> 3.1549972 | G40: Annualized ROE (CAGR) | I40: =(H35/$C$10)^(1/20)-1 -> 0.073812702
A41: Cumulative Net Holding Benefit | E41: =N35 -> 812620.85 | G41: Breakeven Year (Equity > Day-1 Outlay) | I41: {=IFERROR(MATCH(TRUE,INDEX(H16:H35>$C$10,0),0),"Never")} -> 2
A42: Real CAGR (Inflation-Adj) | E42: =S35 -> 0.047622148 | G42: Real Cumul. Net Benefit (Year 20) | I42: =R35 -> 495918.9
A43: Inflation Rate Assumed | E43: =Assumptions!$C$43 -> 0.025

Sheet FH Condo
A1: FREEHOLD CONDO — 20-YEAR ANALYSIS
A3: CAPITAL STRUCTURE
A4: Purchase Price | C4: =Assumptions!E31 -> 3900000
A5: Loan Amount (75% LTV) | C5: =Assumptions!C22*Assumptions!E31 -> 2925000
A6: Cash Downpayment | C6: =Assumptions!C23*Assumptions!E31-C7 -> 825000
A7: CPF OA Used | C7: =MIN(Assumptions!C24*Assumptions!E31,Assumptions!C8) -> 150000
A8: Total Upfront Costs | C8: =Assumptions!E51 -> 236200
A9: Total Cash Outlay (Day 1) | C9: =C6+C8 -> 1061200
A10: Total Equity at Risk (Cash + CPF) | C10: =C6+C7+C8 -> 1211200
A11: Monthly Mortgage Payment | C11: =PMT('Scenario Tables'!E$27/12,Assumptions!C26*12,-C5) -> 10336.514
A12: Annual Mortgage Payment | C12: =C11*12 -> 124038.17
A14: Year | B14: Age | C14: Remaining Lease | D14: Bala Factor (%FH) | E14: FH Equiv. Land Value | F14: Market Value | G14: Loan Balance | H14: Property Equity | I14: Annual Interest | J14: Annual Principal | K14: Rent / Imputed Rent (Annual) | L14: Maintenance + Prop Tax (+Mgmt) | M14: Net Holding Benefit (After Tax) | N14: Cumulative Net Benefit | O14: ROE on Equity (%) | P14: CPF Accrued Interest | Q14: Net Equity After CPF | R14: Real Cumul. Net Benefit | S14: Real ROE (CAGR %)
A15: 0 | B15: =Assumptions!C4 -> 32 | C15: Freehold | D15: 1 | E15: =C4 -> 3900000 | F15: =E15*D15 -> 3900000 | G15: =C5 -> 2925000 | H15: =F15-G15 -> 975000 | I15: - | J15: - | K15: - | L15: - | M15: - | N15: - | O15: - | P15: 0 | Q15: =H15-P15 -> 975000 | R15: - | S15: -
A16: =A15+1 -> 1 | B16: =B15+1 -> 33 | C16: Freehold | D16: 1 | E16: =E15*(1+Assumptions!$E$34) -> 4056000 | F16: =E16*D16 -> 4056000 | G16: =IF(A16<=Assumptions!$C$26,PV('Scenario Tables'!E$27/12,(Assumptions!$C$26-A16)*12,-$C$11),0) -> 2849260.3 | H16: =F16-G16 -> 1206739.7 | I16: =IF(A16<=Assumptions!$C$26,G15*'Scenario Tables'!E$27,0) -> 48876.75 | J16: =IF(A16<=Assumptions!$C$26,$C$12-I16,0) -> 75161.416 | K16: =IF(Assumptions!$C$39="Investment",Assumptions!$E$35*12*(1+Assumptions!$E$36)^(A16-1)*(1-Assumptions!$C$40),Assumptions!$E$35*12*(1+Assumptions!$E$36)^(A16-1)) -> 98400 | L16: =IF(Assumptions!$C$39="Investment",_xlfn.LET(_xlpm.gr,Assumptions!$E$35*12*(1+Assumptions!$E$36)^(A16-1),Assumptions!$E$37*(1+Assumptions!$E$36)^(A16-1)+MIN(_xlpm.gr,30000)*0.12+MAX(0,MIN(_xlpm.gr,45000)-30000)*0.2+MAX(0,MIN(_xlpm.gr,60000)-45000)*0.28+MAX(0,_xlpm.gr-60000)*0.36+K16*Assumptions!$C$41),Assumptions!$E$37*(1+Assumptions!$E$36)^(A16-1)+MAX(0,MIN(K16,25000)-12000)*0.04+MAX(0,MIN(K16,38000)-25000)*0.06+MAX(0,MIN(K16,50000)-38000)*0.08+MAX(0,MIN(K16,65000)-50000)*0.1+MAX(0,MIN(K16,80000)-65000)*0.12+MAX(0,MIN(K16,95000)-80000)*0.14+MAX(0,MIN(K16,110000)-95000)*0.16+MAX(0,K16-110000)*0.23) -> 16604 | M16: =IF(Assumptions!$C$39="Investment",(K16-I16-L16)*(1-Assumptions!$C$42),K16-I16-L16) -> 32919.25 | N16: =IF(A16=1,M16,N15+M16) -> 32919.25 | O16: =(H16-$C$10)/$C$10 -> -0.003682514 | P16: =Assumptions!$C$8*(1+Assumptions!$C$9)^A16-Assumptions!$C$8+$C$7*((1+Assumptions!$C$9)^A16-1) -> 7500 | Q16: =H16-P16 -> 1199239.7 | R16: =N16/(1+Assumptions!$C$43)^A16 -> 32116.341 | S16: =((H16/$C$10)^(1/A16))/(1+Assumptions!$C$43)-1 -> -0.027982941
A17: =A16+1 -> 2 | B17: =B16+1 -> 34 | C17: Freehold | D17: 1 | E17: =E16*(1+Assumptions!$E$34) -> 4218240 | F17: =E17*D17 -> 4218240 | G17: =IF(A17<=Assumptions!$C$26,PV('Scenario Tables'!E$27/12,(Assumptions!$C$26-A17)*12,-$C$11),0) -> 2772245.2 | H17: =F17-G17 -> 1445994.8 | I17: =IF(A17<=Assumptions!$C$26,G16*'Scenario Tables'!E$27,0) -> 47611.139 | J17: =IF(A17<=Assumptions!$C$26,$C$12-I17,0) -> 76427.027 | K17: =IF(Assumptions!$C$39="Investment",Assumptions!$E$35*12*(1+Assumptions!$E$36)^(A17-1)*(1-Assumptions!$C$40),Assumptions!$E$35*12*(1+Assumptions!$E$36)^(A17-1)) -> 100368 | L17: =IF(Assumptions!$C$39="Investment",_xlfn.LET(_xlpm.gr,Assumptions!$E$35*12*(1+Assumptions!$E$36)^(A17-1),Assumptions!$E$37*(1+Assumptions!$E$36)^(A17-1)+MIN(_xlpm.gr,30000)*0.12+MAX(0,MIN(_xlpm.gr,45000)-30000)*0.2+MAX(0,MIN(_xlpm.gr,60000)-45000)*0.28+MAX(0,_xlpm.gr-60000)*0.36+K17*Assumptions!$C$41),Assumptions!$E$37*(1+Assumptions!$E$36)^(A17-1)+MAX(0,MIN(K17,25000)-12000)*0.04+MAX(0,MIN(K17,38000)-25000)*0.06+MAX(0,MIN(K17,50000)-38000)*0.08+MAX(0,MIN(K17,65000)-50000)*0.1+MAX(0,MIN(K17,80000)-65000)*0.12+MAX(0,MIN(K17,95000)-80000)*0.14+MAX(0,MIN(K17,110000)-95000)*0.16+MAX(0,K17-110000)*0.23) -> 17086.88 | M17: =IF(Assumptions!$C$39="Investment",(K17-I17-L17)*(1-Assumptions!$C$42),K17-I17-L17) -> 35669.981 | N17: =IF(A17=1,M17,N16+M17) -> 68589.231 | O17: =(H17-$C$10)/$C$10 -> 0.19385306 | P17: =Assumptions!$C$8*(1+Assumptions!$C$9)^A17-Assumptions!$C$8+$C$7*((1+Assumptions!$C$9)^A17-1) -> 15187.5 | Q17: =H17-P17 -> 1430807.3 | R17: =N17/(1+Assumptions!$C$43)^A17 -> 65284.218 | S17: =((H17/$C$10)^(1/A17))/(1+Assumptions!$C$43)-1 -> 0.065986177
A18: =A17+1 -> 3 | B18: =B17+1 -> 35 | C18: Freehold | D18: 1 | E18: =E17*(1+Assumptions!$E$34) -> 4386969.6 | F18: =E18*D18 -> 4386969.6 | G18: =IF(A18<=Assumptions!$C$26,PV('Scenario Tables'!E$27/12,(Assumptions!$C$26-A18)*12,-$C$11),0) -> 2693933.3 | H18: =F18-G18 -> 1693036.3 | I18: =IF(A18<=Assumptions!$C$26,G17*'Scenario Tables'!E$27,0) -> 46324.217 | J18: =IF(A18<=Assumptions!$C$26,$C$12-I18,0) -> 77713.949 | K18: =IF(Assumptions!$C$39="Investment",Assumptions!$E$35*12*(1+Assumptions!$E$36)^(A18-1)*(1-Assumptions!$C$40),Assumptions!$E$35*12*(1+Assumptions!$E$36)^(A18-1)) -> 102375.36 | L18: =IF(Assumptions!$C$39="Investment",_xlfn.LET(_xlpm.gr,Assumptions!$E$35*12*(1+Assumptions!$E$36)^(A18-1),Assumptions!$E$37*(1+Assumptions!$E$36)^(A18-1)+MIN(_xlpm.gr,30000)*0.12+MAX(0,MIN(_xlpm.gr,45000)-30000)*0.2+MAX(0,MIN(_xlpm.gr,60000)-45000)*0.28+MAX(0,_xlpm.gr-60000)*0.36+K18*Assumptions!$C$41),Assumptions!$E$37*(1+Assumptions!$E$36)^(A18-1)+MAX(0,MIN(K18,25000)-12000)*0.04+MAX(0,MIN(K18,38000)-25000)*0.06+MAX(0,MIN(K18,50000)-38000)*0.08+MAX(0,MIN(K18,65000)-50000)*0.1+MAX(0,MIN(K18,80000)-65000)*0.12+MAX(0,MIN(K18,95000)-80000)*0.14+MAX(0,MIN(K18,110000)-95000)*0.16+MAX(0,K18-110000)*0.23) -> 17579.418 | M18: =IF(Assumptions!$C$39="Investment",(K18-I18-L18)*(1-Assumptions!$C$42),K18-I18-L18) -> 38471.726 | N18: =IF(A18=1,M18,N17+M18) -> 107060.96 | O18: =(H18-$C$10)/$C$10 -> 0.39781732 | P18: =Assumptions!$C$8*(1+Assumptions!$C$9)^A18-Assumptions!$C$8+$C$7*((1+Assumptions!$C$9)^A18-1) -> 23067.187 | Q18: =H18-P18 -> 1669969.2 | R18: =N18/(1+Assumptions!$C$43)^A18 -> 99416.741 | S18: =((H18/$C$10)^(1/A18))/(1+Assumptions!$C$43)-1 -> 0.090836364
A19: =A18+1 -> 4 | B19: =B18+1 -> 36 | C19: Freehold | D19: 1 | E19: =E18*(1+Assumptions!$E$34) -> 4562448.4 | F19: =E19*D19 -> 4562448.4 | G19: =IF(A19<=Assumptions!$C$26,PV('Scenario Tables'!E$27/12,(Assumptions!$C$26-A19)*12,-$C$11),0) -> 2614302.7 | H19: =F19-G19 -> 1948145.7 | I19: =IF(A19<=Assumptions!$C$26,G18*'Scenario Tables'!E$27,0) -> 45015.625 | J19: =IF(A19<=Assumptions!$C$26,$C$12-I19,0) -> 79022.541 | K19: =IF(Assumptions!$C$39="Investment",Assumptions!$E$35*12*(1+Assumptions!$E$36)^(A19-1)*(1-Assumptions!$C$40),Assumptions!$E$35*12*(1+Assumptions!$E$36)^(A19-1)) -> 104422.87 | L19: =IF(Assumptions!$C$39="Investment",_xlfn.LET(_xlpm.gr,Assumptions!$E$35*12*(1+Assumptions!$E$36)^(A19-1),Assumptions!$E$37*(1+Assumptions!$E$36)^(A19-1)+MIN(_xlpm.gr,30000)*0.12+MAX(0,MIN(_xlpm.gr,45000)-30000)*0.2+MAX(0,MIN(_xlpm.gr,60000)-45000)*0.28+MAX(0,_xlpm.gr-60000)*0.36+K19*Assumptions!$C$41),Assumptions!$E$37*(1+Assumptions!$E$36)^(A19-1)+MAX(0,MIN(K19,25000)-12000)*0.04+MAX(0,MIN(K19,38000)-25000)*0.06+MAX(0,MIN(K19,50000)-38000)*0.08+MAX(0,MIN(K19,65000)-50000)*0.1+MAX(0,MIN(K19,80000)-65000)*0.12+MAX(0,MIN(K19,95000)-80000)*0.14+MAX(0,MIN(K19,110000)-95000)*0.16+MAX(0,K19-110000)*0.23) -> 18081.806 | M19: =IF(Assumptions!$C$39="Investment",(K19-I19-L19)*(1-Assumptions!$C$42),K19-I19-L19) -> 41325.436 | N19: =IF(A19=1,M19,N18+M19) -> 148386.39 | O19: =(H19-$C$10)/$C$10 -> 0.60844262 | P19: =Assumptions!$C$8*(1+Assumptions!$C$9)^A19-Assumptions!$C$8+$C$7*((1+Assumptions!$C$9)^A19-1) -> 31143.867 | Q19: =H19-P19 -> 1917001.8 | R19: =N19/(1+Assumptions!$C$43)^A19 -> 134430.75 | S19: =((H19/$C$10)^(1/A19))/(1+Assumptions!$C$43)-1 -> 0.09869596
A20: =A19+1 -> 5 | B20: =B19+1 -> 37 | C20: Freehold | D20: 1 | E20: =E19*(1+Assumptions!$E$34) -> 4744946.3 | F20: =E20*D20 -> 4744946.3 | G20: =IF(A20<=Assumptions!$C$26,PV('Scenario Tables'!E$27/12,(Assumptions!$C$26-A20)*12,-$C$11),0) -> 2533331.2 | H20: =F20-G20 -> 2211615.1 | I20: =IF(A20<=Assumptions!$C$26,G19*'Scenario Tables'!E$27,0) -> 43684.998 | J20: =IF(A20<=Assumptions!$C$26,$C$12-I20,0) -> 80353.168 | K20: =IF(Assumptions!$C$39="Investment",Assumptions!$E$35*12*(1+Assumptions!$E$36)^(A20-1)*(1-Assumptions!$C$40),Assumptions!$E$35*12*(1+Assumptions!$E$36)^(A20-1)) -> 106511.32 | L20: =IF(Assumptions!$C$39="Investment",_xlfn.LET(_xlpm.gr,Assumptions!$E$35*12*(1+Assumptions!$E$36)^(A20-1),Assumptions!$E$37*(1+Assumptions!$E$36)^(A20-1)+MIN(_xlpm.gr,30000)*0.12+MAX(0,MIN(_xlpm.gr,45000)-30000)*0.2+MAX(0,MIN(_xlpm.gr,60000)-45000)*0.28+MAX(0,_xlpm.gr-60000)*0.36+K20*Assumptions!$C$41),Assumptions!$E$37*(1+Assumptions!$E$36)^(A20-1)+MAX(0,MIN(K20,25000)-12000)*0.04+MAX(0,MIN(K20,38000)-25000)*0.06+MAX(0,MIN(K20,50000)-38000)*0.08+MAX(0,MIN(K20,65000)-50000)*0.1+MAX(0,MIN(K20,80000)-65000)*0.12+MAX(0,MIN(K20,95000)-80000)*0.14+MAX(0,MIN(K20,110000)-95000)*0.16+MAX(0,K20-110000)*0.23) -> 18594.242 | M20: =IF(Assumptions!$C$39="Investment",(K20-I20-L20)*(1-Assumptions!$C$42),K20-I20-L20) -> 44232.085 | N20: =IF(A20=1,M20,N19+M20) -> 192618.48 | O20: =(H20-$C$10)/$C$10 -> 0.82597017 | P20: =Assumptions!$C$8*(1+Assumptions!$C$9)^A20-Assumptions!$C$8+$C$7*((1+Assumptions!$C$9)^A20-1) -> 39422.464 | Q20: =H20-P20 -> 2172192.6 | R20: =N20/(1+Assumptions!$C$43)^A20 -> 170246.67 | S20: =((H20/$C$10)^(1/A20))/(1+Assumptions!$C$43)-1 -> 0.10046154
A21: =A20+1 -> 6 | B21: =B20+1 -> 38 | C21: Freehold | D21: 1 | E21: =E20*(1+Assumptions!$E$34) -> 4934744.2 | F21: =E21*D21 -> 4934744.2 | G21: =IF(A21<=Assumptions!$C$26,PV('Scenario Tables'!E$27/12,(Assumptions!$C$26-A21)*12,-$C$11),0) -> 2450996.4 | H21: =F21-G21 -> 2483747.8 | I21: =IF(A21<=Assumptions!$C$26,G20*'Scenario Tables'!E$27,0) -> 42331.965 | J21: =IF(A21<=Assumptions!$C$26,$C$12-I21,0) -> 81706.201 | K21: =IF(Assumptions!$C$39="Investment",Assumptions!$E$35*12*(1+Assumptions!$E$36)^(A21-1)*(1-Assumptions!$C$40),Assumptions!$E$35*12*(1+Assumptions!$E$36)^(A21-1)) -> 108641.55 | L21: =IF(Assumptions!$C$39="Investment",_xlfn.LET(_xlpm.gr,Assumptions!$E$35*12*(1+Assumptions!$E$36)^(A21-1),Assumptions!$E$37*(1+Assumptions!$E$36)^(A21-1)+MIN(_xlpm.gr,30000)*0.12+MAX(0,MIN(_xlpm.gr,45000)-30000)*0.2+MAX(0,MIN(_xlpm.gr,60000)-45000)*0.28+MAX(0,_xlpm.gr-60000)*0.36+K21*Assumptions!$C$41),Assumptions!$E$37*(1+Assumptions!$E$36)^(A21-1)+MAX(0,MIN(K21,25000)-12000)*0.04+MAX(0,MIN(K21,38000)-25000)*0.06+MAX(0,MIN(K21,50000)-38000)*0.08+MAX(0,MIN(K21,65000)-50000)*0.1+MAX(0,MIN(K21,80000)-65000)*0.12+MAX(0,MIN(K21,95000)-80000)*0.14+MAX(0,MIN(K21,110000)-95000)*0.16+MAX(0,K21-110000)*0.23) -> 19116.927 | M21: =IF(Assumptions!$C$39="Investment",(K21-I21-L21)*(1-Assumptions!$C$42),K21-I21-L21) -> 47192.659 | N21: =IF(A21=1,M21,N20+M21) -> 239811.14 | O21: =(H21-$C$10)/$C$10 -> 1.0506504 | P21: =Assumptions!$C$8*(1+Assumptions!$C$9)^A21-Assumptions!$C$8+$C$7*((1+Assumptions!$C$9)^A21-1) -> 47908.025 | Q21: =H21-P21 -> 2435839.8 | R21: =N21/(1+Assumptions!$C$43)^A21 -> 206788.39 | S21: =((H21/$C$10)^(1/A21))/(1+Assumptions!$C$43)-1 -> 0.099659103
A22: =A21+1 -> 7 | B22: =B21+1 -> 39 | C22: Freehold | D22: 1 | E22: =E21*(1+Assumptions!$E$34) -> 5132133.9 | F22: =E22*D22 -> 5132133.9 | G22: =IF(A22<=Assumptions!$C$26,PV('Scenario Tables'!E$27/12,(Assumptions!$C$26-A22)*12,-$C$11),0) -> 2367275.1 | H22: =F22-G22 -> 2764858.9 | I22: =IF(A22<=Assumptions!$C$26,G21*'Scenario Tables'!E$27,0) -> 40956.149 | J22: =IF(A22<=Assumptions!$C$26,$C$12-I22,0) -> 83082.017 | K22: =IF(Assumptions!$C$39="Investment",Assumptions!$E$35*12*(1+Assumptions!$E$36)^(A22-1)*(1-Assumptions!$C$40),Assumptions!$E$35*12*(1+Assumptions!$E$36)^(A22-1)) -> 110814.38 | L22: =IF(Assumptions!$C$39="Investment",_xlfn.LET(_xlpm.gr,Assumptions!$E$35*12*(1+Assumptions!$E$36)^(A22-1),Assumptions!$E$37*(1+Assumptions!$E$36)^(A22-1)+MIN(_xlpm.gr,30000)*0.12+MAX(0,MIN(_xlpm.gr,45000)-30000)*0.2+MAX(0,MIN(_xlpm.gr,60000)-45000)*0.28+MAX(0,_xlpm.gr-60000)*0.36+K22*Assumptions!$C$41),Assumptions!$E$37*(1+Assumptions!$E$36)^(A22-1)+MAX(0,MIN(K22,25000)-12000)*0.04+MAX(0,MIN(K22,38000)-25000)*0.06+MAX(0,MIN(K22,50000)-38000)*0.08+MAX(0,MIN(K22,65000)-50000)*0.1+MAX(0,MIN(K22,80000)-65000)*0.12+MAX(0,MIN(K22,95000)-80000)*0.14+MAX(0,MIN(K22,110000)-95000)*0.16+MAX(0,K22-110000)*0.23) -> 19707.072 | M22: =IF(Assumptions!$C$39="Investment",(K22-I22-L22)*(1-Assumptions!$C$42),K22-I22-L22) -> 50151.161 | N22: =IF(A22=1,M22,N21+M22) -> 289962.3 | O22: =(H22-$C$10)/$C$10 -> 1.2827434 | P22: =Assumptions!$C$8*(1+Assumptions!$C$9)^A22-Assumptions!$C$8+$C$7*((1+Assumptions!$C$9)^A22-1) -> 56605.726 | Q22: =H22-P22 -> 2708253.1 | R22: =N22/(1+Assumptions!$C$43)^A22 -> 243935.2 | S22: =((H22/$C$10)^(1/A22))/(1+Assumptions!$C$43)-1 -> 0.097701587
A23: =A22+1 -> 8 | B23: =B22+1 -> 40 | C23: Freehold | D23: 1 | E23: =E22*(1+Assumptions!$E$34) -> 5337419.3 | F23: =E23*D23 -> 5337419.3 | G23: =IF(A23<=Assumptions!$C$26,PV('Scenario Tables'!E$27/12,(Assumptions!$C$26-A23)*12,-$C$11),0) -> 2282144.1 | H23: =F23-G23 -> 3055275.2 | I23: =IF(A23<=Assumptions!$C$26,G22*'Scenario Tables'!E$27,0) -> 39557.167 | J23: =IF(A23<=Assumptions!$C$26,$C$12-I23,0) -> 84481 | K23: =IF(Assumptions!$C$39="Investment",Assumptions!$E$35*12*(1+Assumptions!$E$36)^(A23-1)*(1-Assumptions!$C$40),Assumptions!$E$35*12*(1+Assumptions!$E$36)^(A23-1)) -> 113030.67 | L23: =IF(Assumptions!$C$39="Investment",_xlfn.LET(_xlpm.gr,Assumptions!$E$35*12*(1+Assumptions!$E$36)^(A23-1),Assumptions!$E$37*(1+Assumptions!$E$36)^(A23-1)+MIN(_xlpm.gr,30000)*0.12+MAX(0,MIN(_xlpm.gr,45000)-30000)*0.2+MAX(0,MIN(_xlpm.gr,60000)-45000)*0.28+MAX(0,_xlpm.gr-60000)*0.36+K23*Assumptions!$C$41),Assumptions!$E$37*(1+Assumptions!$E$36)^(A23-1)+MAX(0,MIN(K23,25000)-12000)*0.04+MAX(0,MIN(K23,38000)-25000)*0.06+MAX(0,MIN(K23,50000)-38000)*0.08+MAX(0,MIN(K23,65000)-50000)*0.1+MAX(0,MIN(K23,80000)-65000)*0.12+MAX(0,MIN(K23,95000)-80000)*0.14+MAX(0,MIN(K23,110000)-95000)*0.16+MAX(0,K23-110000)*0.23) -> 20406.014 | M23: =IF(Assumptions!$C$39="Investment",(K23-I23-L23)*(1-Assumptions!$C$42),K23-I23-L23) -> 53067.489 | N23: =IF(A23=1,M23,N22+M23) -> 343029.79 | O23: =(H23-$C$10)/$C$10 -> 1.5225192 | P23: =Assumptions!$C$8*(1+Assumptions!$C$9)^A23-Assumptions!$C$8+$C$7*((1+Assumptions!$C$9)^A23-1) -> 65520.869 | Q23: =H23-P23 -> 2989754.4 | R23: =N23/(1+Assumptions!$C$43)^A23 -> 281540.52 | S23: =((H23/$C$10)^(1/A23))/(1+Assumptions!$C$43)-1 -> 0.095230286
A24: =A23+1 -> 9 | B24: =B23+1 -> 41 | C24: Freehold | D24: 1 | E24: =E23*(1+Assumptions!$E$34) -> 5550916.1 | F24: =E24*D24 -> 5550916.1 | G24: =IF(A24<=Assumptions!$C$26,PV('Scenario Tables'!E$27/12,(Assumptions!$C$26-A24)*12,-$C$11),0) -> 2195579.5 | H24: =F24-G24 -> 3355336.5 | I24: =IF(A24<=Assumptions!$C$26,G23*'Scenario Tables'!E$27,0) -> 38134.627 | J24: =IF(A24<=Assumptions!$C$26,$C$12-I24,0) -> 85903.539 | K24: =IF(Assumptions!$C$39="Investment",Assumptions!$E$35*12*(1+Assumptions!$E$36)^(A24-1)*(1-Assumptions!$C$40),Assumptions!$E$35*12*(1+Assumptions!$E$36)^(A24-1)) -> 115291.28 | L24: =IF(Assumptions!$C$39="Investment",_xlfn.LET(_xlpm.gr,Assumptions!$E$35*12*(1+Assumptions!$E$36)^(A24-1),Assumptions!$E$37*(1+Assumptions!$E$36)^(A24-1)+MIN(_xlpm.gr,30000)*0.12+MAX(0,MIN(_xlpm.gr,45000)-30000)*0.2+MAX(0,MIN(_xlpm.gr,60000)-45000)*0.28+MAX(0,_xlpm.gr-60000)*0.36+K24*Assumptions!$C$41),Assumptions!$E$37*(1+Assumptions!$E$36)^(A24-1)+MAX(0,MIN(K24,25000)-12000)*0.04+MAX(0,MIN(K24,38000)-25000)*0.06+MAX(0,MIN(K24,50000)-38000)*0.08+MAX(0,MIN(K24,65000)-50000)*0.1+MAX(0,MIN(K24,80000)-65000)*0.12+MAX(0,MIN(K24,95000)-80000)*0.14+MAX(0,MIN(K24,110000)-95000)*0.16+MAX(0,K24-110000)*0.23) -> 21118.934 | M24: =IF(Assumptions!$C$39="Investment",(K24-I24-L24)*(1-Assumptions!$C$42),K24-I24-L24) -> 56037.722 | N24: =IF(A24=1,M24,N23+M24) -> 399067.51 | O24: =(H24-$C$10)/$C$10 -> 1.770258 | P24: =Assumptions!$C$8*(1+Assumptions!$C$9)^A24-Assumptions!$C$8+$C$7*((1+Assumptions!$C$9)^A24-1) -> 74658.891 | Q24: =H24-P24 -> 3280677.6 | R24: =N24/(1+Assumptions!$C$43)^A24 -> 319544.67 | S24: =((H24/$C$10)^(1/A24))/(1+Assumptions!$C$43)-1 -> 0.092559376
A25: =A24+1 -> 10 | B25: =B24+1 -> 42 | C25: Freehold | D25: 1 | E25: =E24*(1+Assumptions!$E$34) -> 5772952.7 | F25: =E25*D25 -> 5772952.7 | G25: =IF(A25<=Assumptions!$C$26,PV('Scenario Tables'!E$27/12,(Assumptions!$C$26-A25)*12,-$C$11),0) -> 2107557.4 | H25: =F25-G25 -> 3665395.3 | I25: =IF(A25<=Assumptions!$C$26,G24*'Scenario Tables'!E$27,0) -> 36688.134 | J25: =IF(A25<=Assumptions!$C$26,$C$12-I25,0) -> 87350.032 | K25: =IF(Assumptions!$C$39="Investment",Assumptions!$E$35*12*(1+Assumptions!$E$36)^(A25-1)*(1-Assumptions!$C$40),Assumptions!$E$35*12*(1+Assumptions!$E$36)^(A25-1)) -> 117597.11 | L25: =IF(Assumptions!$C$39="Investment",_xlfn.LET(_xlpm.gr,Assumptions!$E$35*12*(1+Assumptions!$E$36)^(A25-1),Assumptions!$E$37*(1+Assumptions!$E$36)^(A25-1)+MIN(_xlpm.gr,30000)*0.12+MAX(0,MIN(_xlpm.gr,45000)-30000)*0.2+MAX(0,MIN(_xlpm.gr,60000)-45000)*0.28+MAX(0,_xlpm.gr-60000)*0.36+K25*Assumptions!$C$41),Assumptions!$E$37*(1+Assumptions!$E$36)^(A25-1)+MAX(0,MIN(K25,25000)-12000)*0.04+MAX(0,MIN(K25,38000)-25000)*0.06+MAX(0,MIN(K25,50000)-38000)*0.08+MAX(0,MIN(K25,65000)-50000)*0.1+MAX(0,MIN(K25,80000)-65000)*0.12+MAX(0,MIN(K25,95000)-80000)*0.14+MAX(0,MIN(K25,110000)-95000)*0.16+MAX(0,K25-110000)*0.23) -> 21846.113 | M25: =IF(Assumptions!$C$39="Investment",(K25-I25-L25)*(1-Assumptions!$C$42),K25-I25-L25) -> 59062.862 | N25: =IF(A25=1,M25,N24+M25) -> 458130.37 | O25: =(H25-$C$10)/$C$10 -> 2.0262511 | P25: =Assumptions!$C$8*(1+Assumptions!$C$9)^A25-Assumptions!$C$8+$C$7*((1+Assumptions!$C$9)^A25-1) -> 84025.363 | Q25: =H25-P25 -> 3581370 | R25: =N25/(1+Assumptions!$C$43)^A25 -> 357890.71 | S25: =((H25/$C$10)^(1/A25))/(1+Assumptions!$C$43)-1 -> 0.089849754
A26: =A25+1 -> 11 | B26: =B25+1 -> 43 | C26: Freehold | D26: 1 | E26: =E25*(1+Assumptions!$E$34) -> 6003870.8 | F26: =E26*D26 -> 6003870.8 | G26: =IF(A26<=Assumptions!$C$26,PV('Scenario Tables'!E$27/12,(Assumptions!$C$26-A26)*12,-$C$11),0) -> 2018053.1 | H26: =F26-G26 -> 3985817.7 | I26: =IF(A26<=Assumptions!$C$26,G25*'Scenario Tables'!E$27,0) -> 35217.284 | J26: =IF(A26<=Assumptions!$C$26,$C$12-I26,0) -> 88820.882 | K26: =IF(Assumptions!$C$39="Investment",Assumptions!$E$35*12*(1+Assumptions!$E$36)^(A26-1)*(1-Assumptions!$C$40),Assumptions!$E$35*12*(1+Assumptions!$E$36)^(A26-1)) -> 119949.05 | L26: =IF(Assumptions!$C$39="Investment",_xlfn.LET(_xlpm.gr,Assumptions!$E$35*12*(1+Assumptions!$E$36)^(A26-1),Assumptions!$E$37*(1+Assumptions!$E$36)^(A26-1)+MIN(_xlpm.gr,30000)*0.12+MAX(0,MIN(_xlpm.gr,45000)-30000)*0.2+MAX(0,MIN(_xlpm.gr,60000)-45000)*0.28+MAX(0,_xlpm.gr-60000)*0.36+K26*Assumptions!$C$41),Assumptions!$E$37*(1+Assumptions!$E$36)^(A26-1)+MAX(0,MIN(K26,25000)-12000)*0.04+MAX(0,MIN(K26,38000)-25000)*0.06+MAX(0,MIN(K26,50000)-38000)*0.08+MAX(0,MIN(K26,65000)-50000)*0.1+MAX(0,MIN(K26,80000)-65000)*0.12+MAX(0,MIN(K26,95000)-80000)*0.14+MAX(0,MIN(K26,110000)-95000)*0.16+MAX(0,K26-110000)*0.23) -> 22587.835 | M26: =IF(Assumptions!$C$39="Investment",(K26-I26-L26)*(1-Assumptions!$C$42),K26-I26-L26) -> 62143.932 | N26: =IF(A26=1,M26,N25+M26) -> 520274.3 | O26: =(H26-$C$10)/$C$10 -> 2.2908006 | P26: =Assumptions!$C$8*(1+Assumptions!$C$9)^A26-Assumptions!$C$8+$C$7*((1+Assumptions!$C$9)^A26-1) -> 93625.997 | Q26: =H26-P26 -> 3892191.7 | R26: =N26/(1+Assumptions!$C$43)^A26 -> 396524.35 | S26: =((H26/$C$10)^(1/A26))/(1+Assumptions!$C$43)-1 -> 0.087185247
A27: =A26+1 -> 12 | B27: =B26+1 -> 44 | C27: Freehold | D27: 1 | E27: =E26*(1+Assumptions!$E$34) -> 6244025.7 | F27: =E27*D27 -> 6244025.7 | G27: =IF(A27<=Assumptions!$C$26,PV('Scenario Tables'!E$27/12,(Assumptions!$C$26-A27)*12,-$C$11),0) -> 1927041.7 | H27: =F27-G27 -> 4316984 | I27: =IF(A27<=Assumptions!$C$26,G26*'Scenario Tables'!E$27,0) -> 33721.667 | J27: =IF(A27<=Assumptions!$C$26,$C$12-I27,0) -> 90316.499 | K27: =IF(Assumptions!$C$39="Investment",Assumptions!$E$35*12*(1+Assumptions!$E$36)^(A27-1)*(1-Assumptions!$C$40),Assumptions!$E$35*12*(1+Assumptions!$E$36)^(A27-1)) -> 122348.03 | L27: =IF(Assumptions!$C$39="Investment",_xlfn.LET(_xlpm.gr,Assumptions!$E$35*12*(1+Assumptions!$E$36)^(A27-1),Assumptions!$E$37*(1+Assumptions!$E$36)^(A27-1)+MIN(_xlpm.gr,30000)*0.12+MAX(0,MIN(_xlpm.gr,45000)-30000)*0.2+MAX(0,MIN(_xlpm.gr,60000)-45000)*0.28+MAX(0,_xlpm.gr-60000)*0.36+K27*Assumptions!$C$41),Assumptions!$E$37*(1+Assumptions!$E$36)^(A27-1)+MAX(0,MIN(K27,25000)-12000)*0.04+MAX(0,MIN(K27,38000)-25000)*0.06+MAX(0,MIN(K27,50000)-38000)*0.08+MAX(0,MIN(K27,65000)-50000)*0.1+MAX(0,MIN(K27,80000)-65000)*0.12+MAX(0,MIN(K27,95000)-80000)*0.14+MAX(0,MIN(K27,110000)-95000)*0.16+MAX(0,K27-110000)*0.23) -> 23344.392 | M27: =IF(Assumptions!$C$39="Investment",(K27-I27-L27)*(1-Assumptions!$C$42),K27-I27-L27) -> 65281.973 | N27: =IF(A27=1,M27,N26+M27) -> 585556.28 | O27: =(H27-$C$10)/$C$10 -> 2.5642206 | P27: =Assumptions!$C$8*(1+Assumptions!$C$9)^A27-Assumptions!$C$8+$C$7*((1+Assumptions!$C$9)^A27-1) -> 103466.65 | Q27: =H27-P27 -> 4213517.3 | R27: =N27/(1+Assumptions!$C$43)^A27 -> 435393.82 | S27: =((H27/$C$10)^(1/A27))/(1+Assumptions!$C$43)-1 -> 0.084608947
... A35: =A34+1 -> 20 | B35: =B34+1 -> 52 | C35: Freehold | D35: 1 | E35: =E34*(1+Assumptions!$E$34) -> 8545380.3 | F35: =E35*D35 -> 8545380.3 | G35: =IF(A35<=Assumptions!$C$26,PV('Scenario Tables'!E$27/12,(Assumptions!$C$26-A35)*12,-$C$11),0) -> 1141556.8 | H35: =F35-G35 -> 7403823.5 | I35: =IF(A35<=Assumptions!$C$26,G34*'Scenario Tables'!E$27,0) -> 20813.569 | J35: =IF(A35<=Assumptions!$C$26,$C$12-I35,0) -> 103224.6 | K35: =IF(Assumptions!$C$39="Investment",Assumptions!$E$35*12*(1+Assumptions!$E$36)^(A35-1)*(1-Assumptions!$C$40),Assumptions!$E$35*12*(1+Assumptions!$E$36)^(A35-1)) -> 143350.22 | L35: =IF(Assumptions!$C$39="Investment",_xlfn.LET(_xlpm.gr,Assumptions!$E$35*12*(1+Assumptions!$E$36)^(A35-1),Assumptions!$E$37*(1+Assumptions!$E$36)^(A35-1)+MIN(_xlpm.gr,30000)*0.12+MAX(0,MIN(_xlpm.gr,45000)-30000)*0.2+MAX(0,MIN(_xlpm.gr,60000)-45000)*0.28+MAX(0,_xlpm.gr-60000)*0.36+K35*Assumptions!$C$41),Assumptions!$E$37*(1+Assumptions!$E$36)^(A35-1)+MAX(0,MIN(K35,25000)-12000)*0.04+MAX(0,MIN(K35,38000)-25000)*0.06+MAX(0,MIN(K35,50000)-38000)*0.08+MAX(0,MIN(K35,65000)-50000)*0.1+MAX(0,MIN(K35,80000)-65000)*0.12+MAX(0,MIN(K35,95000)-80000)*0.14+MAX(0,MIN(K35,110000)-95000)*0.16+MAX(0,K35-110000)*0.23) -> 29967.764 | M35: =IF(Assumptions!$C$39="Investment",(K35-I35-L35)*(1-Assumptions!$C$42),K35-I35-L35) -> 92568.886 | N35: =IF(A35=1,M35,N34+M35) -> 1227977.7 | O35: =(H35-$C$10)/$C$10 -> 5.1128001 | P35: =Assumptions!$C$8*(1+Assumptions!$C$9)^A35-Assumptions!$C$8+$C$7*((1+Assumptions!$C$9)^A35-1) -> 191584.93 | Q35: =H35-P35 -> 7212238.5 | R35: =N35/(1+Assumptions!$C$43)^A35 -> 749399.09 | S35: =((H35/$C$10)^(1/A35))/(1+Assumptions!$C$43)-1 -> 0.06804154
A37: SUMMARY METRICS
A38: Terminal Property Equity (Year 20) | E38: =H35 -> 7403823.5 | G38: Terminal Loan Balance | I38: =G35 -> 1141556.8
A39: Net Equity After CPF Accrued Interest | E39: =Q35 -> 7212238.5 | G39: Total CPF Accrued Interest Owed | I39: =P35 -> 191584.93
A40: ROE on Day-1 Equity (20yr) | E40: =O35 -> 5.1128001 | G40: Annualized ROE (CAGR) | I40: =(H35/$C$10)^(1/20)-1 -> 0.094742578
A41: Cumulative Net Holding Benefit | E41: =N35 -> 1227977.7 | G41: Breakeven Year (Equity > Day-1 Outlay) | I41: {=IFERROR(MATCH(TRUE,INDEX(H16:H35>$C$10,0),0),"Never")} -> 2
A42: Real CAGR (Inflation-Adj) | E42: =S35 -> 0.06804154 | G42: Real Cumul. Net Benefit (Year 20) | I42: =R35 -> 749399.09
A43: Inflation Rate Assumed | E43: =Assumptions!$C$43 -> 0.025

Sheet FH Landed (Prime)
A1: FH LANDED (PRIME) — 20-YEAR ANALYSIS
A3: CAPITAL STRUCTURE
A4: Purchase Price | C4: =Assumptions!H31 -> 7000000
A5: Loan Amount (75% LTV) | C5: =Assumptions!C22*Assumptions!H31 -> 5250000
A6: Cash Downpayment | C6: =Assumptions!C23*Assumptions!H31-C7 -> 1600000
A7: CPF OA Used | C7: =MIN(Assumptions!C24*Assumptions!H31,Assumptions!C8) -> 150000
A8: Total Upfront Costs | C8: =Assumptions!H51 -> 453200
A9: Total Cash Outlay (Day 1) | C9: =C6+C8 -> 2053200
A10: Total Equity at Risk (Cash + CPF) | C10: =C6+C7+C8 -> 2203200
A11: Monthly Mortgage Payment | C11: =PMT('Scenario Tables'!H$27/12,Assumptions!C26*12,-C5) -> 18552.717
A12: Annual Mortgage Payment | C12: =C11*12 -> 222632.61
A14: Year | B14: Age | C14: Remaining Lease | D14: Bala Factor (%FH) | E14: FH Equiv. Land Value | F14: Market Value | G14: Loan Balance | H14: Property Equity | I14: Annual Interest | J14: Annual Principal | K14: Rent / Imputed Rent (Annual) | L14: Maintenance + Prop Tax (+Mgmt) | M14: Net Holding Benefit (After Tax) | N14: Cumulative Net Benefit | O14: ROE on Equity (%) | P14: CPF Accrued Interest | Q14: Net Equity After CPF | R14: Real Cumul. Net Benefit | S14: Real ROE (CAGR %)
A15: 0 | B15: =Assumptions!C4 -> 32 | C15: Freehold | D15: 1 | E15: =C4 -> 7000000 | F15: =E15*D15 -> 7000000 | G15: =C5 -> 5250000 | H15: =F15-G15 -> 1750000 | I15: - | J15: - | K15: - | L15: - | M15: - | N15: - | O15: - | P15: 0 | Q15: =H15-P15 -> 1750000 | R15: - | S15: -
A16: =A15+1 -> 1 | B16: =B15+1 -> 33 | C16: Freehold | D16: 1 | E16: =E15*(1+Assumptions!$H$34) -> 7350000 | F16: =E16*D16 -> 7350000 | G16: =IF(A16<=Assumptions!$C$26,PV('Scenario Tables'!H$27/12,(Assumptions!$C$26-A16)*12,-$C$11),0) -> 5114056.9 | H16: =F16-G16 -> 2235943.1 | I16: =IF(A16<=Assumptions!$C$26,G15*'Scenario Tables'!H$27,0) -> 87727.5 | J16: =IF(A16<=Assumptions!$C$26,$C$12-I16,0) -> 134905.11 | K16: =IF(Assumptions!$C$39="Investment",Assumptions!$H$35*12*(1+Assumptions!$H$36)^(A16-1)*(1-Assumptions!$C$40),Assumptions!$H$35*12*(1+Assumptions!$H$36)^(A16-1)) -> 180000 | L16: =IF(Assumptions!$C$39="Investment",_xlfn.LET(_xlpm.gr,Assumptions!$H$35*12*(1+Assumptions!$H$36)^(A16-1),Assumptions!$H$37*(1+Assumptions!$H$36)^(A16-1)+MIN(_xlpm.gr,30000)*0.12+MAX(0,MIN(_xlpm.gr,45000)-30000)*0.2+MAX(0,MIN(_xlpm.gr,60000)-45000)*0.28+MAX(0,_xlpm.gr-60000)*0.36+K16*Assumptions!$C$41),Assumptions!$H$37*(1+Assumptions!$H$36)^(A16-1)+MAX(0,MIN(K16,25000)-12000)*0.04+MAX(0,MIN(K16,38000)-25000)*0.06+MAX(0,MIN(K16,50000)-38000)*0.08+MAX(0,MIN(K16,65000)-50000)*0.1+MAX(0,MIN(K16,80000)-65000)*0.12+MAX(0,MIN(K16,95000)-80000)*0.14+MAX(0,MIN(K16,110000)-95000)*0.16+MAX(0,K16-110000)*0.23) -> 44160 | M16: =IF(Assumptions!$C$39="Investment",(K16-I16-L16)*(1-Assumptions!$C$42),K16-I16-L16) -> 48112.5 | N16: =IF(A16=1,M16,N15+M16) -> 48112.5 | O16: =(H16-$C$10)/$C$10 -> 0.01486162 | P16: =Assumptions!$C$8*(1+Assumptions!$C$9)^A16-Assumptions!$C$8+$C$7*((1+Assumptions!$C$9)^A16-1) -> 7500 | Q16: =H16-P16 -> 2228443.1 | R16: =N16/(1+Assumptions!$C$43)^A16 -> 46939.024 | S16: =((H16/$C$10)^(1/A16))/(1+Assumptions!$C$43)-1 -> -0.0098911024
A17: =A16+1 -> 2 | B17: =B16+1 -> 34 | C17: Freehold | D17: 1 | E17: =E16*(1+Assumptions!$H$34) -> 7717500 | F17: =E17*D17 -> 7717500 | G17: =IF(A17<=Assumptions!$C$26,PV('Scenario Tables'!H$27/12,(Assumptions!$C$26-A17)*12,-$C$11),0) -> 4975824.7 | H17: =F17-G17 -> 2741675.3 | I17: =IF(A17<=Assumptions!$C$26,G16*'Scenario Tables'!H$27,0) -> 85455.89 | J17: =IF(A17<=Assumptions!$C$26,$C$12-I17,0) -> 137176.72 | K17: =IF(Assumptions!$C$39="Investment",Assumptions!$H$35*12*(1+Assumptions!$H$36)^(A17-1)*(1-Assumptions!$C$40),Assumptions!$H$35*12*(1+Assumptions!$H$36)^(A17-1)) -> 183600 | L17: =IF(Assumptions!$C$39="Investment",_xlfn.LET(_xlpm.gr,Assumptions!$H$35*12*(1+Assumptions!$H$36)^(A17-1),Assumptions!$H$37*(1+Assumptions!$H$36)^(A17-1)+MIN(_xlpm.gr,30000)*0.12+MAX(0,MIN(_xlpm.gr,45000)-30000)*0.2+MAX(0,MIN(_xlpm.gr,60000)-45000)*0.28+MAX(0,_xlpm.gr-60000)*0.36+K17*Assumptions!$C$41),Assumptions!$H$37*(1+Assumptions!$H$36)^(A17-1)+MAX(0,MIN(K17,25000)-12000)*0.04+MAX(0,MIN(K17,38000)-25000)*0.06+MAX(0,MIN(K17,50000)-38000)*0.08+MAX(0,MIN(K17,65000)-50000)*0.1+MAX(0,MIN(K17,80000)-65000)*0.12+MAX(0,MIN(K17,95000)-80000)*0.14+MAX(0,MIN(K17,110000)-95000)*0.16+MAX(0,K17-110000)*0.23) -> 45348 | M17: =IF(Assumptions!$C$39="Investment",(K17-I17-L17)*(1-Assumptions!$C$42),K17-I17-L17) -> 52796.11 | N17: =IF(A17=1,M17,N16+M17) -> 100908.61 | O17: =(H17-$C$10)/$C$10 -> 0.24440601 | P17: =Assumptions!$C$8*(1+Assumptions!$C$9)^A17-Assumptions!$C$8+$C$7*((1+Assumptions!$C$9)^A17-1) -> 15187.5 | Q17: =H17-P17 -> 2726487.8 | R17: =N17/(1+Assumptions!$C$43)^A17 -> 96046.267 | S17: =((H17/$C$10)^(1/A17))/(1+Assumptions!$C$43)-1 -> 0.088321441
